final class akc$1
  implements Runnable
{
  akc$1(akc paramakc) {}
  
  /* Error */
  public final void run()
  {
    // Byte code:
    //   0: aload_0
    //   1: getfield 17	akc$1:this$0	Lakc;
    //   4: astore_1
    //   5: invokestatic 28	bgp:b	()V
    //   8: aload_1
    //   9: getfield 32	akc:mConversations	Ljava/util/List;
    //   12: astore_2
    //   13: aload_2
    //   14: monitorenter
    //   15: aload_1
    //   16: getfield 32	akc:mConversations	Ljava/util/List;
    //   19: invokestatic 38	java/util/Collections:sort	(Ljava/util/List;)V
    //   22: aload_2
    //   23: monitorexit
    //   24: new 40	akc$2
    //   27: dup
    //   28: aload_1
    //   29: invokespecial 42	akc$2:<init>	(Lakc;)V
    //   32: invokestatic 46	bgp:a	(Ljava/lang/Runnable;)V
    //   35: return
    //   36: astore_3
    //   37: aload_2
    //   38: monitorexit
    //   39: aload_3
    //   40: athrow
    //   41: astore_2
    //   42: ldc 48
    //   44: ldc 50
    //   46: iconst_0
    //   47: anewarray 4	java/lang/Object
    //   50: invokestatic 55	com/snapchat/android/Timber:f	(Ljava/lang/String;Ljava/lang/String;[Ljava/lang/Object;)V
    //   53: goto -29 -> 24
    // Local variable table:
    //   start	length	slot	name	signature
    //   0	56	0	this	1
    //   4	25	1	localakc	akc
    //   41	1	2	localIllegalArgumentException	IllegalArgumentException
    //   36	4	3	localObject	Object
    // Exception table:
    //   from	to	target	type
    //   15	24	36	finally
    //   37	39	36	finally
    //   8	15	41	java/lang/IllegalArgumentException
    //   39	41	41	java/lang/IllegalArgumentException
  }
}

/* Location:
 * Qualified Name:     akc.1
 * Java Class Version: 6 (50.0)
 * JD-Core Version:    0.7.1
 */