import android.content.Context;

public final class bkz$1
  implements Runnable
{
  public bkz$1(bkz parambkz, Context paramContext) {}
  
  /* Error */
  public final void run()
  {
    // Byte code:
    //   0: iconst_0
    //   1: istore_2
    //   2: aload_0
    //   3: getfield 16	bkz$1:b	Lbkz;
    //   6: astore 7
    //   8: aload_0
    //   9: getfield 18	bkz$1:a	Landroid/content/Context;
    //   12: astore 6
    //   14: aload 6
    //   16: ldc 29
    //   18: iconst_0
    //   19: invokevirtual 35	android/content/Context:getSharedPreferences	(Ljava/lang/String;I)Landroid/content/SharedPreferences;
    //   22: astore 9
    //   24: aload 6
    //   26: invokevirtual 39	android/content/Context:getPackageName	()Ljava/lang/String;
    //   29: astore 5
    //   31: aload 5
    //   33: ifnonnull +7 -> 40
    //   36: invokestatic 43	ble:b	()V
    //   39: return
    //   40: aload 6
    //   42: invokestatic 46	bkz:a	(Landroid/content/Context;)I
    //   45: istore_1
    //   46: aload 9
    //   48: ldc 48
    //   50: iconst_m1
    //   51: invokeinterface 54 3 0
    //   56: iload_1
    //   57: if_icmpne +100 -> 157
    //   60: iconst_1
    //   61: istore_1
    //   62: iload_1
    //   63: ifeq +436 -> 499
    //   66: new 56	java/io/File
    //   69: dup
    //   70: ldc 58
    //   72: invokespecial 61	java/io/File:<init>	(Ljava/lang/String;)V
    //   75: invokevirtual 65	java/io/File:exists	()Z
    //   78: ifeq +421 -> 499
    //   81: new 67	blf
    //   84: dup
    //   85: aload 5
    //   87: invokespecial 68	blf:<init>	(Ljava/lang/String;)V
    //   90: astore 8
    //   92: new 70	java/io/FileReader
    //   95: dup
    //   96: ldc 58
    //   98: invokespecial 71	java/io/FileReader:<init>	(Ljava/lang/String;)V
    //   101: astore 6
    //   103: aload 6
    //   105: astore 5
    //   107: aload 8
    //   109: aload 6
    //   111: invokestatic 74	bkz:a	(Lblf;Ljava/io/FileReader;)Lbld;
    //   114: astore 8
    //   116: aload 8
    //   118: ifnonnull +84 -> 202
    //   121: aload 6
    //   123: invokestatic 79	blc:a	(Ljava/io/Closeable;)V
    //   126: return
    //   127: astore 5
    //   129: aload_0
    //   130: getfield 16	bkz$1:b	Lbkz;
    //   133: getfield 82	bkz:b	Ljava/lang/Thread$UncaughtExceptionHandler;
    //   136: ifnull +363 -> 499
    //   139: aload_0
    //   140: getfield 16	bkz$1:b	Lbkz;
    //   143: getfield 82	bkz:b	Ljava/lang/Thread$UncaughtExceptionHandler;
    //   146: invokestatic 88	java/lang/Thread:currentThread	()Ljava/lang/Thread;
    //   149: aload 5
    //   151: invokeinterface 94 3 0
    //   156: return
    //   157: aload 9
    //   159: invokeinterface 98 1 0
    //   164: astore 6
    //   166: aload 6
    //   168: ldc 48
    //   170: iload_1
    //   171: invokeinterface 104 3 0
    //   176: pop
    //   177: aload 6
    //   179: ldc 106
    //   181: invokestatic 112	java/lang/System:currentTimeMillis	()J
    //   184: invokeinterface 116 4 0
    //   189: pop
    //   190: aload 6
    //   192: invokeinterface 119 1 0
    //   197: iconst_0
    //   198: istore_1
    //   199: goto -137 -> 62
    //   202: aload 6
    //   204: astore 5
    //   206: aload 8
    //   208: getfield 124	bld:a	J
    //   211: lstore_3
    //   212: lload_3
    //   213: ldc2_w 125
    //   216: lcmp
    //   217: ifne +15 -> 232
    //   220: iload_2
    //   221: istore_1
    //   222: iload_1
    //   223: ifne +76 -> 299
    //   226: aload 6
    //   228: invokestatic 79	blc:a	(Ljava/io/Closeable;)V
    //   231: return
    //   232: iload_2
    //   233: istore_1
    //   234: aload 6
    //   236: astore 5
    //   238: lload_3
    //   239: aload 9
    //   241: ldc 106
    //   243: ldc2_w 127
    //   246: invokeinterface 132 4 0
    //   251: lcmp
    //   252: ifle -30 -> 222
    //   255: aload 6
    //   257: astore 5
    //   259: aload 9
    //   261: invokeinterface 98 1 0
    //   266: astore 9
    //   268: aload 6
    //   270: astore 5
    //   272: aload 9
    //   274: ldc 106
    //   276: lload_3
    //   277: invokeinterface 116 4 0
    //   282: pop
    //   283: aload 6
    //   285: astore 5
    //   287: aload 9
    //   289: invokeinterface 119 1 0
    //   294: iconst_1
    //   295: istore_1
    //   296: goto -74 -> 222
    //   299: aload 6
    //   301: astore 5
    //   303: aload 7
    //   305: getfield 135	bkz:a	Ljava/util/List;
    //   308: invokeinterface 141 1 0
    //   313: astore 7
    //   315: aload 6
    //   317: astore 5
    //   319: aload 7
    //   321: invokeinterface 146 1 0
    //   326: ifeq +146 -> 472
    //   329: aload 6
    //   331: astore 5
    //   333: aload 7
    //   335: invokeinterface 150 1 0
    //   340: checkcast 152	blb
    //   343: astore 9
    //   345: aload 6
    //   347: astore 5
    //   349: new 154	bla$a
    //   352: dup
    //   353: aload 8
    //   355: getfield 157	bld:b	Ljava/lang/String;
    //   358: invokespecial 158	bla$a:<init>	(Ljava/lang/String;)V
    //   361: astore 10
    //   363: aload 6
    //   365: astore 5
    //   367: new 160	bla
    //   370: dup
    //   371: aload 10
    //   373: getfield 162	bla$a:a	Ljava/lang/String;
    //   376: iconst_0
    //   377: invokespecial 165	bla:<init>	(Ljava/lang/String;B)V
    //   380: astore 11
    //   382: aload 6
    //   384: astore 5
    //   386: aload 10
    //   388: getfield 168	bla$a:b	[Ljava/lang/StackTraceElement;
    //   391: ifnull +17 -> 408
    //   394: aload 6
    //   396: astore 5
    //   398: aload 11
    //   400: aload 10
    //   402: getfield 168	bla$a:b	[Ljava/lang/StackTraceElement;
    //   405: invokevirtual 172	bla:setStackTrace	([Ljava/lang/StackTraceElement;)V
    //   408: aload 6
    //   410: astore 5
    //   412: new 174	java/lang/StringBuilder
    //   415: dup
    //   416: ldc -80
    //   418: invokespecial 177	java/lang/StringBuilder:<init>	(Ljava/lang/String;)V
    //   421: aload 11
    //   423: invokevirtual 181	java/lang/StringBuilder:append	(Ljava/lang/Object;)Ljava/lang/StringBuilder;
    //   426: pop
    //   427: aload 6
    //   429: astore 5
    //   431: invokestatic 183	ble:a	()V
    //   434: aload 6
    //   436: astore 5
    //   438: aload 9
    //   440: aload 8
    //   442: getfield 157	bld:b	Ljava/lang/String;
    //   445: aload 11
    //   447: invokeinterface 186 3 0
    //   452: goto -137 -> 315
    //   455: astore 7
    //   457: aload 6
    //   459: astore 5
    //   461: aload 7
    //   463: invokevirtual 189	java/io/FileNotFoundException:printStackTrace	()V
    //   466: aload 6
    //   468: invokestatic 79	blc:a	(Ljava/io/Closeable;)V
    //   471: return
    //   472: aload 6
    //   474: invokestatic 79	blc:a	(Ljava/io/Closeable;)V
    //   477: return
    //   478: aload 5
    //   480: invokestatic 79	blc:a	(Ljava/io/Closeable;)V
    //   483: aload 6
    //   485: athrow
    //   486: astore 6
    //   488: goto -10 -> 478
    //   491: astore 7
    //   493: aconst_null
    //   494: astore 6
    //   496: goto -39 -> 457
    //   499: return
    //   500: astore 6
    //   502: aconst_null
    //   503: astore 5
    //   505: goto -27 -> 478
    // Local variable table:
    //   start	length	slot	name	signature
    //   0	508	0	this	1
    //   45	251	1	i	int
    //   1	232	2	j	int
    //   211	66	3	l	long
    //   29	77	5	localObject1	Object
    //   127	23	5	localThrowable	Throwable
    //   204	300	5	localObject2	Object
    //   12	472	6	localObject3	Object
    //   486	1	6	localObject4	Object
    //   494	1	6	localObject5	Object
    //   500	1	6	localObject6	Object
    //   6	328	7	localObject7	Object
    //   455	7	7	localFileNotFoundException1	java.io.FileNotFoundException
    //   491	1	7	localFileNotFoundException2	java.io.FileNotFoundException
    //   90	351	8	localObject8	Object
    //   22	417	9	localObject9	Object
    //   361	40	10	locala	bla.a
    //   380	66	11	localbla	bla
    // Exception table:
    //   from	to	target	type
    //   2	31	127	java/lang/Throwable
    //   36	39	127	java/lang/Throwable
    //   40	60	127	java/lang/Throwable
    //   66	92	127	java/lang/Throwable
    //   121	126	127	java/lang/Throwable
    //   157	197	127	java/lang/Throwable
    //   226	231	127	java/lang/Throwable
    //   466	471	127	java/lang/Throwable
    //   472	477	127	java/lang/Throwable
    //   478	486	127	java/lang/Throwable
    //   107	116	455	java/io/FileNotFoundException
    //   206	212	455	java/io/FileNotFoundException
    //   238	255	455	java/io/FileNotFoundException
    //   259	268	455	java/io/FileNotFoundException
    //   272	283	455	java/io/FileNotFoundException
    //   287	294	455	java/io/FileNotFoundException
    //   303	315	455	java/io/FileNotFoundException
    //   319	329	455	java/io/FileNotFoundException
    //   333	345	455	java/io/FileNotFoundException
    //   349	363	455	java/io/FileNotFoundException
    //   367	382	455	java/io/FileNotFoundException
    //   386	394	455	java/io/FileNotFoundException
    //   398	408	455	java/io/FileNotFoundException
    //   412	427	455	java/io/FileNotFoundException
    //   431	434	455	java/io/FileNotFoundException
    //   438	452	455	java/io/FileNotFoundException
    //   107	116	486	finally
    //   206	212	486	finally
    //   238	255	486	finally
    //   259	268	486	finally
    //   272	283	486	finally
    //   287	294	486	finally
    //   303	315	486	finally
    //   319	329	486	finally
    //   333	345	486	finally
    //   349	363	486	finally
    //   367	382	486	finally
    //   386	394	486	finally
    //   398	408	486	finally
    //   412	427	486	finally
    //   431	434	486	finally
    //   438	452	486	finally
    //   461	466	486	finally
    //   92	103	491	java/io/FileNotFoundException
    //   92	103	500	finally
  }
}

/* Location:
 * Qualified Name:     bkz.1
 * Java Class Version: 6 (50.0)
 * JD-Core Version:    0.7.1
 */