import java.io.BufferedReader;
import java.io.InputStreamReader;
import java.net.URLConnection;
import org.json.JSONObject;

public class bsu
  extends bss
{
  private static final String a = bsu.class.getName();
  private bsg b;
  private bsm c;
  private boolean d;
  private bsi e;
  
  public bsu(bsg parambsg, bsm parambsm, bsi parambsi)
  {
    this(parambsg, parambsm, false, parambsi);
  }
  
  public bsu(bsg parambsg, bsm parambsm, boolean paramBoolean, bsi parambsi)
  {
    b = parambsg;
    c = parambsm;
    d = paramBoolean;
    e = parambsi;
  }
  
  private static JSONObject a(URLConnection paramURLConnection)
  {
    StringBuilder localStringBuilder = new StringBuilder();
    paramURLConnection = new BufferedReader(new InputStreamReader(paramURLConnection.getInputStream()));
    for (;;)
    {
      int i = paramURLConnection.read();
      if (i == -1) {
        break;
      }
      localStringBuilder.append((char)i);
    }
    paramURLConnection.close();
    return new JSONObject(localStringBuilder.toString());
  }
  
  /* Error */
  public final void a()
  {
    // Byte code:
    //   0: aconst_null
    //   1: astore 4
    //   3: aload_0
    //   4: getfield 36	bsu:c	Lbsm;
    //   7: astore_3
    //   8: aload_3
    //   9: getfield 92	bsm:a	Ljava/net/URL;
    //   12: invokevirtual 98	java/net/URL:openConnection	()Ljava/net/URLConnection;
    //   15: checkcast 100	java/net/HttpURLConnection
    //   18: astore 5
    //   20: aload_3
    //   21: getfield 103	bsm:b	Ljava/util/Map;
    //   24: invokeinterface 109 1 0
    //   29: invokeinterface 115 1 0
    //   34: astore 6
    //   36: aload 6
    //   38: invokeinterface 121 1 0
    //   43: ifeq +74 -> 117
    //   46: aload 6
    //   48: invokeinterface 125 1 0
    //   53: checkcast 127	java/util/Map$Entry
    //   56: astore 7
    //   58: aload 7
    //   60: invokeinterface 130 1 0
    //   65: checkcast 132	java/util/List
    //   68: invokeinterface 133 1 0
    //   73: astore 8
    //   75: aload 8
    //   77: invokeinterface 121 1 0
    //   82: ifeq -46 -> 36
    //   85: aload 8
    //   87: invokeinterface 125 1 0
    //   92: checkcast 135	java/lang/String
    //   95: astore 9
    //   97: aload 5
    //   99: aload 7
    //   101: invokeinterface 138 1 0
    //   106: checkcast 135	java/lang/String
    //   109: aload 9
    //   111: invokevirtual 142	java/net/HttpURLConnection:addRequestProperty	(Ljava/lang/String;Ljava/lang/String;)V
    //   114: goto -39 -> 75
    //   117: aload 5
    //   119: aload_3
    //   120: getfield 146	bsm:h	I
    //   123: invokevirtual 150	java/net/HttpURLConnection:setConnectTimeout	(I)V
    //   126: aload 5
    //   128: aload_3
    //   129: getfield 146	bsm:h	I
    //   132: invokevirtual 153	java/net/HttpURLConnection:setReadTimeout	(I)V
    //   135: aload 5
    //   137: aload_3
    //   138: getfield 154	bsm:d	Z
    //   141: invokevirtual 158	java/net/HttpURLConnection:setDoInput	(Z)V
    //   144: aload 5
    //   146: aload_3
    //   147: getfield 160	bsm:e	Z
    //   150: invokevirtual 163	java/net/HttpURLConnection:setDoOutput	(Z)V
    //   153: aload_3
    //   154: getfield 166	bsm:g	Z
    //   157: ifeq +12 -> 169
    //   160: aload 5
    //   162: aload_3
    //   163: getfield 168	bsm:c	I
    //   166: invokevirtual 171	java/net/HttpURLConnection:setChunkedStreamingMode	(I)V
    //   169: aload 5
    //   171: aload_3
    //   172: getfield 174	bsm:f	Ljava/lang/String;
    //   175: invokevirtual 177	java/net/HttpURLConnection:setRequestMethod	(Ljava/lang/String;)V
    //   178: aload 5
    //   180: ifnull +243 -> 423
    //   183: aload_0
    //   184: getfield 34	bsu:b	Lbsg;
    //   187: astore_3
    //   188: aload 5
    //   190: invokevirtual 181	java/net/HttpURLConnection:getOutputStream	()Ljava/io/OutputStream;
    //   193: astore 6
    //   195: invokestatic 185	btd:b	()V
    //   198: aload 6
    //   200: new 73	org/json/JSONObject
    //   203: dup
    //   204: aload_3
    //   205: getfield 189	bsg:a	Ljava/util/Map;
    //   208: invokespecial 192	org/json/JSONObject:<init>	(Ljava/util/Map;)V
    //   211: invokevirtual 193	org/json/JSONObject:toString	()Ljava/lang/String;
    //   214: ldc -61
    //   216: invokevirtual 199	java/lang/String:getBytes	(Ljava/lang/String;)[B
    //   219: invokevirtual 205	java/io/OutputStream:write	([B)V
    //   222: aload 5
    //   224: invokevirtual 208	java/net/HttpURLConnection:getResponseCode	()I
    //   227: istore_1
    //   228: aload_0
    //   229: getfield 38	bsu:d	Z
    //   232: ifeq +185 -> 417
    //   235: aload 5
    //   237: invokestatic 210	bsu:a	(Ljava/net/URLConnection;)Lorg/json/JSONObject;
    //   240: astore_3
    //   241: iconst_0
    //   242: istore_2
    //   243: aload 5
    //   245: invokevirtual 213	java/net/HttpURLConnection:disconnect	()V
    //   248: aload_0
    //   249: getfield 40	bsu:e	Lbsi;
    //   252: ifnull +171 -> 423
    //   255: aload_0
    //   256: getfield 40	bsu:e	Lbsi;
    //   259: iload_2
    //   260: iload_1
    //   261: aload_3
    //   262: invokeinterface 218 4 0
    //   267: return
    //   268: astore_3
    //   269: iconst_m1
    //   270: istore_1
    //   271: new 43	java/lang/StringBuilder
    //   274: dup
    //   275: ldc -36
    //   277: invokespecial 221	java/lang/StringBuilder:<init>	(Ljava/lang/String;)V
    //   280: aload_3
    //   281: invokevirtual 224	java/io/UnsupportedEncodingException:getMessage	()Ljava/lang/String;
    //   284: invokevirtual 227	java/lang/StringBuilder:append	(Ljava/lang/String;)Ljava/lang/StringBuilder;
    //   287: pop
    //   288: invokestatic 185	btd:b	()V
    //   291: invokestatic 229	btd:c	()V
    //   294: iconst_0
    //   295: istore_2
    //   296: aload 4
    //   298: astore_3
    //   299: goto -56 -> 243
    //   302: astore_3
    //   303: iconst_m1
    //   304: istore_1
    //   305: new 43	java/lang/StringBuilder
    //   308: dup
    //   309: ldc -25
    //   311: invokespecial 221	java/lang/StringBuilder:<init>	(Ljava/lang/String;)V
    //   314: aload_3
    //   315: invokevirtual 232	java/net/SocketTimeoutException:getMessage	()Ljava/lang/String;
    //   318: invokevirtual 227	java/lang/StringBuilder:append	(Ljava/lang/String;)Ljava/lang/StringBuilder;
    //   321: pop
    //   322: invokestatic 185	btd:b	()V
    //   325: iconst_1
    //   326: istore_2
    //   327: aload 4
    //   329: astore_3
    //   330: goto -87 -> 243
    //   333: astore_3
    //   334: iconst_m1
    //   335: istore_1
    //   336: new 43	java/lang/StringBuilder
    //   339: dup
    //   340: ldc -22
    //   342: invokespecial 221	java/lang/StringBuilder:<init>	(Ljava/lang/String;)V
    //   345: aload_3
    //   346: invokevirtual 235	java/io/IOException:getMessage	()Ljava/lang/String;
    //   349: invokevirtual 227	java/lang/StringBuilder:append	(Ljava/lang/String;)Ljava/lang/StringBuilder;
    //   352: pop
    //   353: invokestatic 185	btd:b	()V
    //   356: invokestatic 229	btd:c	()V
    //   359: iconst_0
    //   360: istore_2
    //   361: aload 4
    //   363: astore_3
    //   364: goto -121 -> 243
    //   367: astore_3
    //   368: iconst_m1
    //   369: istore_1
    //   370: new 43	java/lang/StringBuilder
    //   373: dup
    //   374: ldc -19
    //   376: invokespecial 221	java/lang/StringBuilder:<init>	(Ljava/lang/String;)V
    //   379: aload_3
    //   380: invokevirtual 238	org/json/JSONException:getMessage	()Ljava/lang/String;
    //   383: invokevirtual 227	java/lang/StringBuilder:append	(Ljava/lang/String;)Ljava/lang/StringBuilder;
    //   386: pop
    //   387: invokestatic 185	btd:b	()V
    //   390: iconst_0
    //   391: istore_2
    //   392: invokestatic 229	btd:c	()V
    //   395: aload 4
    //   397: astore_3
    //   398: goto -155 -> 243
    //   401: astore_3
    //   402: goto -32 -> 370
    //   405: astore_3
    //   406: goto -70 -> 336
    //   409: astore_3
    //   410: goto -105 -> 305
    //   413: astore_3
    //   414: goto -143 -> 271
    //   417: aconst_null
    //   418: astore_3
    //   419: goto -178 -> 241
    //   422: astore_3
    //   423: return
    // Local variable table:
    //   start	length	slot	name	signature
    //   0	424	0	this	bsu
    //   227	143	1	i	int
    //   242	150	2	bool	boolean
    //   7	255	3	localObject1	Object
    //   268	13	3	localUnsupportedEncodingException1	java.io.UnsupportedEncodingException
    //   298	1	3	localObject2	Object
    //   302	13	3	localSocketTimeoutException1	java.net.SocketTimeoutException
    //   329	1	3	localObject3	Object
    //   333	13	3	localIOException1	java.io.IOException
    //   363	1	3	localObject4	Object
    //   367	13	3	localJSONException1	org.json.JSONException
    //   397	1	3	localObject5	Object
    //   401	1	3	localJSONException2	org.json.JSONException
    //   405	1	3	localIOException2	java.io.IOException
    //   409	1	3	localSocketTimeoutException2	java.net.SocketTimeoutException
    //   413	1	3	localUnsupportedEncodingException2	java.io.UnsupportedEncodingException
    //   418	1	3	localObject6	Object
    //   422	1	3	localIOException3	java.io.IOException
    //   1	395	4	localObject7	Object
    //   18	226	5	localHttpURLConnection	java.net.HttpURLConnection
    //   34	165	6	localObject8	Object
    //   56	44	7	localEntry	java.util.Map.Entry
    //   73	13	8	localIterator	java.util.Iterator
    //   95	15	9	str	String
    // Exception table:
    //   from	to	target	type
    //   183	228	268	java/io/UnsupportedEncodingException
    //   183	228	302	java/net/SocketTimeoutException
    //   183	228	333	java/io/IOException
    //   183	228	367	org/json/JSONException
    //   228	241	401	org/json/JSONException
    //   228	241	405	java/io/IOException
    //   228	241	409	java/net/SocketTimeoutException
    //   228	241	413	java/io/UnsupportedEncodingException
    //   3	36	422	java/io/IOException
    //   36	75	422	java/io/IOException
    //   75	114	422	java/io/IOException
    //   117	169	422	java/io/IOException
    //   169	178	422	java/io/IOException
  }
}

/* Location:
 * Qualified Name:     bsu
 * Java Class Version: 6 (50.0)
 * JD-Core Version:    0.7.1
 */