import android.os.ConditionVariable;
import java.io.BufferedReader;
import java.io.InputStream;

public final class btu
  extends btt
{
  private BufferedReader a = null;
  private InputStream b = null;
  private ConditionVariable c;
  private Process d;
  private StringBuilder e;
  private int f;
  private boolean g;
  
  public btu(Process paramProcess, ConditionVariable paramConditionVariable, int paramInt)
  {
    c = paramConditionVariable;
    d = paramProcess;
    e = new StringBuilder();
    f = paramInt;
    g = false;
  }
  
  private void c()
  {
    try
    {
      g = true;
      return;
    }
    finally
    {
      localObject = finally;
      throw ((Throwable)localObject);
    }
  }
  
  /* Error */
  public final void a()
  {
    // Byte code:
    //   0: aload_0
    //   1: getfield 40	btu:f	I
    //   4: getstatic 49	btu$a:a	I
    //   7: if_icmpne +112 -> 119
    //   10: aload_0
    //   11: getfield 33	btu:d	Ljava/lang/Process;
    //   14: invokevirtual 55	java/lang/Process:getInputStream	()Ljava/io/InputStream;
    //   17: astore_1
    //   18: aload_0
    //   19: aload_1
    //   20: putfield 29	btu:b	Ljava/io/InputStream;
    //   23: aload_0
    //   24: new 57	java/io/BufferedReader
    //   27: dup
    //   28: new 59	java/io/InputStreamReader
    //   31: dup
    //   32: aload_0
    //   33: getfield 29	btu:b	Ljava/io/InputStream;
    //   36: invokespecial 62	java/io/InputStreamReader:<init>	(Ljava/io/InputStream;)V
    //   39: invokespecial 65	java/io/BufferedReader:<init>	(Ljava/io/Reader;)V
    //   42: putfield 27	btu:a	Ljava/io/BufferedReader;
    //   45: aload_0
    //   46: getfield 27	btu:a	Ljava/io/BufferedReader;
    //   49: invokevirtual 69	java/io/BufferedReader:readLine	()Ljava/lang/String;
    //   52: astore_1
    //   53: aload_1
    //   54: ifnull +27 -> 81
    //   57: aload_0
    //   58: getfield 38	btu:e	Ljava/lang/StringBuilder;
    //   61: aload_1
    //   62: invokevirtual 73	java/lang/StringBuilder:append	(Ljava/lang/String;)Ljava/lang/StringBuilder;
    //   65: bipush 10
    //   67: invokevirtual 76	java/lang/StringBuilder:append	(C)Ljava/lang/StringBuilder;
    //   70: pop
    //   71: goto -26 -> 45
    //   74: astore_1
    //   75: invokestatic 80	bue:b	()V
    //   78: invokestatic 82	bue:c	()V
    //   81: aload_0
    //   82: getfield 27	btu:a	Ljava/io/BufferedReader;
    //   85: invokevirtual 85	java/io/BufferedReader:close	()V
    //   88: aload_0
    //   89: getfield 29	btu:b	Ljava/io/InputStream;
    //   92: invokevirtual 88	java/io/InputStream:close	()V
    //   95: aload_0
    //   96: aconst_null
    //   97: putfield 27	btu:a	Ljava/io/BufferedReader;
    //   100: aload_0
    //   101: invokespecial 89	btu:c	()V
    //   104: aload_0
    //   105: getfield 31	btu:c	Landroid/os/ConditionVariable;
    //   108: ifnull +10 -> 118
    //   111: aload_0
    //   112: getfield 31	btu:c	Landroid/os/ConditionVariable;
    //   115: invokevirtual 94	android/os/ConditionVariable:open	()V
    //   118: return
    //   119: aload_0
    //   120: getfield 33	btu:d	Ljava/lang/Process;
    //   123: invokevirtual 97	java/lang/Process:getErrorStream	()Ljava/io/InputStream;
    //   126: astore_1
    //   127: goto -109 -> 18
    //   130: astore_1
    //   131: new 35	java/lang/StringBuilder
    //   134: dup
    //   135: ldc 99
    //   137: invokespecial 102	java/lang/StringBuilder:<init>	(Ljava/lang/String;)V
    //   140: aload_1
    //   141: invokevirtual 108	java/lang/Object:getClass	()Ljava/lang/Class;
    //   144: invokevirtual 113	java/lang/Class:getName	()Ljava/lang/String;
    //   147: invokevirtual 73	java/lang/StringBuilder:append	(Ljava/lang/String;)Ljava/lang/StringBuilder;
    //   150: pop
    //   151: invokestatic 80	bue:b	()V
    //   154: invokestatic 82	bue:c	()V
    //   157: goto -76 -> 81
    //   160: astore_1
    //   161: invokestatic 80	bue:b	()V
    //   164: invokestatic 82	bue:c	()V
    //   167: goto -79 -> 88
    //   170: astore_1
    //   171: aload_0
    //   172: aconst_null
    //   173: putfield 27	btu:a	Ljava/io/BufferedReader;
    //   176: aload_1
    //   177: athrow
    //   178: astore_1
    //   179: invokestatic 80	bue:b	()V
    //   182: invokestatic 82	bue:c	()V
    //   185: goto -90 -> 95
    // Local variable table:
    //   start	length	slot	name	signature
    //   0	188	0	this	btu
    //   17	45	1	localObject1	Object
    //   74	1	1	localIOException1	java.io.IOException
    //   126	1	1	localInputStream	InputStream
    //   130	11	1	localException	Exception
    //   160	1	1	localIOException2	java.io.IOException
    //   170	7	1	localObject2	Object
    //   178	1	1	localIOException3	java.io.IOException
    // Exception table:
    //   from	to	target	type
    //   0	18	74	java/io/IOException
    //   18	45	74	java/io/IOException
    //   45	53	74	java/io/IOException
    //   57	71	74	java/io/IOException
    //   119	127	74	java/io/IOException
    //   0	18	130	java/lang/Exception
    //   18	45	130	java/lang/Exception
    //   45	53	130	java/lang/Exception
    //   57	71	130	java/lang/Exception
    //   119	127	130	java/lang/Exception
    //   81	88	160	java/io/IOException
    //   81	88	170	finally
    //   88	95	170	finally
    //   161	167	170	finally
    //   179	185	170	finally
    //   88	95	178	java/io/IOException
  }
  
  /* Error */
  public final StringBuilder b()
  {
    // Byte code:
    //   0: aload_0
    //   1: monitorenter
    //   2: aload_0
    //   3: getfield 42	btu:g	Z
    //   6: ifeq +12 -> 18
    //   9: aload_0
    //   10: getfield 38	btu:e	Ljava/lang/StringBuilder;
    //   13: astore_1
    //   14: aload_0
    //   15: monitorexit
    //   16: aload_1
    //   17: areturn
    //   18: aconst_null
    //   19: astore_1
    //   20: goto -6 -> 14
    //   23: astore_1
    //   24: aload_0
    //   25: monitorexit
    //   26: aload_1
    //   27: athrow
    // Local variable table:
    //   start	length	slot	name	signature
    //   0	28	0	this	btu
    //   13	7	1	localStringBuilder	StringBuilder
    //   23	4	1	localObject	Object
    // Exception table:
    //   from	to	target	type
    //   2	14	23	finally
  }
  
  public static enum a {}
}

/* Location:
 * Qualified Name:     btu
 * Java Class Version: 6 (50.0)
 * JD-Core Version:    0.7.1
 */