public final class bwg
{
  /* Error */
  public static bvu a(String paramString)
  {
    // Byte code:
    //   0: aload_0
    //   1: ifnull +752 -> 753
    //   4: new 19	org/json/JSONObject
    //   7: dup
    //   8: aload_0
    //   9: invokespecial 22	org/json/JSONObject:<init>	(Ljava/lang/String;)V
    //   12: astore 9
    //   14: aload 9
    //   16: ldc 24
    //   18: invokevirtual 28	org/json/JSONObject:getJSONObject	(Ljava/lang/String;)Lorg/json/JSONObject;
    //   21: astore 11
    //   23: new 30	bvr
    //   26: dup
    //   27: invokespecial 31	bvr:<init>	()V
    //   30: astore 10
    //   32: aload 11
    //   34: ldc 33
    //   36: invokevirtual 37	org/json/JSONObject:getJSONArray	(Ljava/lang/String;)Lorg/json/JSONArray;
    //   39: astore 12
    //   41: aconst_null
    //   42: astore_0
    //   43: aload 12
    //   45: invokevirtual 43	org/json/JSONArray:length	()I
    //   48: ifle +536 -> 584
    //   51: new 45	java/util/ArrayList
    //   54: dup
    //   55: invokespecial 46	java/util/ArrayList:<init>	()V
    //   58: astore 7
    //   60: iconst_0
    //   61: istore_1
    //   62: aload 7
    //   64: astore_0
    //   65: iload_1
    //   66: aload 12
    //   68: invokevirtual 43	org/json/JSONArray:length	()I
    //   71: if_icmpge +513 -> 584
    //   74: aload 12
    //   76: iload_1
    //   77: invokevirtual 49	org/json/JSONArray:getJSONObject	(I)Lorg/json/JSONObject;
    //   80: ldc 51
    //   82: invokevirtual 55	org/json/JSONObject:getString	(Ljava/lang/String;)Ljava/lang/String;
    //   85: invokevirtual 61	java/lang/String:toString	()Ljava/lang/String;
    //   88: astore 13
    //   90: aload 12
    //   92: iload_1
    //   93: invokevirtual 49	org/json/JSONArray:getJSONObject	(I)Lorg/json/JSONObject;
    //   96: ldc 63
    //   98: invokevirtual 55	org/json/JSONObject:getString	(Ljava/lang/String;)Ljava/lang/String;
    //   101: invokevirtual 61	java/lang/String:toString	()Ljava/lang/String;
    //   104: astore 14
    //   106: aload 12
    //   108: iload_1
    //   109: invokevirtual 49	org/json/JSONArray:getJSONObject	(I)Lorg/json/JSONObject;
    //   112: ldc 65
    //   114: invokevirtual 55	org/json/JSONObject:getString	(Ljava/lang/String;)Ljava/lang/String;
    //   117: invokevirtual 61	java/lang/String:toString	()Ljava/lang/String;
    //   120: astore 15
    //   122: aload 12
    //   124: iload_1
    //   125: invokevirtual 49	org/json/JSONArray:getJSONObject	(I)Lorg/json/JSONObject;
    //   128: ldc 67
    //   130: invokevirtual 55	org/json/JSONObject:getString	(Ljava/lang/String;)Ljava/lang/String;
    //   133: invokevirtual 61	java/lang/String:toString	()Ljava/lang/String;
    //   136: astore 16
    //   138: aload 12
    //   140: iload_1
    //   141: invokevirtual 49	org/json/JSONArray:getJSONObject	(I)Lorg/json/JSONObject;
    //   144: ldc 69
    //   146: invokevirtual 55	org/json/JSONObject:getString	(Ljava/lang/String;)Ljava/lang/String;
    //   149: invokevirtual 61	java/lang/String:toString	()Ljava/lang/String;
    //   152: astore 17
    //   154: aload 12
    //   156: iload_1
    //   157: invokevirtual 49	org/json/JSONArray:getJSONObject	(I)Lorg/json/JSONObject;
    //   160: ldc 71
    //   162: invokevirtual 55	org/json/JSONObject:getString	(Ljava/lang/String;)Ljava/lang/String;
    //   165: invokevirtual 61	java/lang/String:toString	()Ljava/lang/String;
    //   168: astore 18
    //   170: aload 12
    //   172: iload_1
    //   173: invokevirtual 49	org/json/JSONArray:getJSONObject	(I)Lorg/json/JSONObject;
    //   176: ldc 73
    //   178: invokevirtual 77	org/json/JSONObject:getInt	(Ljava/lang/String;)I
    //   181: istore_3
    //   182: aload 12
    //   184: iload_1
    //   185: invokevirtual 49	org/json/JSONArray:getJSONObject	(I)Lorg/json/JSONObject;
    //   188: ldc 79
    //   190: invokevirtual 55	org/json/JSONObject:getString	(Ljava/lang/String;)Ljava/lang/String;
    //   193: invokevirtual 61	java/lang/String:toString	()Ljava/lang/String;
    //   196: astore 19
    //   198: aload 12
    //   200: iload_1
    //   201: invokevirtual 49	org/json/JSONArray:getJSONObject	(I)Lorg/json/JSONObject;
    //   204: ldc 81
    //   206: invokevirtual 77	org/json/JSONObject:getInt	(Ljava/lang/String;)I
    //   209: istore 4
    //   211: aload 12
    //   213: iload_1
    //   214: invokevirtual 49	org/json/JSONArray:getJSONObject	(I)Lorg/json/JSONObject;
    //   217: ldc 83
    //   219: invokevirtual 55	org/json/JSONObject:getString	(Ljava/lang/String;)Ljava/lang/String;
    //   222: invokevirtual 61	java/lang/String:toString	()Ljava/lang/String;
    //   225: astore 20
    //   227: aload 12
    //   229: iload_1
    //   230: invokevirtual 49	org/json/JSONArray:getJSONObject	(I)Lorg/json/JSONObject;
    //   233: ldc 85
    //   235: invokevirtual 55	org/json/JSONObject:getString	(Ljava/lang/String;)Ljava/lang/String;
    //   238: invokevirtual 61	java/lang/String:toString	()Ljava/lang/String;
    //   241: astore 21
    //   243: aload 12
    //   245: iload_1
    //   246: invokevirtual 49	org/json/JSONArray:getJSONObject	(I)Lorg/json/JSONObject;
    //   249: ldc 87
    //   251: invokevirtual 55	org/json/JSONObject:getString	(Ljava/lang/String;)Ljava/lang/String;
    //   254: invokevirtual 61	java/lang/String:toString	()Ljava/lang/String;
    //   257: astore 22
    //   259: aload 12
    //   261: iload_1
    //   262: invokevirtual 49	org/json/JSONArray:getJSONObject	(I)Lorg/json/JSONObject;
    //   265: ldc 89
    //   267: invokevirtual 55	org/json/JSONObject:getString	(Ljava/lang/String;)Ljava/lang/String;
    //   270: invokevirtual 61	java/lang/String:toString	()Ljava/lang/String;
    //   273: astore 23
    //   275: aload 12
    //   277: iload_1
    //   278: invokevirtual 49	org/json/JSONArray:getJSONObject	(I)Lorg/json/JSONObject;
    //   281: ldc 91
    //   283: invokevirtual 94	org/json/JSONObject:optJSONArray	(Ljava/lang/String;)Lorg/json/JSONArray;
    //   286: astore 24
    //   288: invokestatic 100	java/util/Collections:emptyList	()Ljava/util/List;
    //   291: astore_0
    //   292: aload 24
    //   294: ifnull +170 -> 464
    //   297: new 45	java/util/ArrayList
    //   300: dup
    //   301: invokespecial 46	java/util/ArrayList:<init>	()V
    //   304: astore 8
    //   306: iconst_0
    //   307: istore_2
    //   308: aload 8
    //   310: astore_0
    //   311: iload_2
    //   312: aload 24
    //   314: invokevirtual 43	org/json/JSONArray:length	()I
    //   317: if_icmpge +147 -> 464
    //   320: aload 24
    //   322: iload_2
    //   323: invokevirtual 49	org/json/JSONArray:getJSONObject	(I)Lorg/json/JSONObject;
    //   326: ldc 73
    //   328: invokevirtual 77	org/json/JSONObject:getInt	(Ljava/lang/String;)I
    //   331: istore 5
    //   333: aload 24
    //   335: iload_2
    //   336: invokevirtual 49	org/json/JSONArray:getJSONObject	(I)Lorg/json/JSONObject;
    //   339: ldc 102
    //   341: invokevirtual 77	org/json/JSONObject:getInt	(Ljava/lang/String;)I
    //   344: istore 6
    //   346: aload 24
    //   348: iload_2
    //   349: invokevirtual 49	org/json/JSONArray:getJSONObject	(I)Lorg/json/JSONObject;
    //   352: ldc 104
    //   354: invokevirtual 55	org/json/JSONObject:getString	(Ljava/lang/String;)Ljava/lang/String;
    //   357: astore_0
    //   358: aload 24
    //   360: iload_2
    //   361: invokevirtual 49	org/json/JSONArray:getJSONObject	(I)Lorg/json/JSONObject;
    //   364: ldc 106
    //   366: invokevirtual 55	org/json/JSONObject:getString	(Ljava/lang/String;)Ljava/lang/String;
    //   369: astore 25
    //   371: aload 24
    //   373: iload_2
    //   374: invokevirtual 49	org/json/JSONArray:getJSONObject	(I)Lorg/json/JSONObject;
    //   377: ldc 71
    //   379: invokevirtual 55	org/json/JSONObject:getString	(Ljava/lang/String;)Ljava/lang/String;
    //   382: astore 26
    //   384: aload 24
    //   386: iload_2
    //   387: invokevirtual 49	org/json/JSONArray:getJSONObject	(I)Lorg/json/JSONObject;
    //   390: ldc 108
    //   392: invokevirtual 55	org/json/JSONObject:getString	(Ljava/lang/String;)Ljava/lang/String;
    //   395: astore 27
    //   397: new 110	bvs
    //   400: dup
    //   401: invokespecial 111	bvs:<init>	()V
    //   404: astore 28
    //   406: aload 28
    //   408: iload 5
    //   410: putfield 114	bvs:a	I
    //   413: aload 28
    //   415: iload 6
    //   417: putfield 117	bvs:b	I
    //   420: aload 28
    //   422: aload_0
    //   423: putfield 121	bvs:c	Ljava/lang/String;
    //   426: aload 28
    //   428: aload 25
    //   430: putfield 124	bvs:d	Ljava/lang/String;
    //   433: aload 28
    //   435: aload 26
    //   437: putfield 127	bvs:e	Ljava/lang/String;
    //   440: aload 28
    //   442: aload 27
    //   444: putfield 130	bvs:f	Ljava/lang/String;
    //   447: aload 8
    //   449: aload 28
    //   451: invokeinterface 136 2 0
    //   456: pop
    //   457: iload_2
    //   458: iconst_1
    //   459: iadd
    //   460: istore_2
    //   461: goto -153 -> 308
    //   464: new 138	bvt
    //   467: dup
    //   468: invokespecial 139	bvt:<init>	()V
    //   471: astore 8
    //   473: aload 8
    //   475: aload 23
    //   477: putfield 142	bvt:m	Ljava/lang/String;
    //   480: aload 8
    //   482: aload 21
    //   484: putfield 145	bvt:k	Ljava/lang/String;
    //   487: aload 8
    //   489: aload 18
    //   491: putfield 146	bvt:f	Ljava/lang/String;
    //   494: aload 8
    //   496: iload_3
    //   497: putfield 149	bvt:g	I
    //   500: aload 8
    //   502: aload 16
    //   504: putfield 150	bvt:d	Ljava/lang/String;
    //   507: aload 8
    //   509: aload 22
    //   511: putfield 153	bvt:l	Ljava/lang/String;
    //   514: aload 8
    //   516: aload 15
    //   518: putfield 154	bvt:c	Ljava/lang/String;
    //   521: aload 8
    //   523: aload 17
    //   525: putfield 155	bvt:e	Ljava/lang/String;
    //   528: aload 8
    //   530: aload 13
    //   532: putfield 157	bvt:a	Ljava/lang/String;
    //   535: aload 8
    //   537: aload 14
    //   539: putfield 159	bvt:b	Ljava/lang/String;
    //   542: aload 8
    //   544: aload 19
    //   546: putfield 162	bvt:h	Ljava/lang/String;
    //   549: aload 8
    //   551: aload 20
    //   553: putfield 165	bvt:j	Ljava/lang/String;
    //   556: aload 8
    //   558: iload 4
    //   560: putfield 168	bvt:i	I
    //   563: aload 8
    //   565: aload_0
    //   566: putfield 172	bvt:n	Ljava/util/List;
    //   569: aload 7
    //   571: aload 8
    //   573: invokevirtual 173	java/util/ArrayList:add	(Ljava/lang/Object;)Z
    //   576: pop
    //   577: iload_1
    //   578: iconst_1
    //   579: iadd
    //   580: istore_1
    //   581: goto -519 -> 62
    //   584: aload 10
    //   586: aload_0
    //   587: putfield 176	bvr:e	Ljava/util/ArrayList;
    //   590: aload 10
    //   592: aload 11
    //   594: ldc 87
    //   596: invokevirtual 55	org/json/JSONObject:getString	(Ljava/lang/String;)Ljava/lang/String;
    //   599: invokevirtual 61	java/lang/String:toString	()Ljava/lang/String;
    //   602: putfield 177	bvr:a	Ljava/lang/String;
    //   605: aload 10
    //   607: aload 11
    //   609: ldc -77
    //   611: invokevirtual 55	org/json/JSONObject:getString	(Ljava/lang/String;)Ljava/lang/String;
    //   614: invokevirtual 61	java/lang/String:toString	()Ljava/lang/String;
    //   617: putfield 180	bvr:b	Ljava/lang/String;
    //   620: aload 10
    //   622: aload 11
    //   624: ldc 73
    //   626: invokevirtual 77	org/json/JSONObject:getInt	(Ljava/lang/String;)I
    //   629: putfield 182	bvr:c	I
    //   632: aload 10
    //   634: aload 11
    //   636: ldc 71
    //   638: invokevirtual 55	org/json/JSONObject:getString	(Ljava/lang/String;)Ljava/lang/String;
    //   641: invokevirtual 61	java/lang/String:toString	()Ljava/lang/String;
    //   644: putfield 183	bvr:d	Ljava/lang/String;
    //   647: new 185	bvu
    //   650: dup
    //   651: invokespecial 186	bvu:<init>	()V
    //   654: astore_0
    //   655: aload_0
    //   656: aload 10
    //   658: putfield 189	bvu:b	Lbvr;
    //   661: aload_0
    //   662: aload 9
    //   664: ldc -65
    //   666: invokevirtual 55	org/json/JSONObject:getString	(Ljava/lang/String;)Ljava/lang/String;
    //   669: invokevirtual 61	java/lang/String:toString	()Ljava/lang/String;
    //   672: putfield 192	bvu:a	Ljava/lang/String;
    //   675: aload_0
    //   676: aload 9
    //   678: ldc 79
    //   680: invokevirtual 55	org/json/JSONObject:getString	(Ljava/lang/String;)Ljava/lang/String;
    //   683: invokevirtual 61	java/lang/String:toString	()Ljava/lang/String;
    //   686: putfield 193	bvu:c	Ljava/lang/String;
    //   689: aload_0
    //   690: areturn
    //   691: astore_0
    //   692: aload_0
    //   693: invokevirtual 196	org/json/JSONException:printStackTrace	()V
    //   696: goto -91 -> 605
    //   699: astore 7
    //   701: aconst_null
    //   702: astore_0
    //   703: aload 7
    //   705: invokevirtual 196	org/json/JSONException:printStackTrace	()V
    //   708: aload_0
    //   709: areturn
    //   710: astore_0
    //   711: aload_0
    //   712: invokevirtual 196	org/json/JSONException:printStackTrace	()V
    //   715: goto -95 -> 620
    //   718: astore_0
    //   719: aload_0
    //   720: invokevirtual 196	org/json/JSONException:printStackTrace	()V
    //   723: goto -91 -> 632
    //   726: astore_0
    //   727: aload_0
    //   728: invokevirtual 196	org/json/JSONException:printStackTrace	()V
    //   731: goto -84 -> 647
    //   734: astore 7
    //   736: aload 7
    //   738: invokevirtual 196	org/json/JSONException:printStackTrace	()V
    //   741: goto -66 -> 675
    //   744: astore 7
    //   746: aload 7
    //   748: invokevirtual 196	org/json/JSONException:printStackTrace	()V
    //   751: aload_0
    //   752: areturn
    //   753: aconst_null
    //   754: areturn
    //   755: astore 7
    //   757: goto -54 -> 703
    // Local variable table:
    //   start	length	slot	name	signature
    //   0	760	0	paramString	String
    //   61	520	1	i	int
    //   307	154	2	j	int
    //   181	316	3	k	int
    //   209	350	4	m	int
    //   331	78	5	n	int
    //   344	72	6	i1	int
    //   58	512	7	localArrayList	java.util.ArrayList
    //   699	5	7	localJSONException1	org.json.JSONException
    //   734	3	7	localJSONException2	org.json.JSONException
    //   744	3	7	localJSONException3	org.json.JSONException
    //   755	1	7	localJSONException4	org.json.JSONException
    //   304	268	8	localObject	Object
    //   12	665	9	localJSONObject1	org.json.JSONObject
    //   30	627	10	localbvr	bvr
    //   21	614	11	localJSONObject2	org.json.JSONObject
    //   39	237	12	localJSONArray1	org.json.JSONArray
    //   88	443	13	str1	String
    //   104	434	14	str2	String
    //   120	397	15	str3	String
    //   136	367	16	str4	String
    //   152	372	17	str5	String
    //   168	322	18	str6	String
    //   196	349	19	str7	String
    //   225	327	20	str8	String
    //   241	242	21	str9	String
    //   257	253	22	str10	String
    //   273	203	23	str11	String
    //   286	99	24	localJSONArray2	org.json.JSONArray
    //   369	60	25	str12	String
    //   382	54	26	str13	String
    //   395	48	27	str14	String
    //   404	46	28	localbvs	bvs
    // Exception table:
    //   from	to	target	type
    //   590	605	691	org/json/JSONException
    //   4	41	699	org/json/JSONException
    //   43	60	699	org/json/JSONException
    //   65	292	699	org/json/JSONException
    //   297	306	699	org/json/JSONException
    //   311	457	699	org/json/JSONException
    //   464	577	699	org/json/JSONException
    //   584	590	699	org/json/JSONException
    //   647	655	699	org/json/JSONException
    //   692	696	699	org/json/JSONException
    //   711	715	699	org/json/JSONException
    //   719	723	699	org/json/JSONException
    //   727	731	699	org/json/JSONException
    //   605	620	710	org/json/JSONException
    //   620	632	718	org/json/JSONException
    //   632	647	726	org/json/JSONException
    //   661	675	734	org/json/JSONException
    //   675	689	744	org/json/JSONException
    //   655	661	755	org/json/JSONException
    //   736	741	755	org/json/JSONException
    //   746	751	755	org/json/JSONException
  }
  
  public static final class a
  {
    public static final bwg a = new bwg((byte)0);
  }
}

/* Location:
 * Qualified Name:     bwg
 * Java Class Version: 6 (50.0)
 * JD-Core Version:    0.7.1
 */