public final class byu
  implements bxg
{
  /* Error */
  public final bxk a(bwz parambwz, String paramString)
  {
    // Byte code:
    //   0: aload_2
    //   1: invokestatic 23	bxj:d	(Ljava/lang/String;)Ljava/util/ArrayList;
    //   4: astore_2
    //   5: aload_2
    //   6: invokevirtual 29	java/util/ArrayList:size	()I
    //   9: iconst_3
    //   10: if_icmpeq +13 -> 23
    //   13: new 15	bxh
    //   16: dup
    //   17: ldc 31
    //   19: invokespecial 34	bxh:<init>	(Ljava/lang/String;)V
    //   22: athrow
    //   23: aload_2
    //   24: iconst_0
    //   25: invokevirtual 38	java/util/ArrayList:get	(I)Ljava/lang/Object;
    //   28: checkcast 40	java/lang/String
    //   31: aload_1
    //   32: getfield 45	bwz:a	C
    //   35: invokestatic 48	bxj:a	(Ljava/lang/String;C)Ljava/lang/String;
    //   38: aload_2
    //   39: iconst_1
    //   40: invokevirtual 38	java/util/ArrayList:get	(I)Ljava/lang/Object;
    //   43: checkcast 40	java/lang/String
    //   46: aload_1
    //   47: getfield 45	bwz:a	C
    //   50: invokestatic 48	bxj:a	(Ljava/lang/String;C)Ljava/lang/String;
    //   53: aload_2
    //   54: iconst_2
    //   55: invokevirtual 38	java/util/ArrayList:get	(I)Ljava/lang/Object;
    //   58: checkcast 50	java/lang/Integer
    //   61: invokevirtual 53	java/lang/Integer:intValue	()I
    //   64: invokevirtual 57	java/lang/String:startsWith	(Ljava/lang/String;I)Z
    //   67: ifeq +16 -> 83
    //   70: ldc 59
    //   72: astore_1
    //   73: new 61	bxk
    //   76: dup
    //   77: aload_1
    //   78: iconst_0
    //   79: invokespecial 64	bxk:<init>	(Ljava/lang/String;I)V
    //   82: areturn
    //   83: ldc 66
    //   85: astore_1
    //   86: goto -13 -> 73
    //   89: astore_1
    //   90: new 15	bxh
    //   93: dup
    //   94: aload_1
    //   95: invokevirtual 70	bxh:getMessage	()Ljava/lang/String;
    //   98: aload_1
    //   99: invokespecial 73	bxh:<init>	(Ljava/lang/String;Ljava/lang/Exception;)V
    //   102: athrow
    //   103: astore_1
    //   104: new 15	bxh
    //   107: dup
    //   108: ldc 31
    //   110: aload_1
    //   111: invokespecial 73	bxh:<init>	(Ljava/lang/String;Ljava/lang/Exception;)V
    //   114: athrow
    // Local variable table:
    //   start	length	slot	name	signature
    //   0	115	0	this	byu
    //   0	115	1	parambwz	bwz
    //   0	115	2	paramString	String
    // Exception table:
    //   from	to	target	type
    //   23	70	89	bxh
    //   23	70	103	java/lang/Exception
  }
  
  public final String a()
  {
    return "startsWith";
  }
}

/* Location:
 * Qualified Name:     byu
 * Java Class Version: 6 (50.0)
 * JD-Core Version:    0.7.1
 */