import java.io.IOException;
import java.io.InputStream;
import java.util.Collections;
import java.util.HashMap;
import java.util.HashSet;
import java.util.Map;
import java.util.Set;
import java.util.logging.Level;
import java.util.logging.Logger;

class el
{
  private static final Logger a = Logger.getLogger(el.class.getName());
  private static final Map<Integer, eq.b> b = Collections.synchronizedMap(new HashMap());
  private static final Map<String, eq.b> c = Collections.synchronizedMap(new HashMap());
  private static final Set<Integer> d;
  private static final Set<String> e;
  
  static
  {
    HashSet localHashSet = new HashSet(57);
    localHashSet.add(Integer.valueOf(7));
    localHashSet.add(Integer.valueOf(27));
    localHashSet.add(Integer.valueOf(30));
    localHashSet.add(Integer.valueOf(31));
    localHashSet.add(Integer.valueOf(34));
    localHashSet.add(Integer.valueOf(36));
    localHashSet.add(Integer.valueOf(43));
    localHashSet.add(Integer.valueOf(44));
    localHashSet.add(Integer.valueOf(49));
    localHashSet.add(Integer.valueOf(54));
    localHashSet.add(Integer.valueOf(55));
    localHashSet.add(Integer.valueOf(58));
    localHashSet.add(Integer.valueOf(61));
    localHashSet.add(Integer.valueOf(62));
    localHashSet.add(Integer.valueOf(63));
    localHashSet.add(Integer.valueOf(66));
    localHashSet.add(Integer.valueOf(81));
    localHashSet.add(Integer.valueOf(84));
    localHashSet.add(Integer.valueOf(90));
    localHashSet.add(Integer.valueOf(91));
    localHashSet.add(Integer.valueOf(94));
    localHashSet.add(Integer.valueOf(95));
    localHashSet.add(Integer.valueOf(255));
    localHashSet.add(Integer.valueOf(350));
    localHashSet.add(Integer.valueOf(351));
    localHashSet.add(Integer.valueOf(352));
    localHashSet.add(Integer.valueOf(358));
    localHashSet.add(Integer.valueOf(359));
    localHashSet.add(Integer.valueOf(372));
    localHashSet.add(Integer.valueOf(373));
    localHashSet.add(Integer.valueOf(380));
    localHashSet.add(Integer.valueOf(381));
    localHashSet.add(Integer.valueOf(385));
    localHashSet.add(Integer.valueOf(505));
    localHashSet.add(Integer.valueOf(506));
    localHashSet.add(Integer.valueOf(595));
    localHashSet.add(Integer.valueOf(675));
    localHashSet.add(Integer.valueOf(676));
    localHashSet.add(Integer.valueOf(679));
    localHashSet.add(Integer.valueOf(855));
    localHashSet.add(Integer.valueOf(971));
    localHashSet.add(Integer.valueOf(972));
    localHashSet.add(Integer.valueOf(995));
    d = localHashSet;
    localHashSet = new HashSet(309);
    localHashSet.add("AC");
    localHashSet.add("AD");
    localHashSet.add("AE");
    localHashSet.add("AF");
    localHashSet.add("AG");
    localHashSet.add("AI");
    localHashSet.add("AL");
    localHashSet.add("AM");
    localHashSet.add("AO");
    localHashSet.add("AR");
    localHashSet.add("AS");
    localHashSet.add("AT");
    localHashSet.add("AU");
    localHashSet.add("AW");
    localHashSet.add("AX");
    localHashSet.add("AZ");
    localHashSet.add("BA");
    localHashSet.add("BB");
    localHashSet.add("BD");
    localHashSet.add("BE");
    localHashSet.add("BF");
    localHashSet.add("BG");
    localHashSet.add("BH");
    localHashSet.add("BI");
    localHashSet.add("BJ");
    localHashSet.add("BL");
    localHashSet.add("BM");
    localHashSet.add("BN");
    localHashSet.add("BO");
    localHashSet.add("BQ");
    localHashSet.add("BR");
    localHashSet.add("BS");
    localHashSet.add("BT");
    localHashSet.add("BW");
    localHashSet.add("BY");
    localHashSet.add("BZ");
    localHashSet.add("CA");
    localHashSet.add("CC");
    localHashSet.add("CD");
    localHashSet.add("CH");
    localHashSet.add("CI");
    localHashSet.add("CK");
    localHashSet.add("CL");
    localHashSet.add("CM");
    localHashSet.add("CN");
    localHashSet.add("CO");
    localHashSet.add("CR");
    localHashSet.add("CU");
    localHashSet.add("CV");
    localHashSet.add("CW");
    localHashSet.add("CX");
    localHashSet.add("CY");
    localHashSet.add("CZ");
    localHashSet.add("DE");
    localHashSet.add("DJ");
    localHashSet.add("DK");
    localHashSet.add("DM");
    localHashSet.add("DO");
    localHashSet.add("DZ");
    localHashSet.add("EC");
    localHashSet.add("EE");
    localHashSet.add("EG");
    localHashSet.add("EH");
    localHashSet.add("ES");
    localHashSet.add("ET");
    localHashSet.add("FI");
    localHashSet.add("FJ");
    localHashSet.add("FK");
    localHashSet.add("FM");
    localHashSet.add("FO");
    localHashSet.add("FR");
    localHashSet.add("GA");
    localHashSet.add("GB");
    localHashSet.add("GD");
    localHashSet.add("GE");
    localHashSet.add("GF");
    localHashSet.add("GG");
    localHashSet.add("GH");
    localHashSet.add("GI");
    localHashSet.add("GL");
    localHashSet.add("GM");
    localHashSet.add("GN");
    localHashSet.add("GP");
    localHashSet.add("GR");
    localHashSet.add("GT");
    localHashSet.add("GU");
    localHashSet.add("GW");
    localHashSet.add("GY");
    localHashSet.add("HK");
    localHashSet.add("HN");
    localHashSet.add("HR");
    localHashSet.add("HT");
    localHashSet.add("HU");
    localHashSet.add("ID");
    localHashSet.add("IE");
    localHashSet.add("IL");
    localHashSet.add("IM");
    localHashSet.add("IN");
    localHashSet.add("IQ");
    localHashSet.add("IR");
    localHashSet.add("IS");
    localHashSet.add("IT");
    localHashSet.add("JE");
    localHashSet.add("JM");
    localHashSet.add("JO");
    localHashSet.add("JP");
    localHashSet.add("KE");
    localHashSet.add("KG");
    localHashSet.add("KH");
    localHashSet.add("KI");
    localHashSet.add("KM");
    localHashSet.add("KN");
    localHashSet.add("KR");
    localHashSet.add("KW");
    localHashSet.add("KY");
    localHashSet.add("KZ");
    localHashSet.add("LA");
    localHashSet.add("LB");
    localHashSet.add("LC");
    localHashSet.add("LI");
    localHashSet.add("LK");
    localHashSet.add("LR");
    localHashSet.add("LS");
    localHashSet.add("LT");
    localHashSet.add("LU");
    localHashSet.add("LV");
    localHashSet.add("LY");
    localHashSet.add("MA");
    localHashSet.add("MC");
    localHashSet.add("MD");
    localHashSet.add("ME");
    localHashSet.add("MF");
    localHashSet.add("MG");
    localHashSet.add("MH");
    localHashSet.add("MK");
    localHashSet.add("ML");
    localHashSet.add("MM");
    localHashSet.add("MN");
    localHashSet.add("MO");
    localHashSet.add("MP");
    localHashSet.add("MQ");
    localHashSet.add("MR");
    localHashSet.add("MS");
    localHashSet.add("MT");
    localHashSet.add("MU");
    localHashSet.add("MV");
    localHashSet.add("MW");
    localHashSet.add("MX");
    localHashSet.add("MY");
    localHashSet.add("MZ");
    localHashSet.add("NA");
    localHashSet.add("NC");
    localHashSet.add("NF");
    localHashSet.add("NG");
    localHashSet.add("NI");
    localHashSet.add("NL");
    localHashSet.add("NO");
    localHashSet.add("NP");
    localHashSet.add("NR");
    localHashSet.add("NU");
    localHashSet.add("NZ");
    localHashSet.add("OM");
    localHashSet.add("PA");
    localHashSet.add("PE");
    localHashSet.add("PF");
    localHashSet.add("PG");
    localHashSet.add("PH");
    localHashSet.add("PK");
    localHashSet.add("PL");
    localHashSet.add("PM");
    localHashSet.add("PR");
    localHashSet.add("PT");
    localHashSet.add("PW");
    localHashSet.add("PY");
    localHashSet.add("QA");
    localHashSet.add("RE");
    localHashSet.add("RO");
    localHashSet.add("RS");
    localHashSet.add("RU");
    localHashSet.add("RW");
    localHashSet.add("SA");
    localHashSet.add("SB");
    localHashSet.add("SC");
    localHashSet.add("SD");
    localHashSet.add("SE");
    localHashSet.add("SG");
    localHashSet.add("SH");
    localHashSet.add("SI");
    localHashSet.add("SJ");
    localHashSet.add("SK");
    localHashSet.add("SL");
    localHashSet.add("SM");
    localHashSet.add("SN");
    localHashSet.add("SR");
    localHashSet.add("ST");
    localHashSet.add("SV");
    localHashSet.add("SX");
    localHashSet.add("SY");
    localHashSet.add("SZ");
    localHashSet.add("TC");
    localHashSet.add("TD");
    localHashSet.add("TG");
    localHashSet.add("TH");
    localHashSet.add("TJ");
    localHashSet.add("TL");
    localHashSet.add("TM");
    localHashSet.add("TN");
    localHashSet.add("TO");
    localHashSet.add("TR");
    localHashSet.add("TT");
    localHashSet.add("TV");
    localHashSet.add("TW");
    localHashSet.add("TZ");
    localHashSet.add("UA");
    localHashSet.add("UG");
    localHashSet.add("US");
    localHashSet.add("UY");
    localHashSet.add("UZ");
    localHashSet.add("VA");
    localHashSet.add("VC");
    localHashSet.add("VE");
    localHashSet.add("VG");
    localHashSet.add("VI");
    localHashSet.add("VN");
    localHashSet.add("VU");
    localHashSet.add("WF");
    localHashSet.add("WS");
    localHashSet.add("YE");
    localHashSet.add("YT");
    localHashSet.add("ZA");
    localHashSet.add("ZM");
    localHashSet.add("ZW");
    e = localHashSet;
  }
  
  /* Error */
  static eq.b a(int paramInt)
  {
    // Byte code:
    //   0: getstatic 66	el:d	Ljava/util/Set;
    //   3: iload_0
    //   4: invokestatic 58	java/lang/Integer:valueOf	(I)Ljava/lang/Integer;
    //   7: invokeinterface 540 2 0
    //   12: ifne +5 -> 17
    //   15: aconst_null
    //   16: areturn
    //   17: getstatic 45	el:b	Ljava/util/Map;
    //   20: astore 4
    //   22: aload 4
    //   24: monitorenter
    //   25: getstatic 45	el:b	Ljava/util/Map;
    //   28: iload_0
    //   29: invokestatic 58	java/lang/Integer:valueOf	(I)Ljava/lang/Integer;
    //   32: invokeinterface 545 2 0
    //   37: ifne +151 -> 188
    //   40: ldc_w 547
    //   43: invokestatic 552	java/lang/String:valueOf	(Ljava/lang/Object;)Ljava/lang/String;
    //   46: invokestatic 552	java/lang/String:valueOf	(Ljava/lang/Object;)Ljava/lang/String;
    //   49: astore_1
    //   50: ldc_w 554
    //   53: new 556	java/lang/StringBuilder
    //   56: dup
    //   57: aload_1
    //   58: invokevirtual 560	java/lang/String:length	()I
    //   61: bipush 11
    //   63: iadd
    //   64: invokespecial 561	java/lang/StringBuilder:<init>	(I)V
    //   67: aload_1
    //   68: invokevirtual 565	java/lang/StringBuilder:append	(Ljava/lang/String;)Ljava/lang/StringBuilder;
    //   71: iload_0
    //   72: invokevirtual 568	java/lang/StringBuilder:append	(I)Ljava/lang/StringBuilder;
    //   75: invokevirtual 571	java/lang/StringBuilder:toString	()Ljava/lang/String;
    //   78: invokevirtual 575	java/lang/Class:getResourceAsStream	(Ljava/lang/String;)Ljava/io/InputStream;
    //   81: astore_1
    //   82: new 577	java/io/ObjectInputStream
    //   85: dup
    //   86: aload_1
    //   87: invokespecial 580	java/io/ObjectInputStream:<init>	(Ljava/io/InputStream;)V
    //   90: astore_2
    //   91: aload_2
    //   92: astore_1
    //   93: new 582	eq$c
    //   96: dup
    //   97: invokespecial 583	eq$c:<init>	()V
    //   100: astore_3
    //   101: aload_2
    //   102: astore_1
    //   103: aload_3
    //   104: aload_2
    //   105: invokevirtual 587	eq$c:readExternal	(Ljava/io/ObjectInput;)V
    //   108: aload_2
    //   109: astore_1
    //   110: aload_3
    //   111: getfield 590	eq$c:a	Ljava/util/List;
    //   114: invokeinterface 596 1 0
    //   119: astore_3
    //   120: aload_2
    //   121: astore_1
    //   122: aload_3
    //   123: invokeinterface 602 1 0
    //   128: ifeq +79 -> 207
    //   131: aload_2
    //   132: astore_1
    //   133: aload_3
    //   134: invokeinterface 606 1 0
    //   139: checkcast 608	eq$b
    //   142: astore 5
    //   144: aload_2
    //   145: astore_1
    //   146: getstatic 45	el:b	Ljava/util/Map;
    //   149: aload 5
    //   151: getfield 612	eq$b:l	I
    //   154: invokestatic 58	java/lang/Integer:valueOf	(I)Ljava/lang/Integer;
    //   157: aload 5
    //   159: invokeinterface 616 3 0
    //   164: pop
    //   165: goto -45 -> 120
    //   168: astore_3
    //   169: aload_2
    //   170: astore_1
    //   171: getstatic 32	el:a	Ljava/util/logging/Logger;
    //   174: getstatic 622	java/util/logging/Level:WARNING	Ljava/util/logging/Level;
    //   177: aload_3
    //   178: invokevirtual 623	java/io/IOException:toString	()Ljava/lang/String;
    //   181: invokevirtual 627	java/util/logging/Logger:log	(Ljava/util/logging/Level;Ljava/lang/String;)V
    //   184: aload_2
    //   185: invokestatic 629	el:a	(Ljava/io/InputStream;)V
    //   188: aload 4
    //   190: monitorexit
    //   191: getstatic 45	el:b	Ljava/util/Map;
    //   194: iload_0
    //   195: invokestatic 58	java/lang/Integer:valueOf	(I)Ljava/lang/Integer;
    //   198: invokeinterface 633 2 0
    //   203: checkcast 608	eq$b
    //   206: areturn
    //   207: aload_2
    //   208: invokestatic 629	el:a	(Ljava/io/InputStream;)V
    //   211: goto -23 -> 188
    //   214: astore_1
    //   215: aload 4
    //   217: monitorexit
    //   218: aload_1
    //   219: athrow
    //   220: astore_1
    //   221: aconst_null
    //   222: astore_3
    //   223: aload_1
    //   224: astore_2
    //   225: aload_3
    //   226: invokestatic 629	el:a	(Ljava/io/InputStream;)V
    //   229: aload_2
    //   230: athrow
    //   231: astore_2
    //   232: aload_1
    //   233: astore_3
    //   234: goto -9 -> 225
    //   237: astore_3
    //   238: aconst_null
    //   239: astore_2
    //   240: goto -71 -> 169
    // Local variable table:
    //   start	length	slot	name	signature
    //   0	243	0	paramInt	int
    //   49	122	1	localObject1	Object
    //   214	5	1	localObject2	Object
    //   220	13	1	localObject3	Object
    //   90	140	2	localObject4	Object
    //   231	1	2	localObject5	Object
    //   239	1	2	localObject6	Object
    //   100	34	3	localObject7	Object
    //   168	10	3	localIOException1	IOException
    //   222	12	3	localObject8	Object
    //   237	1	3	localIOException2	IOException
    //   20	196	4	localMap	Map
    //   142	16	5	localb	eq.b
    // Exception table:
    //   from	to	target	type
    //   93	101	168	java/io/IOException
    //   103	108	168	java/io/IOException
    //   110	120	168	java/io/IOException
    //   122	131	168	java/io/IOException
    //   133	144	168	java/io/IOException
    //   146	165	168	java/io/IOException
    //   25	82	214	finally
    //   184	188	214	finally
    //   188	191	214	finally
    //   207	211	214	finally
    //   215	218	214	finally
    //   225	231	214	finally
    //   82	91	220	finally
    //   93	101	231	finally
    //   103	108	231	finally
    //   110	120	231	finally
    //   122	131	231	finally
    //   133	144	231	finally
    //   146	165	231	finally
    //   171	184	231	finally
    //   82	91	237	java/io/IOException
  }
  
  private static void a(InputStream paramInputStream)
  {
    if (paramInputStream != null) {}
    try
    {
      paramInputStream.close();
      return;
    }
    catch (IOException paramInputStream)
    {
      a.log(Level.WARNING, paramInputStream.toString());
    }
  }
}

/* Location:
 * Qualified Name:     el
 * Java Class Version: 6 (50.0)
 * JD-Core Version:    0.7.1
 */