import android.text.TextUtils;
import com.snapchat.android.api2.framework.HttpMethod;
import java.net.URI;
import java.util.Iterator;
import java.util.Map;
import java.util.Map.Entry;
import java.util.Set;
import javax.inject.Inject;

public final class ud
  implements ub
{
  private static final String GET = "GET";
  private static final String TAG = "OkHttpNetworkInterface";
  private static final bgk mClock = bglmClock;
  private final tq mClientFactory;
  private final tl mEntityFactory;
  private final lx mGoogleAuthManager;
  private final bft mUrlRoutingManager;
  
  @Inject
  public ud(tl paramtl)
  {
    this(paramtl, new ui(), lx.a(), bft.a());
  }
  
  public ud(tl paramtl, tq paramtq)
  {
    this(paramtl, paramtq, lx.a(), bft.a());
  }
  
  private ud(tl paramtl, tq paramtq, lx paramlx, bft parambft)
  {
    mEntityFactory = paramtl;
    mClientFactory = paramtq;
    mGoogleAuthManager = paramlx;
    mUrlRoutingManager = parambft;
  }
  
  private bma.a a(Map<String, String> paramMap, HttpMethod paramHttpMethod, String paramString, Object paramObject)
  {
    if (paramHttpMethod == null) {
      throw new IllegalArgumentException("Null method encountered for url: " + paramString);
    }
    Object localObject = new blu.a();
    if (paramMap != null)
    {
      Iterator localIterator = paramMap.entrySet().iterator();
      for (paramMap = (Map<String, String>)localObject;; paramMap = paramMap.a((String)((Map.Entry)localObject).getKey(), (String)((Map.Entry)localObject).getValue()))
      {
        localObject = paramMap;
        if (!localIterator.hasNext()) {
          break;
        }
        localObject = (Map.Entry)localIterator.next();
      }
    }
    paramMap = ((blu.a)localObject).a();
    if (paramHttpMethod.toString().equals("GET")) {
      return new bma.a().a("GET", null).a(paramMap);
    }
    paramString = mEntityFactory.a(paramString, paramObject);
    return new bma.a().a(paramHttpMethod.toString(), paramString).a(paramMap);
  }
  
  private static String a(String paramString1, String paramString2)
  {
    if (TextUtils.isEmpty(paramString2)) {
      return paramString1;
    }
    return paramString1 + "; UUID: " + paramString2;
  }
  
  public static URI a(String paramString)
  {
    if (TextUtils.isEmpty(paramString)) {
      throw new IllegalArgumentException("Empty URL");
    }
    URI localURI = new URI(paramString);
    if (localURI.getHost() == null) {
      throw new IllegalArgumentException(String.format("Invalid URL - host should not be null - %s", new Object[] { paramString }));
    }
    if (localURI.getScheme() == null) {
      throw new IllegalArgumentException(String.format("Invalid URL - scheme should not be null - %s", new Object[] { paramString }));
    }
    return localURI;
  }
  
  /* Error */
  public final uc a(@cgb String paramString, @cgb HttpMethod paramHttpMethod, @cgc Map<String, String> paramMap, @cgb bfk parambfk, @cgc Object paramObject)
  {
    // Byte code:
    //   0: aload_0
    //   1: getfield 63	ud:mUrlRoutingManager	Lbft;
    //   4: aload_1
    //   5: invokevirtual 186	bft:a	(Ljava/lang/String;)Ljava/lang/String;
    //   8: astore 37
    //   10: invokestatic 192	java/lang/System:currentTimeMillis	()J
    //   13: lstore 31
    //   15: invokestatic 197	android/os/SystemClock:elapsedRealtime	()J
    //   18: lstore 33
    //   20: lconst_0
    //   21: lstore 15
    //   23: lconst_0
    //   24: lstore 9
    //   26: lconst_0
    //   27: lstore 11
    //   29: lconst_0
    //   30: lstore 17
    //   32: lconst_0
    //   33: lstore 13
    //   35: ldc -57
    //   37: astore 40
    //   39: aconst_null
    //   40: astore 38
    //   42: new 201	tj
    //   45: dup
    //   46: invokespecial 202	tj:<init>	()V
    //   49: astore 47
    //   51: new 204	uc$a
    //   54: dup
    //   55: aload 37
    //   57: invokestatic 209	bfp:b	()Ljava/lang/String;
    //   60: invokespecial 212	uc$a:<init>	(Ljava/lang/String;Ljava/lang/String;)V
    //   63: astore_1
    //   64: aload 37
    //   66: ifnull +577 -> 643
    //   69: aload 37
    //   71: ldc -42
    //   73: invokestatic 218	azm:b	(Ljava/lang/String;)Ljava/lang/String;
    //   76: invokevirtual 221	java/lang/String:contains	(Ljava/lang/CharSequence;)Z
    //   79: ifeq +564 -> 643
    //   82: iconst_1
    //   83: istore 7
    //   85: aload 5
    //   87: ifnonnull +562 -> 649
    //   90: aload 37
    //   92: ifnull +13 -> 105
    //   95: aload 37
    //   97: ldc -33
    //   99: invokevirtual 221	java/lang/String:contains	(Ljava/lang/CharSequence;)Z
    //   102: ifne +547 -> 649
    //   105: iconst_1
    //   106: istore 35
    //   108: aload_3
    //   109: ifnonnull +2383 -> 2492
    //   112: new 225	java/util/HashMap
    //   115: dup
    //   116: invokespecial 226	java/util/HashMap:<init>	()V
    //   119: astore 46
    //   121: ldc -57
    //   123: astore_3
    //   124: iconst_1
    //   125: istore 6
    //   127: aconst_null
    //   128: astore 39
    //   130: aload 37
    //   132: astore 41
    //   134: aload_3
    //   135: astore 37
    //   137: iload 6
    //   139: ifeq +1748 -> 1887
    //   142: iload 7
    //   144: ifeq +70 -> 214
    //   147: aload 38
    //   149: astore 42
    //   151: aload 46
    //   153: ldc -28
    //   155: new 68	java/lang/StringBuilder
    //   158: dup
    //   159: ldc -26
    //   161: invokespecial 73	java/lang/StringBuilder:<init>	(Ljava/lang/String;)V
    //   164: aload_0
    //   165: getfield 61	ud:mGoogleAuthManager	Llx;
    //   168: invokevirtual 233	lx:d	()Ljava/lang/String;
    //   171: invokevirtual 77	java/lang/StringBuilder:append	(Ljava/lang/String;)Ljava/lang/StringBuilder;
    //   174: invokevirtual 81	java/lang/StringBuilder:toString	()Ljava/lang/String;
    //   177: invokeinterface 237 3 0
    //   182: pop
    //   183: aload 38
    //   185: astore 42
    //   187: aload_0
    //   188: getfield 61	ud:mGoogleAuthManager	Llx;
    //   191: invokevirtual 238	lx:b	()Ljava/lang/String;
    //   194: astore_3
    //   195: aload_3
    //   196: ifnull +18 -> 214
    //   199: aload 38
    //   201: astore 42
    //   203: aload 46
    //   205: ldc -16
    //   207: aload_3
    //   208: invokeinterface 237 3 0
    //   213: pop
    //   214: aload 38
    //   216: astore 42
    //   218: aload_0
    //   219: aload 46
    //   221: aload_2
    //   222: aload 41
    //   224: aload 5
    //   226: invokespecial 242	ud:a	(Ljava/util/Map;Lcom/snapchat/android/api2/framework/HttpMethod;Ljava/lang/String;Ljava/lang/Object;)Lbma$a;
    //   229: astore_3
    //   230: aload 38
    //   232: astore 42
    //   234: invokestatic 247	uh:a	()Luh;
    //   237: aload_3
    //   238: aload 41
    //   240: aload_2
    //   241: invokevirtual 126	com/snapchat/android/api2/framework/HttpMethod:toString	()Ljava/lang/String;
    //   244: aload_0
    //   245: getfield 59	ud:mClientFactory	Ltq;
    //   248: ldc 12
    //   250: invokevirtual 250	uh:a	(Lbma$a;Ljava/lang/String;Ljava/lang/String;Ltq;Ljava/lang/String;)Luh$a;
    //   253: astore 43
    //   255: aload 38
    //   257: astore 42
    //   259: aload 43
    //   261: getfield 256	uh$a:mRequest	Lbma;
    //   264: astore 49
    //   266: aload 38
    //   268: astore 42
    //   270: aload 43
    //   272: getfield 259	uh$a:mUrl	Ljava/lang/String;
    //   275: astore_3
    //   276: aload 38
    //   278: astore 42
    //   280: aload 43
    //   282: getfield 263	uh$a:mResponse	Lbmc;
    //   285: astore 51
    //   287: aload 38
    //   289: astore 42
    //   291: aload 43
    //   293: getfield 266	uh$a:mMigrationResult	Ljava/lang/String;
    //   296: astore 41
    //   298: aload 38
    //   300: astore 42
    //   302: aload 43
    //   304: getfield 270	uh$a:mException	Ljava/io/IOException;
    //   307: astore 39
    //   309: aload 39
    //   311: ifnull +344 -> 655
    //   314: aload 38
    //   316: astore 42
    //   318: aload 39
    //   320: athrow
    //   321: astore 4
    //   323: aload 37
    //   325: astore 39
    //   327: lload 13
    //   329: lstore 15
    //   331: aload_1
    //   332: astore 37
    //   334: aload 4
    //   336: astore_1
    //   337: aload 41
    //   339: astore 4
    //   341: aload 39
    //   343: astore 41
    //   345: aload 40
    //   347: astore 5
    //   349: aload 37
    //   351: astore 40
    //   353: lload 11
    //   355: lstore 13
    //   357: lload 17
    //   359: lstore 11
    //   361: aload_3
    //   362: astore 39
    //   364: aload_1
    //   365: astore 37
    //   367: aload 41
    //   369: astore_3
    //   370: aload 40
    //   372: astore_1
    //   373: aload 38
    //   375: astore 42
    //   377: ldc 12
    //   379: ldc_w 272
    //   382: iconst_1
    //   383: anewarray 4	java/lang/Object
    //   386: dup
    //   387: iconst_0
    //   388: aload 37
    //   390: invokevirtual 277	java/lang/Exception:getMessage	()Ljava/lang/String;
    //   393: aastore
    //   394: invokestatic 283	com/snapchat/android/Timber:f	(Ljava/lang/String;Ljava/lang/String;[Ljava/lang/Object;)V
    //   397: aload 38
    //   399: astore 42
    //   401: aload_2
    //   402: invokevirtual 126	com/snapchat/android/api2/framework/HttpMethod:toString	()Ljava/lang/String;
    //   405: astore_2
    //   406: aload 38
    //   408: astore 42
    //   410: invokestatic 197	android/os/SystemClock:elapsedRealtime	()J
    //   413: lload 33
    //   415: lsub
    //   416: lstore 21
    //   418: aload 38
    //   420: astore 42
    //   422: invokestatic 288	com/snapchat/android/SnapchatApplication:b	()Lcom/snapchat/android/SnapchatApplication;
    //   425: lload 31
    //   427: aload_2
    //   428: aload 39
    //   430: lload 21
    //   432: aload 37
    //   434: invokevirtual 289	java/lang/Exception:toString	()Ljava/lang/String;
    //   437: invokestatic 294	aaq:a	(Landroid/content/Context;JLjava/lang/String;Ljava/lang/String;JLjava/lang/String;)V
    //   440: aload 38
    //   442: astore 42
    //   444: aload_1
    //   445: aload 37
    //   447: putfield 298	uc$a:mCaughtException	Ljava/lang/Exception;
    //   450: aload 38
    //   452: invokestatic 304	org/apache/commons/io/IOUtils:closeQuietly	(Ljava/io/InputStream;)V
    //   455: lload 13
    //   457: lstore 19
    //   459: lload 11
    //   461: lstore 17
    //   463: lload 15
    //   465: lstore 13
    //   467: aload_1
    //   468: invokevirtual 307	uc$a:a	()Luc;
    //   471: astore_1
    //   472: aload_1
    //   473: ldc_w 309
    //   476: invokevirtual 312	uc:a	(Ljava/lang/String;)Ljava/lang/String;
    //   479: ifnull +1448 -> 1927
    //   482: iconst_1
    //   483: istore 36
    //   485: new 314	com/snapchat/android/analytics/framework/EasyMetric
    //   488: dup
    //   489: ldc_w 316
    //   492: invokespecial 317	com/snapchat/android/analytics/framework/EasyMetric:<init>	(Ljava/lang/String;)V
    //   495: ldc_w 319
    //   498: aload_1
    //   499: getfield 322	uc:mNetworkType	Ljava/lang/String;
    //   502: invokevirtual 325	com/snapchat/android/analytics/framework/EasyMetric:a	(Ljava/lang/String;Ljava/lang/Object;)Lcom/snapchat/android/analytics/framework/EasyMetric;
    //   505: ldc_w 327
    //   508: aload_1
    //   509: invokevirtual 329	uc:a	()Ljava/lang/String;
    //   512: invokevirtual 325	com/snapchat/android/analytics/framework/EasyMetric:a	(Ljava/lang/String;Ljava/lang/Object;)Lcom/snapchat/android/analytics/framework/EasyMetric;
    //   515: ldc_w 331
    //   518: aload_1
    //   519: invokevirtual 332	uc:b	()Ljava/lang/String;
    //   522: invokevirtual 325	com/snapchat/android/analytics/framework/EasyMetric:a	(Ljava/lang/String;Ljava/lang/Object;)Lcom/snapchat/android/analytics/framework/EasyMetric;
    //   525: ldc_w 334
    //   528: lload 9
    //   530: invokestatic 340	java/lang/Long:valueOf	(J)Ljava/lang/Long;
    //   533: invokevirtual 325	com/snapchat/android/analytics/framework/EasyMetric:a	(Ljava/lang/String;Ljava/lang/Object;)Lcom/snapchat/android/analytics/framework/EasyMetric;
    //   536: ldc_w 342
    //   539: lload 21
    //   541: invokestatic 340	java/lang/Long:valueOf	(J)Ljava/lang/Long;
    //   544: invokevirtual 325	com/snapchat/android/analytics/framework/EasyMetric:a	(Ljava/lang/String;Ljava/lang/Object;)Lcom/snapchat/android/analytics/framework/EasyMetric;
    //   547: ldc_w 344
    //   550: aload_1
    //   551: getfield 348	uc:mResponseCode	I
    //   554: invokestatic 353	java/lang/Integer:valueOf	(I)Ljava/lang/Integer;
    //   557: invokevirtual 325	com/snapchat/android/analytics/framework/EasyMetric:a	(Ljava/lang/String;Ljava/lang/Object;)Lcom/snapchat/android/analytics/framework/EasyMetric;
    //   560: ldc_w 355
    //   563: lload 19
    //   565: invokestatic 340	java/lang/Long:valueOf	(J)Ljava/lang/Long;
    //   568: invokevirtual 325	com/snapchat/android/analytics/framework/EasyMetric:a	(Ljava/lang/String;Ljava/lang/Object;)Lcom/snapchat/android/analytics/framework/EasyMetric;
    //   571: ldc_w 357
    //   574: lload 13
    //   576: invokestatic 340	java/lang/Long:valueOf	(J)Ljava/lang/Long;
    //   579: invokevirtual 325	com/snapchat/android/analytics/framework/EasyMetric:a	(Ljava/lang/String;Ljava/lang/Object;)Lcom/snapchat/android/analytics/framework/EasyMetric;
    //   582: ldc_w 359
    //   585: lload 17
    //   587: invokestatic 340	java/lang/Long:valueOf	(J)Ljava/lang/Long;
    //   590: invokevirtual 325	com/snapchat/android/analytics/framework/EasyMetric:a	(Ljava/lang/String;Ljava/lang/Object;)Lcom/snapchat/android/analytics/framework/EasyMetric;
    //   593: ldc_w 361
    //   596: iload 36
    //   598: invokestatic 366	java/lang/Boolean:valueOf	(Z)Ljava/lang/Boolean;
    //   601: invokevirtual 325	com/snapchat/android/analytics/framework/EasyMetric:a	(Ljava/lang/String;Ljava/lang/Object;)Lcom/snapchat/android/analytics/framework/EasyMetric;
    //   604: ldc_w 368
    //   607: aload 5
    //   609: invokevirtual 325	com/snapchat/android/analytics/framework/EasyMetric:a	(Ljava/lang/String;Ljava/lang/Object;)Lcom/snapchat/android/analytics/framework/EasyMetric;
    //   612: ldc_w 370
    //   615: aload_3
    //   616: invokevirtual 325	com/snapchat/android/analytics/framework/EasyMetric:a	(Ljava/lang/String;Ljava/lang/Object;)Lcom/snapchat/android/analytics/framework/EasyMetric;
    //   619: ldc_w 372
    //   622: iload 35
    //   624: invokestatic 366	java/lang/Boolean:valueOf	(Z)Ljava/lang/Boolean;
    //   627: invokevirtual 325	com/snapchat/android/analytics/framework/EasyMetric:a	(Ljava/lang/String;Ljava/lang/Object;)Lcom/snapchat/android/analytics/framework/EasyMetric;
    //   630: astore_2
    //   631: aload_2
    //   632: aload 4
    //   634: invokestatic 375	uh:a	(Lcom/snapchat/android/analytics/framework/EasyMetric;Ljava/lang/String;)V
    //   637: aload_2
    //   638: invokevirtual 377	com/snapchat/android/analytics/framework/EasyMetric:d	()V
    //   641: aload_1
    //   642: areturn
    //   643: iconst_0
    //   644: istore 7
    //   646: goto -561 -> 85
    //   649: iconst_0
    //   650: istore 35
    //   652: goto -544 -> 108
    //   655: aload 38
    //   657: astore 42
    //   659: aload 46
    //   661: ldc_w 379
    //   664: invokeinterface 383 2 0
    //   669: checkcast 114	java/lang/String
    //   672: astore 39
    //   674: aload 38
    //   676: astore 42
    //   678: new 204	uc$a
    //   681: dup
    //   682: aload_3
    //   683: invokestatic 209	bfp:b	()Ljava/lang/String;
    //   686: invokespecial 212	uc$a:<init>	(Ljava/lang/String;Ljava/lang/String;)V
    //   689: astore 37
    //   691: aload 38
    //   693: astore 42
    //   695: lload 13
    //   697: lstore 19
    //   699: aload 40
    //   701: astore 44
    //   703: lload 13
    //   705: lstore 21
    //   707: aload 40
    //   709: astore 45
    //   711: lload 13
    //   713: lstore 23
    //   715: aload 40
    //   717: astore 43
    //   719: aload 51
    //   721: getfield 388	bmc:c	I
    //   724: istore 6
    //   726: iload 6
    //   728: sipush 499
    //   731: if_icmpne +132 -> 863
    //   734: iload 7
    //   736: ifeq +127 -> 863
    //   739: aload 38
    //   741: astore 42
    //   743: lload 13
    //   745: lstore 19
    //   747: aload 40
    //   749: astore 44
    //   751: lload 13
    //   753: lstore 21
    //   755: aload 40
    //   757: astore 45
    //   759: lload 13
    //   761: lstore 23
    //   763: aload 40
    //   765: astore 43
    //   767: aload_0
    //   768: getfield 61	ud:mGoogleAuthManager	Llx;
    //   771: invokevirtual 390	lx:c	()V
    //   774: aload 38
    //   776: astore 42
    //   778: lload 13
    //   780: lstore 19
    //   782: aload 40
    //   784: astore 44
    //   786: lload 13
    //   788: lstore 21
    //   790: aload 40
    //   792: astore 45
    //   794: lload 13
    //   796: lstore 23
    //   798: aload 40
    //   800: astore 43
    //   802: ldc 12
    //   804: new 68	java/lang/StringBuilder
    //   807: dup
    //   808: ldc_w 392
    //   811: invokespecial 73	java/lang/StringBuilder:<init>	(Ljava/lang/String;)V
    //   814: aload_2
    //   815: invokevirtual 395	java/lang/StringBuilder:append	(Ljava/lang/Object;)Ljava/lang/StringBuilder;
    //   818: ldc_w 397
    //   821: invokevirtual 77	java/lang/StringBuilder:append	(Ljava/lang/String;)Ljava/lang/StringBuilder;
    //   824: aload_3
    //   825: invokevirtual 77	java/lang/StringBuilder:append	(Ljava/lang/String;)Ljava/lang/StringBuilder;
    //   828: invokevirtual 81	java/lang/StringBuilder:toString	()Ljava/lang/String;
    //   831: aload 39
    //   833: invokestatic 399	ud:a	(Ljava/lang/String;Ljava/lang/String;)Ljava/lang/String;
    //   836: iconst_0
    //   837: anewarray 4	java/lang/Object
    //   840: invokestatic 401	com/snapchat/android/Timber:b	(Ljava/lang/String;Ljava/lang/String;[Ljava/lang/Object;)V
    //   843: aload 37
    //   845: astore_1
    //   846: aload 39
    //   848: astore 37
    //   850: iconst_1
    //   851: istore 6
    //   853: aload 41
    //   855: astore 39
    //   857: aload_3
    //   858: astore 41
    //   860: goto -723 -> 137
    //   863: aload 38
    //   865: astore 42
    //   867: lload 13
    //   869: lstore 19
    //   871: aload 40
    //   873: astore 44
    //   875: lload 13
    //   877: lstore 21
    //   879: aload 40
    //   881: astore 45
    //   883: lload 13
    //   885: lstore 23
    //   887: aload 40
    //   889: astore 43
    //   891: aload 51
    //   893: getfield 403	bmc:d	Ljava/lang/String;
    //   896: astore 48
    //   898: aload 38
    //   900: astore 42
    //   902: lload 13
    //   904: lstore 19
    //   906: aload 40
    //   908: astore 44
    //   910: lload 13
    //   912: lstore 21
    //   914: aload 40
    //   916: astore 45
    //   918: lload 13
    //   920: lstore 23
    //   922: aload 40
    //   924: astore 43
    //   926: new 405	ug
    //   929: dup
    //   930: aload 51
    //   932: getfield 408	bmc:f	Lblu;
    //   935: invokespecial 411	ug:<init>	(Lblu;)V
    //   938: astore 50
    //   940: aload 38
    //   942: astore 42
    //   944: lload 13
    //   946: lstore 19
    //   948: aload 40
    //   950: astore 44
    //   952: lload 13
    //   954: lstore 21
    //   956: aload 40
    //   958: astore 45
    //   960: lload 13
    //   962: lstore 23
    //   964: aload 40
    //   966: astore 43
    //   968: aload 51
    //   970: getfield 415	bmc:g	Lbmd;
    //   973: astore_1
    //   974: aload 38
    //   976: astore 42
    //   978: lload 13
    //   980: lstore 19
    //   982: aload 40
    //   984: astore 44
    //   986: lload 13
    //   988: lstore 21
    //   990: aload 40
    //   992: astore 45
    //   994: lload 13
    //   996: lstore 23
    //   998: aload 40
    //   1000: astore 43
    //   1002: aload 51
    //   1004: getfield 418	bmc:b	Lblz;
    //   1007: ifnonnull +828 -> 1835
    //   1010: ldc -57
    //   1012: astore 40
    //   1014: lload 13
    //   1016: lstore 15
    //   1018: aload 38
    //   1020: astore 42
    //   1022: lload 13
    //   1024: lstore 19
    //   1026: aload 40
    //   1028: astore 44
    //   1030: lload 13
    //   1032: lstore 21
    //   1034: aload 40
    //   1036: astore 45
    //   1038: lload 13
    //   1040: lstore 23
    //   1042: aload 40
    //   1044: astore 43
    //   1046: aload 49
    //   1048: getfield 423	bma:d	Lbmb;
    //   1051: ifnull +41 -> 1092
    //   1054: aload 38
    //   1056: astore 42
    //   1058: lload 13
    //   1060: lstore 19
    //   1062: aload 40
    //   1064: astore 44
    //   1066: lload 13
    //   1068: lstore 21
    //   1070: aload 40
    //   1072: astore 45
    //   1074: lload 13
    //   1076: lstore 23
    //   1078: aload 40
    //   1080: astore 43
    //   1082: aload 49
    //   1084: getfield 423	bma:d	Lbmb;
    //   1087: invokevirtual 427	bmb:b	()J
    //   1090: lstore 15
    //   1092: aload 38
    //   1094: astore 42
    //   1096: lload 15
    //   1098: lstore 19
    //   1100: aload 40
    //   1102: astore 44
    //   1104: lload 15
    //   1106: lstore 21
    //   1108: aload 40
    //   1110: astore 45
    //   1112: lload 15
    //   1114: lstore 23
    //   1116: aload 40
    //   1118: astore 43
    //   1120: aload 37
    //   1122: aload 39
    //   1124: putfield 430	uc$a:mRequestId	Ljava/lang/String;
    //   1127: aload 38
    //   1129: astore 42
    //   1131: lload 15
    //   1133: lstore 19
    //   1135: aload 40
    //   1137: astore 44
    //   1139: lload 15
    //   1141: lstore 21
    //   1143: aload 40
    //   1145: astore 45
    //   1147: lload 15
    //   1149: lstore 23
    //   1151: aload 40
    //   1153: astore 43
    //   1155: aload 37
    //   1157: iload 6
    //   1159: putfield 431	uc$a:mResponseCode	I
    //   1162: aload 38
    //   1164: astore 42
    //   1166: lload 15
    //   1168: lstore 19
    //   1170: aload 40
    //   1172: astore 44
    //   1174: lload 15
    //   1176: lstore 21
    //   1178: aload 40
    //   1180: astore 45
    //   1182: lload 15
    //   1184: lstore 23
    //   1186: aload 40
    //   1188: astore 43
    //   1190: aload 37
    //   1192: aload 48
    //   1194: putfield 434	uc$a:mResponseMessage	Ljava/lang/String;
    //   1197: aload 38
    //   1199: astore 42
    //   1201: lload 15
    //   1203: lstore 19
    //   1205: aload 40
    //   1207: astore 44
    //   1209: lload 15
    //   1211: lstore 21
    //   1213: aload 40
    //   1215: astore 45
    //   1217: lload 15
    //   1219: lstore 23
    //   1221: aload 40
    //   1223: astore 43
    //   1225: aload 37
    //   1227: aload 50
    //   1229: putfield 438	uc$a:mResponseHeaders	Lug;
    //   1232: aload 38
    //   1234: astore 42
    //   1236: lload 15
    //   1238: lstore 19
    //   1240: aload 40
    //   1242: astore 44
    //   1244: lload 15
    //   1246: lstore 21
    //   1248: aload 40
    //   1250: astore 45
    //   1252: lload 15
    //   1254: lstore 23
    //   1256: aload 40
    //   1258: astore 43
    //   1260: new 440	uo
    //   1263: dup
    //   1264: invokespecial 441	uo:<init>	()V
    //   1267: astore 49
    //   1269: aload_1
    //   1270: ifnull +1216 -> 2486
    //   1273: aload 38
    //   1275: astore 42
    //   1277: lload 15
    //   1279: lstore 19
    //   1281: aload 40
    //   1283: astore 44
    //   1285: lload 15
    //   1287: lstore 21
    //   1289: aload 40
    //   1291: astore 45
    //   1293: lload 15
    //   1295: lstore 23
    //   1297: aload 40
    //   1299: astore 43
    //   1301: aload_1
    //   1302: invokevirtual 446	bmd:c	()Ljava/io/InputStream;
    //   1305: astore_1
    //   1306: aload 4
    //   1308: aload_1
    //   1309: aload 49
    //   1311: invokeinterface 451 3 0
    //   1316: istore 8
    //   1318: iload 8
    //   1320: i2l
    //   1321: lstore 17
    //   1323: lload 11
    //   1325: lstore 25
    //   1327: lload 9
    //   1329: lstore 19
    //   1331: lload 11
    //   1333: lstore 27
    //   1335: lload 9
    //   1337: lstore 21
    //   1339: lload 11
    //   1341: lstore 23
    //   1343: lload 9
    //   1345: lstore 13
    //   1347: aload 37
    //   1349: aload 4
    //   1351: putfield 455	uc$a:mBuffer	Lbfk;
    //   1354: lload 11
    //   1356: lstore 25
    //   1358: lload 9
    //   1360: lstore 19
    //   1362: lload 11
    //   1364: lstore 27
    //   1366: lload 9
    //   1368: lstore 21
    //   1370: lload 11
    //   1372: lstore 23
    //   1374: lload 9
    //   1376: lstore 13
    //   1378: invokestatic 197	android/os/SystemClock:elapsedRealtime	()J
    //   1381: lload 33
    //   1383: lsub
    //   1384: lstore 29
    //   1386: lload 11
    //   1388: lstore 25
    //   1390: lload 9
    //   1392: lstore 19
    //   1394: lload 11
    //   1396: lstore 27
    //   1398: lload 9
    //   1400: lstore 21
    //   1402: lload 11
    //   1404: lstore 23
    //   1406: lload 9
    //   1408: lstore 13
    //   1410: aload 49
    //   1412: getfield 459	uo:mIsReceived	Z
    //   1415: ifeq +461 -> 1876
    //   1418: lload 11
    //   1420: lstore 25
    //   1422: lload 9
    //   1424: lstore 19
    //   1426: lload 11
    //   1428: lstore 27
    //   1430: lload 9
    //   1432: lstore 21
    //   1434: lload 11
    //   1436: lstore 23
    //   1438: lload 9
    //   1440: lstore 13
    //   1442: aload 49
    //   1444: getfield 463	uo:mFirstByteReceivedElapsedRealtimeInMillis	J
    //   1447: lload 33
    //   1449: lsub
    //   1450: lstore 9
    //   1452: lload 11
    //   1454: lstore 25
    //   1456: lload 9
    //   1458: lstore 19
    //   1460: lload 11
    //   1462: lstore 27
    //   1464: lload 9
    //   1466: lstore 21
    //   1468: lload 11
    //   1470: lstore 23
    //   1472: lload 9
    //   1474: lstore 13
    //   1476: aload 49
    //   1478: getfield 466	uo:mFirstByteSize	I
    //   1481: i2l
    //   1482: lstore 11
    //   1484: lload 11
    //   1486: lstore 25
    //   1488: lload 9
    //   1490: lstore 19
    //   1492: lload 11
    //   1494: lstore 27
    //   1496: lload 9
    //   1498: lstore 21
    //   1500: lload 11
    //   1502: lstore 23
    //   1504: lload 9
    //   1506: lstore 13
    //   1508: aload 37
    //   1510: lload 17
    //   1512: putfield 469	uc$a:mResponseBodySize	J
    //   1515: lload 11
    //   1517: lstore 25
    //   1519: lload 9
    //   1521: lstore 19
    //   1523: lload 11
    //   1525: lstore 27
    //   1527: lload 9
    //   1529: lstore 21
    //   1531: lload 11
    //   1533: lstore 23
    //   1535: lload 9
    //   1537: lstore 13
    //   1539: aload 47
    //   1541: lload 17
    //   1543: lload 15
    //   1545: invokevirtual 472	tj:a	(JJ)V
    //   1548: lload 11
    //   1550: lstore 25
    //   1552: lload 9
    //   1554: lstore 19
    //   1556: lload 11
    //   1558: lstore 27
    //   1560: lload 9
    //   1562: lstore 21
    //   1564: lload 11
    //   1566: lstore 23
    //   1568: lload 9
    //   1570: lstore 13
    //   1572: aload 47
    //   1574: aload_2
    //   1575: invokevirtual 126	com/snapchat/android/api2/framework/HttpMethod:toString	()Ljava/lang/String;
    //   1578: aload_3
    //   1579: aload 48
    //   1581: iload 6
    //   1583: lload 31
    //   1585: lload 29
    //   1587: invokevirtual 475	tj:a	(Ljava/lang/String;Ljava/lang/String;Ljava/lang/String;IJJ)V
    //   1590: aconst_null
    //   1591: astore 38
    //   1593: lload 11
    //   1595: lstore 25
    //   1597: lload 9
    //   1599: lstore 19
    //   1601: lload 11
    //   1603: lstore 27
    //   1605: lload 9
    //   1607: lstore 21
    //   1609: lload 11
    //   1611: lstore 23
    //   1613: lload 9
    //   1615: lstore 13
    //   1617: aload 50
    //   1619: ldc_w 477
    //   1622: invokevirtual 480	ug:a	(Ljava/lang/String;)Ljava/util/List;
    //   1625: astore 42
    //   1627: lload 11
    //   1629: lstore 25
    //   1631: lload 9
    //   1633: lstore 19
    //   1635: lload 11
    //   1637: lstore 27
    //   1639: lload 9
    //   1641: lstore 21
    //   1643: lload 11
    //   1645: lstore 23
    //   1647: lload 9
    //   1649: lstore 13
    //   1651: aload 42
    //   1653: invokeinterface 486 1 0
    //   1658: iconst_1
    //   1659: if_icmpne +40 -> 1699
    //   1662: lload 11
    //   1664: lstore 25
    //   1666: lload 9
    //   1668: lstore 19
    //   1670: lload 11
    //   1672: lstore 27
    //   1674: lload 9
    //   1676: lstore 21
    //   1678: lload 11
    //   1680: lstore 23
    //   1682: lload 9
    //   1684: lstore 13
    //   1686: aload 42
    //   1688: iconst_0
    //   1689: invokeinterface 489 2 0
    //   1694: checkcast 114	java/lang/String
    //   1697: astore 38
    //   1699: lload 11
    //   1701: lstore 25
    //   1703: lload 9
    //   1705: lstore 19
    //   1707: lload 11
    //   1709: lstore 27
    //   1711: lload 9
    //   1713: lstore 21
    //   1715: lload 11
    //   1717: lstore 23
    //   1719: lload 9
    //   1721: lstore 13
    //   1723: ldc 12
    //   1725: ldc_w 491
    //   1728: bipush 8
    //   1730: anewarray 4	java/lang/Object
    //   1733: dup
    //   1734: iconst_0
    //   1735: aload_2
    //   1736: aastore
    //   1737: dup
    //   1738: iconst_1
    //   1739: aload_3
    //   1740: aastore
    //   1741: dup
    //   1742: iconst_2
    //   1743: lload 17
    //   1745: invokestatic 340	java/lang/Long:valueOf	(J)Ljava/lang/Long;
    //   1748: aastore
    //   1749: dup
    //   1750: iconst_3
    //   1751: iload 6
    //   1753: invokestatic 353	java/lang/Integer:valueOf	(I)Ljava/lang/Integer;
    //   1756: aastore
    //   1757: dup
    //   1758: iconst_4
    //   1759: aload 48
    //   1761: aastore
    //   1762: dup
    //   1763: iconst_5
    //   1764: lload 31
    //   1766: invokestatic 340	java/lang/Long:valueOf	(J)Ljava/lang/Long;
    //   1769: aastore
    //   1770: dup
    //   1771: bipush 6
    //   1773: lload 29
    //   1775: invokestatic 340	java/lang/Long:valueOf	(J)Ljava/lang/Long;
    //   1778: aastore
    //   1779: dup
    //   1780: bipush 7
    //   1782: aload 38
    //   1784: aastore
    //   1785: invokestatic 171	java/lang/String:format	(Ljava/lang/String;[Ljava/lang/Object;)Ljava/lang/String;
    //   1788: aload 39
    //   1790: invokestatic 399	ud:a	(Ljava/lang/String;Ljava/lang/String;)Ljava/lang/String;
    //   1793: iconst_0
    //   1794: anewarray 4	java/lang/Object
    //   1797: invokestatic 401	com/snapchat/android/Timber:b	(Ljava/lang/String;Ljava/lang/String;[Ljava/lang/Object;)V
    //   1800: aload_1
    //   1801: astore 38
    //   1803: aload 39
    //   1805: astore 42
    //   1807: iconst_0
    //   1808: istore 6
    //   1810: aload 41
    //   1812: astore 39
    //   1814: aload 37
    //   1816: astore_1
    //   1817: aload 42
    //   1819: astore 37
    //   1821: aload_3
    //   1822: astore 41
    //   1824: lload 15
    //   1826: lstore 13
    //   1828: lload 29
    //   1830: lstore 15
    //   1832: goto -1695 -> 137
    //   1835: aload 38
    //   1837: astore 42
    //   1839: lload 13
    //   1841: lstore 19
    //   1843: aload 40
    //   1845: astore 44
    //   1847: lload 13
    //   1849: lstore 21
    //   1851: aload 40
    //   1853: astore 45
    //   1855: lload 13
    //   1857: lstore 23
    //   1859: aload 40
    //   1861: astore 43
    //   1863: aload 51
    //   1865: getfield 418	bmc:b	Lblz;
    //   1868: invokevirtual 494	blz:toString	()Ljava/lang/String;
    //   1871: astore 40
    //   1873: goto -859 -> 1014
    //   1876: lload 17
    //   1878: lstore 11
    //   1880: lload 29
    //   1882: lstore 9
    //   1884: goto -400 -> 1484
    //   1887: aload 38
    //   1889: invokestatic 304	org/apache/commons/io/IOUtils:closeQuietly	(Ljava/io/InputStream;)V
    //   1892: aload 39
    //   1894: astore 4
    //   1896: aload 37
    //   1898: astore_3
    //   1899: aload 40
    //   1901: astore 5
    //   1903: lload 11
    //   1905: lstore 19
    //   1907: lload 15
    //   1909: lstore 21
    //   1911: goto -1444 -> 467
    //   1914: astore_2
    //   1915: aload_1
    //   1916: astore 42
    //   1918: aload_2
    //   1919: astore_1
    //   1920: aload 42
    //   1922: invokestatic 304	org/apache/commons/io/IOUtils:closeQuietly	(Ljava/io/InputStream;)V
    //   1925: aload_1
    //   1926: athrow
    //   1927: iconst_0
    //   1928: istore 36
    //   1930: goto -1445 -> 485
    //   1933: astore 38
    //   1935: aload 41
    //   1937: astore 4
    //   1939: lload 19
    //   1941: lstore 9
    //   1943: lload 15
    //   1945: lstore 13
    //   1947: aload_3
    //   1948: astore 5
    //   1950: aload 38
    //   1952: astore_3
    //   1953: aload_1
    //   1954: astore 38
    //   1956: aload 5
    //   1958: astore 41
    //   1960: aload_3
    //   1961: astore 42
    //   1963: aload 40
    //   1965: astore 5
    //   1967: aload 37
    //   1969: astore_1
    //   1970: aload 39
    //   1972: astore_3
    //   1973: aload 42
    //   1975: astore 37
    //   1977: aload 41
    //   1979: astore 39
    //   1981: lload 13
    //   1983: lstore 15
    //   1985: lload 17
    //   1987: lstore 11
    //   1989: lload 25
    //   1991: lstore 13
    //   1993: goto -1620 -> 373
    //   1996: astore 4
    //   1998: aload_1
    //   1999: astore 38
    //   2001: lload 21
    //   2003: lstore 9
    //   2005: lload 15
    //   2007: lstore 13
    //   2009: aload 4
    //   2011: astore_1
    //   2012: aload_1
    //   2013: astore 42
    //   2015: aload 41
    //   2017: astore 4
    //   2019: aload 39
    //   2021: astore 5
    //   2023: aload_3
    //   2024: astore 39
    //   2026: aload 37
    //   2028: astore_1
    //   2029: aload 5
    //   2031: astore_3
    //   2032: aload 40
    //   2034: astore 5
    //   2036: aload 42
    //   2038: astore 37
    //   2040: lload 13
    //   2042: lstore 15
    //   2044: lload 17
    //   2046: lstore 11
    //   2048: lload 27
    //   2050: lstore 13
    //   2052: goto -1679 -> 373
    //   2055: astore_1
    //   2056: goto -136 -> 1920
    //   2059: astore_2
    //   2060: aload_1
    //   2061: astore 42
    //   2063: aload_2
    //   2064: astore_1
    //   2065: goto -145 -> 1920
    //   2068: astore 4
    //   2070: aload_1
    //   2071: astore 38
    //   2073: aload 4
    //   2075: astore_1
    //   2076: lload 23
    //   2078: lstore 11
    //   2080: lload 13
    //   2082: lstore 9
    //   2084: goto -1747 -> 337
    //   2087: astore 42
    //   2089: aload_1
    //   2090: astore 4
    //   2092: aload 39
    //   2094: astore 5
    //   2096: aload 41
    //   2098: astore_3
    //   2099: aload 42
    //   2101: astore_1
    //   2102: aload 37
    //   2104: astore 39
    //   2106: aload 4
    //   2108: astore 37
    //   2110: aload 5
    //   2112: astore 41
    //   2114: lload 13
    //   2116: lstore 15
    //   2118: goto -1781 -> 337
    //   2121: astore 5
    //   2123: aload_1
    //   2124: astore 4
    //   2126: aload 39
    //   2128: astore 41
    //   2130: aload 5
    //   2132: astore_1
    //   2133: aload 37
    //   2135: astore 39
    //   2137: aload 4
    //   2139: astore 37
    //   2141: lload 13
    //   2143: lstore 15
    //   2145: goto -1808 -> 337
    //   2148: astore 4
    //   2150: aload_1
    //   2151: astore 37
    //   2153: aload 4
    //   2155: astore_1
    //   2156: lload 13
    //   2158: lstore 15
    //   2160: goto -1823 -> 337
    //   2163: astore_1
    //   2164: lload 19
    //   2166: lstore 15
    //   2168: aload 44
    //   2170: astore 40
    //   2172: goto -1835 -> 337
    //   2175: astore 4
    //   2177: aload_1
    //   2178: astore 38
    //   2180: aload 4
    //   2182: astore_1
    //   2183: goto -1846 -> 337
    //   2186: astore 42
    //   2188: aload_1
    //   2189: astore 4
    //   2191: aload 39
    //   2193: astore 5
    //   2195: aload 41
    //   2197: astore_3
    //   2198: aload 42
    //   2200: astore_1
    //   2201: aload 37
    //   2203: astore 39
    //   2205: aload 4
    //   2207: astore 37
    //   2209: aload 5
    //   2211: astore 41
    //   2213: lload 11
    //   2215: lstore 27
    //   2217: goto -205 -> 2012
    //   2220: astore 5
    //   2222: aload_1
    //   2223: astore 4
    //   2225: aload 39
    //   2227: astore 41
    //   2229: aload 5
    //   2231: astore_1
    //   2232: aload 37
    //   2234: astore 39
    //   2236: aload 4
    //   2238: astore 37
    //   2240: lload 11
    //   2242: lstore 27
    //   2244: goto -232 -> 2012
    //   2247: astore 5
    //   2249: aload_1
    //   2250: astore 4
    //   2252: aload 5
    //   2254: astore_1
    //   2255: aload 37
    //   2257: astore 39
    //   2259: aload 4
    //   2261: astore 37
    //   2263: lload 11
    //   2265: lstore 27
    //   2267: goto -255 -> 2012
    //   2270: astore 4
    //   2272: aload_1
    //   2273: astore 37
    //   2275: aload 4
    //   2277: astore_1
    //   2278: lload 11
    //   2280: lstore 27
    //   2282: goto -270 -> 2012
    //   2285: astore_1
    //   2286: lload 21
    //   2288: lstore 13
    //   2290: lload 11
    //   2292: lstore 27
    //   2294: aload 45
    //   2296: astore 40
    //   2298: goto -286 -> 2012
    //   2301: astore 4
    //   2303: aload_1
    //   2304: astore 38
    //   2306: aload 4
    //   2308: astore_1
    //   2309: lload 15
    //   2311: lstore 13
    //   2313: lload 11
    //   2315: lstore 27
    //   2317: goto -305 -> 2012
    //   2320: astore_3
    //   2321: aload 39
    //   2323: astore 4
    //   2325: aload 41
    //   2327: astore 5
    //   2329: aload 37
    //   2331: astore 39
    //   2333: aload_1
    //   2334: astore 37
    //   2336: aload 38
    //   2338: astore_1
    //   2339: lload 11
    //   2341: lstore 25
    //   2343: goto -390 -> 1953
    //   2346: astore 42
    //   2348: aload 37
    //   2350: astore 41
    //   2352: aload_3
    //   2353: astore 5
    //   2355: aload 39
    //   2357: astore 4
    //   2359: aload 42
    //   2361: astore_3
    //   2362: aload_1
    //   2363: astore 37
    //   2365: aload 38
    //   2367: astore_1
    //   2368: aload 41
    //   2370: astore 39
    //   2372: lload 11
    //   2374: lstore 25
    //   2376: goto -423 -> 1953
    //   2379: astore 42
    //   2381: aload 41
    //   2383: astore 4
    //   2385: aload 37
    //   2387: astore 39
    //   2389: aload_3
    //   2390: astore 5
    //   2392: aload 42
    //   2394: astore_3
    //   2395: aload_1
    //   2396: astore 37
    //   2398: aload 38
    //   2400: astore_1
    //   2401: lload 11
    //   2403: lstore 25
    //   2405: goto -452 -> 1953
    //   2408: astore 37
    //   2410: aload 41
    //   2412: astore 4
    //   2414: aload_3
    //   2415: astore 5
    //   2417: aload 37
    //   2419: astore_3
    //   2420: aload_1
    //   2421: astore 37
    //   2423: aload 38
    //   2425: astore_1
    //   2426: lload 11
    //   2428: lstore 25
    //   2430: goto -477 -> 1953
    //   2433: astore 40
    //   2435: aload 41
    //   2437: astore 4
    //   2439: aload_3
    //   2440: astore 5
    //   2442: aload 38
    //   2444: astore_1
    //   2445: aload 40
    //   2447: astore_3
    //   2448: lload 23
    //   2450: lstore 13
    //   2452: lload 11
    //   2454: lstore 25
    //   2456: aload 43
    //   2458: astore 40
    //   2460: goto -507 -> 1953
    //   2463: astore 38
    //   2465: aload 41
    //   2467: astore 4
    //   2469: aload_3
    //   2470: astore 5
    //   2472: aload 38
    //   2474: astore_3
    //   2475: lload 15
    //   2477: lstore 13
    //   2479: lload 11
    //   2481: lstore 25
    //   2483: goto -530 -> 1953
    //   2486: aload 38
    //   2488: astore_1
    //   2489: goto -1166 -> 1323
    //   2492: ldc -57
    //   2494: astore 42
    //   2496: aload 37
    //   2498: astore 41
    //   2500: iconst_1
    //   2501: istore 6
    //   2503: aconst_null
    //   2504: astore 39
    //   2506: aload 42
    //   2508: astore 37
    //   2510: aload_3
    //   2511: astore 46
    //   2513: goto -2376 -> 137
    // Local variable table:
    //   start	length	slot	name	signature
    //   0	2516	0	this	ud
    //   0	2516	1	paramString	String
    //   0	2516	2	paramHttpMethod	HttpMethod
    //   0	2516	3	paramMap	Map<String, String>
    //   0	2516	4	parambfk	bfk
    //   0	2516	5	paramObject	Object
    //   125	2377	6	i	int
    //   83	652	7	j	int
    //   1316	3	8	k	int
    //   24	2059	9	l1	long
    //   27	2453	11	l2	long
    //   33	2445	13	l3	long
    //   21	2455	15	l4	long
    //   30	2015	17	l5	long
    //   457	1708	19	l6	long
    //   416	1871	21	l7	long
    //   713	1736	23	l8	long
    //   1325	1157	25	l9	long
    //   1333	983	27	l10	long
    //   1384	497	29	l11	long
    //   13	1752	31	l12	long
    //   18	1430	33	l13	long
    //   106	545	35	bool1	boolean
    //   483	1446	36	bool2	boolean
    //   8	2389	37	localObject1	Object
    //   2408	10	37	localIllegalArgumentException1	IllegalArgumentException
    //   2421	88	37	localObject2	Object
    //   40	1848	38	localObject3	Object
    //   1933	18	38	localIllegalArgumentException2	IllegalArgumentException
    //   1954	489	38	str1	String
    //   2463	24	38	localIllegalArgumentException3	IllegalArgumentException
    //   128	2377	39	localObject4	Object
    //   37	2260	40	localObject5	Object
    //   2433	13	40	localIllegalArgumentException4	IllegalArgumentException
    //   2458	1	40	localObject6	Object
    //   132	2367	41	localObject7	Object
    //   149	1913	42	localObject8	Object
    //   2087	13	42	localIOException	java.io.IOException
    //   2186	13	42	localIllegalStateException	IllegalStateException
    //   2346	14	42	localIllegalArgumentException5	IllegalArgumentException
    //   2379	14	42	localIllegalArgumentException6	IllegalArgumentException
    //   2494	13	42	str2	String
    //   253	2204	43	localObject9	Object
    //   701	1468	44	localObject10	Object
    //   709	1586	45	localObject11	Object
    //   119	2393	46	localObject12	Object
    //   49	1524	47	localtj	tj
    //   896	864	48	str3	String
    //   264	1213	49	localObject13	Object
    //   938	680	50	localug	ug
    //   285	1579	51	localbmc	bmc
    // Exception table:
    //   from	to	target	type
    //   302	309	321	java/io/IOException
    //   318	321	321	java/io/IOException
    //   659	674	321	java/io/IOException
    //   1347	1354	1914	finally
    //   1378	1386	1914	finally
    //   1410	1418	1914	finally
    //   1442	1452	1914	finally
    //   1476	1484	1914	finally
    //   1508	1515	1914	finally
    //   1539	1548	1914	finally
    //   1572	1590	1914	finally
    //   1617	1627	1914	finally
    //   1651	1662	1914	finally
    //   1686	1699	1914	finally
    //   1723	1800	1914	finally
    //   1347	1354	1933	java/lang/IllegalArgumentException
    //   1378	1386	1933	java/lang/IllegalArgumentException
    //   1410	1418	1933	java/lang/IllegalArgumentException
    //   1442	1452	1933	java/lang/IllegalArgumentException
    //   1476	1484	1933	java/lang/IllegalArgumentException
    //   1508	1515	1933	java/lang/IllegalArgumentException
    //   1539	1548	1933	java/lang/IllegalArgumentException
    //   1572	1590	1933	java/lang/IllegalArgumentException
    //   1617	1627	1933	java/lang/IllegalArgumentException
    //   1651	1662	1933	java/lang/IllegalArgumentException
    //   1686	1699	1933	java/lang/IllegalArgumentException
    //   1723	1800	1933	java/lang/IllegalArgumentException
    //   1347	1354	1996	java/lang/IllegalStateException
    //   1378	1386	1996	java/lang/IllegalStateException
    //   1410	1418	1996	java/lang/IllegalStateException
    //   1442	1452	1996	java/lang/IllegalStateException
    //   1476	1484	1996	java/lang/IllegalStateException
    //   1508	1515	1996	java/lang/IllegalStateException
    //   1539	1548	1996	java/lang/IllegalStateException
    //   1572	1590	1996	java/lang/IllegalStateException
    //   1617	1627	1996	java/lang/IllegalStateException
    //   1651	1662	1996	java/lang/IllegalStateException
    //   1686	1699	1996	java/lang/IllegalStateException
    //   1723	1800	1996	java/lang/IllegalStateException
    //   151	183	2055	finally
    //   187	195	2055	finally
    //   203	214	2055	finally
    //   218	230	2055	finally
    //   234	255	2055	finally
    //   259	266	2055	finally
    //   270	276	2055	finally
    //   280	287	2055	finally
    //   291	298	2055	finally
    //   302	309	2055	finally
    //   318	321	2055	finally
    //   377	397	2055	finally
    //   401	406	2055	finally
    //   410	418	2055	finally
    //   422	440	2055	finally
    //   444	450	2055	finally
    //   659	674	2055	finally
    //   678	691	2055	finally
    //   719	726	2055	finally
    //   767	774	2055	finally
    //   802	843	2055	finally
    //   891	898	2055	finally
    //   926	940	2055	finally
    //   968	974	2055	finally
    //   1002	1010	2055	finally
    //   1046	1054	2055	finally
    //   1082	1092	2055	finally
    //   1120	1127	2055	finally
    //   1155	1162	2055	finally
    //   1190	1197	2055	finally
    //   1225	1232	2055	finally
    //   1260	1269	2055	finally
    //   1301	1306	2055	finally
    //   1863	1873	2055	finally
    //   1306	1318	2059	finally
    //   1347	1354	2068	java/io/IOException
    //   1378	1386	2068	java/io/IOException
    //   1410	1418	2068	java/io/IOException
    //   1442	1452	2068	java/io/IOException
    //   1476	1484	2068	java/io/IOException
    //   1508	1515	2068	java/io/IOException
    //   1539	1548	2068	java/io/IOException
    //   1572	1590	2068	java/io/IOException
    //   1617	1627	2068	java/io/IOException
    //   1651	1662	2068	java/io/IOException
    //   1686	1699	2068	java/io/IOException
    //   1723	1800	2068	java/io/IOException
    //   151	183	2087	java/io/IOException
    //   187	195	2087	java/io/IOException
    //   203	214	2087	java/io/IOException
    //   218	230	2087	java/io/IOException
    //   234	255	2087	java/io/IOException
    //   259	266	2087	java/io/IOException
    //   270	276	2087	java/io/IOException
    //   280	287	2121	java/io/IOException
    //   291	298	2121	java/io/IOException
    //   678	691	2148	java/io/IOException
    //   719	726	2163	java/io/IOException
    //   767	774	2163	java/io/IOException
    //   802	843	2163	java/io/IOException
    //   891	898	2163	java/io/IOException
    //   926	940	2163	java/io/IOException
    //   968	974	2163	java/io/IOException
    //   1002	1010	2163	java/io/IOException
    //   1046	1054	2163	java/io/IOException
    //   1082	1092	2163	java/io/IOException
    //   1120	1127	2163	java/io/IOException
    //   1155	1162	2163	java/io/IOException
    //   1190	1197	2163	java/io/IOException
    //   1225	1232	2163	java/io/IOException
    //   1260	1269	2163	java/io/IOException
    //   1301	1306	2163	java/io/IOException
    //   1863	1873	2163	java/io/IOException
    //   1306	1318	2175	java/io/IOException
    //   151	183	2186	java/lang/IllegalStateException
    //   187	195	2186	java/lang/IllegalStateException
    //   203	214	2186	java/lang/IllegalStateException
    //   218	230	2186	java/lang/IllegalStateException
    //   234	255	2186	java/lang/IllegalStateException
    //   259	266	2186	java/lang/IllegalStateException
    //   270	276	2186	java/lang/IllegalStateException
    //   280	287	2220	java/lang/IllegalStateException
    //   291	298	2220	java/lang/IllegalStateException
    //   302	309	2247	java/lang/IllegalStateException
    //   318	321	2247	java/lang/IllegalStateException
    //   659	674	2247	java/lang/IllegalStateException
    //   678	691	2270	java/lang/IllegalStateException
    //   719	726	2285	java/lang/IllegalStateException
    //   767	774	2285	java/lang/IllegalStateException
    //   802	843	2285	java/lang/IllegalStateException
    //   891	898	2285	java/lang/IllegalStateException
    //   926	940	2285	java/lang/IllegalStateException
    //   968	974	2285	java/lang/IllegalStateException
    //   1002	1010	2285	java/lang/IllegalStateException
    //   1046	1054	2285	java/lang/IllegalStateException
    //   1082	1092	2285	java/lang/IllegalStateException
    //   1120	1127	2285	java/lang/IllegalStateException
    //   1155	1162	2285	java/lang/IllegalStateException
    //   1190	1197	2285	java/lang/IllegalStateException
    //   1225	1232	2285	java/lang/IllegalStateException
    //   1260	1269	2285	java/lang/IllegalStateException
    //   1301	1306	2285	java/lang/IllegalStateException
    //   1863	1873	2285	java/lang/IllegalStateException
    //   1306	1318	2301	java/lang/IllegalStateException
    //   151	183	2320	java/lang/IllegalArgumentException
    //   187	195	2320	java/lang/IllegalArgumentException
    //   203	214	2320	java/lang/IllegalArgumentException
    //   218	230	2320	java/lang/IllegalArgumentException
    //   234	255	2320	java/lang/IllegalArgumentException
    //   259	266	2320	java/lang/IllegalArgumentException
    //   270	276	2320	java/lang/IllegalArgumentException
    //   280	287	2346	java/lang/IllegalArgumentException
    //   291	298	2346	java/lang/IllegalArgumentException
    //   302	309	2379	java/lang/IllegalArgumentException
    //   318	321	2379	java/lang/IllegalArgumentException
    //   659	674	2379	java/lang/IllegalArgumentException
    //   678	691	2408	java/lang/IllegalArgumentException
    //   719	726	2433	java/lang/IllegalArgumentException
    //   767	774	2433	java/lang/IllegalArgumentException
    //   802	843	2433	java/lang/IllegalArgumentException
    //   891	898	2433	java/lang/IllegalArgumentException
    //   926	940	2433	java/lang/IllegalArgumentException
    //   968	974	2433	java/lang/IllegalArgumentException
    //   1002	1010	2433	java/lang/IllegalArgumentException
    //   1046	1054	2433	java/lang/IllegalArgumentException
    //   1082	1092	2433	java/lang/IllegalArgumentException
    //   1120	1127	2433	java/lang/IllegalArgumentException
    //   1155	1162	2433	java/lang/IllegalArgumentException
    //   1190	1197	2433	java/lang/IllegalArgumentException
    //   1225	1232	2433	java/lang/IllegalArgumentException
    //   1260	1269	2433	java/lang/IllegalArgumentException
    //   1301	1306	2433	java/lang/IllegalArgumentException
    //   1863	1873	2433	java/lang/IllegalArgumentException
    //   1306	1318	2463	java/lang/IllegalArgumentException
  }
}

/* Location:
 * Qualified Name:     ud
 * Java Class Version: 6 (50.0)
 * JD-Core Version:    0.7.1
 */