import android.text.TextUtils;
import com.snapchat.android.api2.framework.HttpMethod;
import java.net.URI;
import java.util.Iterator;
import java.util.Map;
import java.util.Map.Entry;
import java.util.Set;
import javax.inject.Inject;

public final class ut
  implements ur
{
  private static final String GET = "GET";
  private static final String TAG = "OkHttpNetworkInterface";
  private static final bhk mClock = bhlmClock;
  private final ug mClientFactory;
  private final ub mEntityFactory;
  private final mp mGoogleAuthManager;
  private final bgt mUrlRoutingManager;
  
  @Inject
  public ut(ub paramub)
  {
    this(paramub, new uz(), mp.a(), bgt.a());
  }
  
  public ut(ub paramub, ug paramug)
  {
    this(paramub, paramug, mp.a(), bgt.a());
  }
  
  private ut(ub paramub, ug paramug, mp parammp, bgt parambgt)
  {
    mEntityFactory = paramub;
    mClientFactory = paramug;
    mGoogleAuthManager = parammp;
    mUrlRoutingManager = parambgt;
  }
  
  private bnb.a a(Map<String, String> paramMap, HttpMethod paramHttpMethod, String paramString, Object paramObject)
  {
    if (paramHttpMethod == null) {
      throw new IllegalArgumentException("Null method encountered for url: " + paramString);
    }
    Object localObject = new bmv.a();
    if (paramMap != null)
    {
      Iterator localIterator = paramMap.entrySet().iterator();
      for (paramMap = (Map<String, String>)localObject;; paramMap = paramMap.a((String)((Map.Entry)localObject).getKey(), (String)((Map.Entry)localObject).getValue()))
      {
        localObject = paramMap;
        if (!localIterator.hasNext()) {
          break;
        }
        localObject = (Map.Entry)localIterator.next();
      }
    }
    paramMap = ((bmv.a)localObject).a();
    if (paramHttpMethod.toString().equals("GET")) {
      return new bnb.a().a("GET", null).a(paramMap);
    }
    paramString = mEntityFactory.a(paramString, paramObject);
    return new bnb.a().a(paramHttpMethod.toString(), paramString).a(paramMap);
  }
  
  private static String a(String paramString1, String paramString2)
  {
    if (TextUtils.isEmpty(paramString2)) {
      return paramString1;
    }
    return paramString1 + "; UUID: " + paramString2;
  }
  
  public static URI a(String paramString)
  {
    if (TextUtils.isEmpty(paramString)) {
      throw new IllegalArgumentException("Empty URL");
    }
    URI localURI = new URI(paramString);
    if (localURI.getHost() == null) {
      throw new IllegalArgumentException(String.format("Invalid URL - host should not be null - %s", new Object[] { paramString }));
    }
    if (localURI.getScheme() == null) {
      throw new IllegalArgumentException(String.format("Invalid URL - scheme should not be null - %s", new Object[] { paramString }));
    }
    return localURI;
  }
  
  /* Error */
  public final us a(@chc String paramString, @chc HttpMethod paramHttpMethod, @chd Map<String, String> paramMap, @chc bgk parambgk, @chd Object paramObject)
  {
    // Byte code:
    //   0: aload_0
    //   1: getfield 65	ut:mUrlRoutingManager	Lbgt;
    //   4: aload_1
    //   5: invokevirtual 188	bgt:a	(Ljava/lang/String;)Ljava/lang/String;
    //   8: astore 38
    //   10: invokestatic 194	java/lang/System:currentTimeMillis	()J
    //   13: lstore 31
    //   15: invokestatic 199	android/os/SystemClock:elapsedRealtime	()J
    //   18: lstore 33
    //   20: lconst_0
    //   21: lstore 17
    //   23: lconst_0
    //   24: lstore 13
    //   26: lconst_0
    //   27: lstore 11
    //   29: lconst_0
    //   30: lstore 15
    //   32: lconst_0
    //   33: lstore 9
    //   35: ldc -55
    //   37: astore 41
    //   39: aconst_null
    //   40: astore 37
    //   42: new 203	tz
    //   45: dup
    //   46: invokespecial 204	tz:<init>	()V
    //   49: astore 47
    //   51: new 206	us$a
    //   54: dup
    //   55: aload 38
    //   57: invokestatic 211	bgp:b	()Ljava/lang/String;
    //   60: invokespecial 214	us$a:<init>	(Ljava/lang/String;Ljava/lang/String;)V
    //   63: astore_1
    //   64: aload 38
    //   66: ifnull +662 -> 728
    //   69: aload 38
    //   71: ldc -40
    //   73: invokestatic 220	bal:b	(Ljava/lang/String;)Ljava/lang/String;
    //   76: invokevirtual 223	java/lang/String:contains	(Ljava/lang/CharSequence;)Z
    //   79: ifeq +649 -> 728
    //   82: iconst_1
    //   83: istore 7
    //   85: aload 5
    //   87: ifnonnull +647 -> 734
    //   90: aload 38
    //   92: ifnull +13 -> 105
    //   95: aload 38
    //   97: ldc -31
    //   99: invokevirtual 223	java/lang/String:contains	(Ljava/lang/CharSequence;)Z
    //   102: ifne +632 -> 734
    //   105: iconst_1
    //   106: istore 35
    //   108: aload_3
    //   109: ifnonnull +2102 -> 2211
    //   112: new 227	java/util/HashMap
    //   115: dup
    //   116: invokespecial 228	java/util/HashMap:<init>	()V
    //   119: astore 46
    //   121: iconst_1
    //   122: istore 6
    //   124: ldc -55
    //   126: astore 39
    //   128: aconst_null
    //   129: astore 40
    //   131: iload 6
    //   133: ifeq +1496 -> 1629
    //   136: iload 7
    //   138: ifeq +106 -> 244
    //   141: aload 37
    //   143: astore 42
    //   145: aload 38
    //   147: astore 43
    //   149: aload 38
    //   151: astore 44
    //   153: aload 38
    //   155: astore 45
    //   157: aload 46
    //   159: ldc -26
    //   161: new 70	java/lang/StringBuilder
    //   164: dup
    //   165: ldc -24
    //   167: invokespecial 75	java/lang/StringBuilder:<init>	(Ljava/lang/String;)V
    //   170: aload_0
    //   171: getfield 63	ut:mGoogleAuthManager	Lmp;
    //   174: invokevirtual 235	mp:d	()Ljava/lang/String;
    //   177: invokevirtual 79	java/lang/StringBuilder:append	(Ljava/lang/String;)Ljava/lang/StringBuilder;
    //   180: invokevirtual 83	java/lang/StringBuilder:toString	()Ljava/lang/String;
    //   183: invokeinterface 239 3 0
    //   188: pop
    //   189: aload 37
    //   191: astore 42
    //   193: aload 38
    //   195: astore 43
    //   197: aload 38
    //   199: astore 44
    //   201: aload 38
    //   203: astore 45
    //   205: aload_0
    //   206: getfield 63	ut:mGoogleAuthManager	Lmp;
    //   209: invokevirtual 240	mp:b	()Ljava/lang/String;
    //   212: astore_3
    //   213: aload_3
    //   214: ifnull +30 -> 244
    //   217: aload 37
    //   219: astore 42
    //   221: aload 38
    //   223: astore 43
    //   225: aload 38
    //   227: astore 44
    //   229: aload 38
    //   231: astore 45
    //   233: aload 46
    //   235: ldc -14
    //   237: aload_3
    //   238: invokeinterface 239 3 0
    //   243: pop
    //   244: aload 37
    //   246: astore 42
    //   248: aload 38
    //   250: astore 43
    //   252: aload 38
    //   254: astore 44
    //   256: aload 38
    //   258: astore 45
    //   260: aload_0
    //   261: aload 46
    //   263: aload_2
    //   264: aload 38
    //   266: aload 5
    //   268: invokespecial 244	ut:a	(Ljava/util/Map;Lcom/snapchat/android/api2/framework/HttpMethod;Ljava/lang/String;Ljava/lang/Object;)Lbnb$a;
    //   271: astore_3
    //   272: aload 37
    //   274: astore 42
    //   276: aload 38
    //   278: astore 43
    //   280: aload 38
    //   282: astore 44
    //   284: aload 38
    //   286: astore 45
    //   288: invokestatic 249	uy:a	()Luy;
    //   291: aload_3
    //   292: aload 38
    //   294: aload_2
    //   295: invokevirtual 128	com/snapchat/android/api2/framework/HttpMethod:toString	()Ljava/lang/String;
    //   298: aload_0
    //   299: getfield 61	ut:mClientFactory	Lug;
    //   302: invokevirtual 252	uy:a	(Lbnb$a;Ljava/lang/String;Ljava/lang/String;Lug;)Luy$a;
    //   305: astore 50
    //   307: aload 37
    //   309: astore 42
    //   311: aload 38
    //   313: astore 43
    //   315: aload 38
    //   317: astore 44
    //   319: aload 38
    //   321: astore 45
    //   323: aload 50
    //   325: getfield 258	uy$a:mRequest	Lbnb;
    //   328: astore 48
    //   330: aload 37
    //   332: astore 42
    //   334: aload 38
    //   336: astore 43
    //   338: aload 38
    //   340: astore 44
    //   342: aload 38
    //   344: astore 45
    //   346: aload 50
    //   348: getfield 261	uy$a:mUrl	Ljava/lang/String;
    //   351: astore_3
    //   352: aload 37
    //   354: astore 42
    //   356: aload_3
    //   357: astore 43
    //   359: aload_3
    //   360: astore 44
    //   362: aload_3
    //   363: astore 45
    //   365: aload 50
    //   367: getfield 265	uy$a:mResponse	Lbnd;
    //   370: astore 49
    //   372: aload 37
    //   374: astore 42
    //   376: aload_3
    //   377: astore 43
    //   379: aload_3
    //   380: astore 44
    //   382: aload_3
    //   383: astore 45
    //   385: aload 50
    //   387: getfield 268	uy$a:mMigrationResult	Ljava/lang/String;
    //   390: astore 38
    //   392: aload 37
    //   394: astore 42
    //   396: aload 50
    //   398: getfield 272	uy$a:mException	Ljava/io/IOException;
    //   401: astore 40
    //   403: aload 40
    //   405: ifnull +335 -> 740
    //   408: aload 37
    //   410: astore 42
    //   412: aload 40
    //   414: athrow
    //   415: astore 4
    //   417: aload 39
    //   419: astore 40
    //   421: aload_1
    //   422: astore 39
    //   424: aload 4
    //   426: astore_1
    //   427: aload_1
    //   428: astore 5
    //   430: aload 38
    //   432: astore 4
    //   434: lload 11
    //   436: lstore 17
    //   438: lload 9
    //   440: lstore 11
    //   442: aload 39
    //   444: astore_1
    //   445: lload 13
    //   447: lstore 9
    //   449: lload 15
    //   451: lstore 13
    //   453: lload 17
    //   455: lstore 15
    //   457: aload_3
    //   458: astore 39
    //   460: aload 5
    //   462: astore 38
    //   464: aload 41
    //   466: astore 5
    //   468: aload 40
    //   470: astore_3
    //   471: aload 37
    //   473: astore 42
    //   475: aload 38
    //   477: invokevirtual 277	java/lang/Exception:getMessage	()Ljava/lang/String;
    //   480: pop
    //   481: aload 37
    //   483: astore 42
    //   485: aload_2
    //   486: invokevirtual 128	com/snapchat/android/api2/framework/HttpMethod:toString	()Ljava/lang/String;
    //   489: astore_2
    //   490: aload 37
    //   492: astore 42
    //   494: invokestatic 199	android/os/SystemClock:elapsedRealtime	()J
    //   497: lload 33
    //   499: lsub
    //   500: lstore 17
    //   502: aload 37
    //   504: astore 42
    //   506: invokestatic 282	com/snapchat/android/SnapchatApplication:b	()Lcom/snapchat/android/SnapchatApplication;
    //   509: lload 31
    //   511: aload_2
    //   512: aload 39
    //   514: lload 17
    //   516: aload 38
    //   518: invokevirtual 283	java/lang/Exception:toString	()Ljava/lang/String;
    //   521: invokestatic 288	abp:a	(Landroid/content/Context;JLjava/lang/String;Ljava/lang/String;JLjava/lang/String;)V
    //   524: aload 37
    //   526: astore 42
    //   528: aload_1
    //   529: aload 38
    //   531: putfield 292	us$a:mCaughtException	Ljava/lang/Exception;
    //   534: aload 37
    //   536: invokestatic 298	org/apache/commons/io/IOUtils:closeQuietly	(Ljava/io/InputStream;)V
    //   539: lload 9
    //   541: lstore 19
    //   543: lload 15
    //   545: lstore 9
    //   547: lload 13
    //   549: lstore 15
    //   551: aload_1
    //   552: invokevirtual 301	us$a:a	()Lus;
    //   555: astore_1
    //   556: aload_1
    //   557: ldc_w 303
    //   560: invokevirtual 306	us:a	(Ljava/lang/String;)Ljava/lang/String;
    //   563: ifnull +1113 -> 1676
    //   566: iconst_1
    //   567: istore 36
    //   569: new 308	com/snapchat/android/analytics/framework/EasyMetric
    //   572: dup
    //   573: ldc_w 310
    //   576: invokespecial 311	com/snapchat/android/analytics/framework/EasyMetric:<init>	(Ljava/lang/String;)V
    //   579: ldc_w 313
    //   582: aload_1
    //   583: getfield 316	us:mNetworkType	Ljava/lang/String;
    //   586: invokevirtual 319	com/snapchat/android/analytics/framework/EasyMetric:a	(Ljava/lang/String;Ljava/lang/Object;)Lcom/snapchat/android/analytics/framework/EasyMetric;
    //   589: ldc_w 321
    //   592: aload_1
    //   593: invokevirtual 323	us:a	()Ljava/lang/String;
    //   596: invokevirtual 319	com/snapchat/android/analytics/framework/EasyMetric:a	(Ljava/lang/String;Ljava/lang/Object;)Lcom/snapchat/android/analytics/framework/EasyMetric;
    //   599: ldc_w 325
    //   602: aload_1
    //   603: invokevirtual 326	us:b	()Ljava/lang/String;
    //   606: invokevirtual 319	com/snapchat/android/analytics/framework/EasyMetric:a	(Ljava/lang/String;Ljava/lang/Object;)Lcom/snapchat/android/analytics/framework/EasyMetric;
    //   609: ldc_w 328
    //   612: lload 19
    //   614: invokestatic 334	java/lang/Long:valueOf	(J)Ljava/lang/Long;
    //   617: invokevirtual 319	com/snapchat/android/analytics/framework/EasyMetric:a	(Ljava/lang/String;Ljava/lang/Object;)Lcom/snapchat/android/analytics/framework/EasyMetric;
    //   620: ldc_w 336
    //   623: lload 17
    //   625: invokestatic 334	java/lang/Long:valueOf	(J)Ljava/lang/Long;
    //   628: invokevirtual 319	com/snapchat/android/analytics/framework/EasyMetric:a	(Ljava/lang/String;Ljava/lang/Object;)Lcom/snapchat/android/analytics/framework/EasyMetric;
    //   631: ldc_w 338
    //   634: aload_1
    //   635: getfield 342	us:mResponseCode	I
    //   638: invokestatic 347	java/lang/Integer:valueOf	(I)Ljava/lang/Integer;
    //   641: invokevirtual 319	com/snapchat/android/analytics/framework/EasyMetric:a	(Ljava/lang/String;Ljava/lang/Object;)Lcom/snapchat/android/analytics/framework/EasyMetric;
    //   644: ldc_w 349
    //   647: lload 9
    //   649: invokestatic 334	java/lang/Long:valueOf	(J)Ljava/lang/Long;
    //   652: invokevirtual 319	com/snapchat/android/analytics/framework/EasyMetric:a	(Ljava/lang/String;Ljava/lang/Object;)Lcom/snapchat/android/analytics/framework/EasyMetric;
    //   655: ldc_w 351
    //   658: lload 11
    //   660: invokestatic 334	java/lang/Long:valueOf	(J)Ljava/lang/Long;
    //   663: invokevirtual 319	com/snapchat/android/analytics/framework/EasyMetric:a	(Ljava/lang/String;Ljava/lang/Object;)Lcom/snapchat/android/analytics/framework/EasyMetric;
    //   666: ldc_w 353
    //   669: lload 15
    //   671: invokestatic 334	java/lang/Long:valueOf	(J)Ljava/lang/Long;
    //   674: invokevirtual 319	com/snapchat/android/analytics/framework/EasyMetric:a	(Ljava/lang/String;Ljava/lang/Object;)Lcom/snapchat/android/analytics/framework/EasyMetric;
    //   677: ldc_w 355
    //   680: iload 36
    //   682: invokestatic 360	java/lang/Boolean:valueOf	(Z)Ljava/lang/Boolean;
    //   685: invokevirtual 319	com/snapchat/android/analytics/framework/EasyMetric:a	(Ljava/lang/String;Ljava/lang/Object;)Lcom/snapchat/android/analytics/framework/EasyMetric;
    //   688: ldc_w 362
    //   691: aload 5
    //   693: invokevirtual 319	com/snapchat/android/analytics/framework/EasyMetric:a	(Ljava/lang/String;Ljava/lang/Object;)Lcom/snapchat/android/analytics/framework/EasyMetric;
    //   696: ldc_w 364
    //   699: aload_3
    //   700: invokevirtual 319	com/snapchat/android/analytics/framework/EasyMetric:a	(Ljava/lang/String;Ljava/lang/Object;)Lcom/snapchat/android/analytics/framework/EasyMetric;
    //   703: ldc_w 366
    //   706: iload 35
    //   708: invokestatic 360	java/lang/Boolean:valueOf	(Z)Ljava/lang/Boolean;
    //   711: invokevirtual 319	com/snapchat/android/analytics/framework/EasyMetric:a	(Ljava/lang/String;Ljava/lang/Object;)Lcom/snapchat/android/analytics/framework/EasyMetric;
    //   714: astore_2
    //   715: aload_2
    //   716: aload 4
    //   718: invokestatic 369	uy:a	(Lcom/snapchat/android/analytics/framework/EasyMetric;Ljava/lang/String;)V
    //   721: aload_2
    //   722: iconst_0
    //   723: invokevirtual 372	com/snapchat/android/analytics/framework/EasyMetric:a	(Z)V
    //   726: aload_1
    //   727: areturn
    //   728: iconst_0
    //   729: istore 7
    //   731: goto -646 -> 85
    //   734: iconst_0
    //   735: istore 35
    //   737: goto -629 -> 108
    //   740: aload 37
    //   742: astore 42
    //   744: aload 46
    //   746: ldc_w 374
    //   749: invokeinterface 378 2 0
    //   754: checkcast 116	java/lang/String
    //   757: astore 40
    //   759: aload 37
    //   761: astore 42
    //   763: new 206	us$a
    //   766: dup
    //   767: aload_3
    //   768: invokestatic 211	bgp:b	()Ljava/lang/String;
    //   771: invokespecial 214	us$a:<init>	(Ljava/lang/String;Ljava/lang/String;)V
    //   774: astore 39
    //   776: aload 37
    //   778: astore 42
    //   780: aload 49
    //   782: getfield 383	bnd:c	I
    //   785: istore 6
    //   787: iload 6
    //   789: sipush 499
    //   792: if_icmpne +76 -> 868
    //   795: iload 7
    //   797: ifeq +71 -> 868
    //   800: aload 37
    //   802: astore 42
    //   804: aload_0
    //   805: getfield 63	ut:mGoogleAuthManager	Lmp;
    //   808: invokevirtual 385	mp:c	()V
    //   811: aload 37
    //   813: astore 42
    //   815: new 70	java/lang/StringBuilder
    //   818: dup
    //   819: ldc_w 387
    //   822: invokespecial 75	java/lang/StringBuilder:<init>	(Ljava/lang/String;)V
    //   825: aload_2
    //   826: invokevirtual 390	java/lang/StringBuilder:append	(Ljava/lang/Object;)Ljava/lang/StringBuilder;
    //   829: ldc_w 392
    //   832: invokevirtual 79	java/lang/StringBuilder:append	(Ljava/lang/String;)Ljava/lang/StringBuilder;
    //   835: aload_3
    //   836: invokevirtual 79	java/lang/StringBuilder:append	(Ljava/lang/String;)Ljava/lang/StringBuilder;
    //   839: invokevirtual 83	java/lang/StringBuilder:toString	()Ljava/lang/String;
    //   842: aload 40
    //   844: invokestatic 394	ut:a	(Ljava/lang/String;Ljava/lang/String;)Ljava/lang/String;
    //   847: pop
    //   848: iconst_1
    //   849: istore 6
    //   851: aload 39
    //   853: astore_1
    //   854: aload 40
    //   856: astore 39
    //   858: aload 38
    //   860: astore 40
    //   862: aload_3
    //   863: astore 38
    //   865: goto -734 -> 131
    //   868: aload 37
    //   870: astore 42
    //   872: new 8	ut$1
    //   875: dup
    //   876: aload_0
    //   877: aload 49
    //   879: invokespecial 397	ut$1:<init>	(Lut;Lbnd;)V
    //   882: astore_1
    //   883: aload 37
    //   885: astore 42
    //   887: new 399	vf
    //   890: dup
    //   891: invokespecial 400	vf:<init>	()V
    //   894: astore 45
    //   896: aload 37
    //   898: astore 42
    //   900: aload 49
    //   902: getfield 404	bnd:g	Lbne;
    //   905: ifnonnull +663 -> 1568
    //   908: aconst_null
    //   909: astore 43
    //   911: aload 37
    //   913: astore 42
    //   915: aload 49
    //   917: getfield 406	bnd:d	Ljava/lang/String;
    //   920: astore 44
    //   922: aload 37
    //   924: astore 42
    //   926: new 408	ux
    //   929: dup
    //   930: aload 49
    //   932: getfield 412	bnd:f	Lbmv;
    //   935: invokespecial 415	ux:<init>	(Lbmv;)V
    //   938: astore 50
    //   940: aload 37
    //   942: astore 42
    //   944: aload 49
    //   946: getfield 418	bnd:b	Lbna;
    //   949: ifnonnull +653 -> 1602
    //   952: ldc -55
    //   954: astore_1
    //   955: aload 37
    //   957: astore 42
    //   959: aload 48
    //   961: getfield 423	bnb:d	Lbnc;
    //   964: ifnull +1244 -> 2208
    //   967: aload 37
    //   969: astore 42
    //   971: aload 48
    //   973: getfield 423	bnb:d	Lbnc;
    //   976: invokevirtual 427	bnc:b	()J
    //   979: lstore 17
    //   981: lload 17
    //   983: lstore 9
    //   985: aload 37
    //   987: astore 42
    //   989: aload 39
    //   991: aload 40
    //   993: putfield 430	us$a:mRequestId	Ljava/lang/String;
    //   996: aload 37
    //   998: astore 42
    //   1000: aload 39
    //   1002: iload 6
    //   1004: putfield 431	us$a:mResponseCode	I
    //   1007: aload 37
    //   1009: astore 42
    //   1011: aload 39
    //   1013: aload 44
    //   1015: putfield 434	us$a:mResponseMessage	Ljava/lang/String;
    //   1018: aload 37
    //   1020: astore 42
    //   1022: aload 39
    //   1024: aload 50
    //   1026: putfield 438	us$a:mResponseHeaders	Lux;
    //   1029: aload 43
    //   1031: ifnull +1174 -> 2205
    //   1034: aload 37
    //   1036: astore 42
    //   1038: aload 43
    //   1040: invokevirtual 443	bne:c	()Ljava/io/InputStream;
    //   1043: astore 41
    //   1045: aload 4
    //   1047: aload 41
    //   1049: invokeinterface 448 2 0
    //   1054: istore 8
    //   1056: iload 8
    //   1058: i2l
    //   1059: lstore 15
    //   1061: aload 41
    //   1063: astore 37
    //   1065: lload 11
    //   1067: lstore 25
    //   1069: lload 13
    //   1071: lstore 19
    //   1073: lload 11
    //   1075: lstore 27
    //   1077: lload 13
    //   1079: lstore 21
    //   1081: lload 11
    //   1083: lstore 23
    //   1085: lload 13
    //   1087: lstore 17
    //   1089: aload 39
    //   1091: aload 4
    //   1093: putfield 452	us$a:mBuffer	Lbgk;
    //   1096: lload 11
    //   1098: lstore 25
    //   1100: lload 13
    //   1102: lstore 19
    //   1104: lload 11
    //   1106: lstore 27
    //   1108: lload 13
    //   1110: lstore 21
    //   1112: lload 11
    //   1114: lstore 23
    //   1116: lload 13
    //   1118: lstore 17
    //   1120: invokestatic 199	android/os/SystemClock:elapsedRealtime	()J
    //   1123: lload 33
    //   1125: lsub
    //   1126: lstore 29
    //   1128: lload 11
    //   1130: lstore 25
    //   1132: lload 13
    //   1134: lstore 19
    //   1136: lload 11
    //   1138: lstore 27
    //   1140: lload 13
    //   1142: lstore 21
    //   1144: lload 11
    //   1146: lstore 23
    //   1148: lload 13
    //   1150: lstore 17
    //   1152: aload 45
    //   1154: getfield 456	vf:mIsReceived	Z
    //   1157: ifeq +461 -> 1618
    //   1160: lload 11
    //   1162: lstore 25
    //   1164: lload 13
    //   1166: lstore 19
    //   1168: lload 11
    //   1170: lstore 27
    //   1172: lload 13
    //   1174: lstore 21
    //   1176: lload 11
    //   1178: lstore 23
    //   1180: lload 13
    //   1182: lstore 17
    //   1184: aload 45
    //   1186: getfield 460	vf:mFirstByteReceivedElapsedRealtimeInMillis	J
    //   1189: lload 33
    //   1191: lsub
    //   1192: lstore 13
    //   1194: lload 11
    //   1196: lstore 25
    //   1198: lload 13
    //   1200: lstore 19
    //   1202: lload 11
    //   1204: lstore 27
    //   1206: lload 13
    //   1208: lstore 21
    //   1210: lload 11
    //   1212: lstore 23
    //   1214: lload 13
    //   1216: lstore 17
    //   1218: aload 45
    //   1220: getfield 463	vf:mFirstByteSize	J
    //   1223: lstore 11
    //   1225: lload 11
    //   1227: lstore 25
    //   1229: lload 13
    //   1231: lstore 19
    //   1233: lload 11
    //   1235: lstore 27
    //   1237: lload 13
    //   1239: lstore 21
    //   1241: lload 11
    //   1243: lstore 23
    //   1245: lload 13
    //   1247: lstore 17
    //   1249: aload 39
    //   1251: lload 15
    //   1253: putfield 466	us$a:mResponseBodySize	J
    //   1256: lload 11
    //   1258: lstore 25
    //   1260: lload 13
    //   1262: lstore 19
    //   1264: lload 11
    //   1266: lstore 27
    //   1268: lload 13
    //   1270: lstore 21
    //   1272: lload 11
    //   1274: lstore 23
    //   1276: lload 13
    //   1278: lstore 17
    //   1280: aload 47
    //   1282: lload 15
    //   1284: lload 9
    //   1286: invokevirtual 469	tz:a	(JJ)V
    //   1289: lload 11
    //   1291: lstore 25
    //   1293: lload 13
    //   1295: lstore 19
    //   1297: lload 11
    //   1299: lstore 27
    //   1301: lload 13
    //   1303: lstore 21
    //   1305: lload 11
    //   1307: lstore 23
    //   1309: lload 13
    //   1311: lstore 17
    //   1313: aload 47
    //   1315: aload_2
    //   1316: invokevirtual 128	com/snapchat/android/api2/framework/HttpMethod:toString	()Ljava/lang/String;
    //   1319: aload_3
    //   1320: aload 44
    //   1322: iload 6
    //   1324: lload 31
    //   1326: lload 29
    //   1328: invokevirtual 472	tz:a	(Ljava/lang/String;Ljava/lang/String;Ljava/lang/String;IJJ)V
    //   1331: aconst_null
    //   1332: astore 41
    //   1334: lload 11
    //   1336: lstore 25
    //   1338: lload 13
    //   1340: lstore 19
    //   1342: lload 11
    //   1344: lstore 27
    //   1346: lload 13
    //   1348: lstore 21
    //   1350: lload 11
    //   1352: lstore 23
    //   1354: lload 13
    //   1356: lstore 17
    //   1358: aload 50
    //   1360: ldc_w 474
    //   1363: invokevirtual 477	ux:a	(Ljava/lang/String;)Ljava/util/List;
    //   1366: astore 42
    //   1368: lload 11
    //   1370: lstore 25
    //   1372: lload 13
    //   1374: lstore 19
    //   1376: lload 11
    //   1378: lstore 27
    //   1380: lload 13
    //   1382: lstore 21
    //   1384: lload 11
    //   1386: lstore 23
    //   1388: lload 13
    //   1390: lstore 17
    //   1392: aload 42
    //   1394: invokeinterface 483 1 0
    //   1399: iconst_1
    //   1400: if_icmpne +40 -> 1440
    //   1403: lload 11
    //   1405: lstore 25
    //   1407: lload 13
    //   1409: lstore 19
    //   1411: lload 11
    //   1413: lstore 27
    //   1415: lload 13
    //   1417: lstore 21
    //   1419: lload 11
    //   1421: lstore 23
    //   1423: lload 13
    //   1425: lstore 17
    //   1427: aload 42
    //   1429: iconst_0
    //   1430: invokeinterface 486 2 0
    //   1435: checkcast 116	java/lang/String
    //   1438: astore 41
    //   1440: lload 11
    //   1442: lstore 25
    //   1444: lload 13
    //   1446: lstore 19
    //   1448: lload 11
    //   1450: lstore 27
    //   1452: lload 13
    //   1454: lstore 21
    //   1456: lload 11
    //   1458: lstore 23
    //   1460: lload 13
    //   1462: lstore 17
    //   1464: ldc_w 488
    //   1467: bipush 8
    //   1469: anewarray 4	java/lang/Object
    //   1472: dup
    //   1473: iconst_0
    //   1474: aload_2
    //   1475: aastore
    //   1476: dup
    //   1477: iconst_1
    //   1478: aload_3
    //   1479: aastore
    //   1480: dup
    //   1481: iconst_2
    //   1482: lload 15
    //   1484: invokestatic 334	java/lang/Long:valueOf	(J)Ljava/lang/Long;
    //   1487: aastore
    //   1488: dup
    //   1489: iconst_3
    //   1490: iload 6
    //   1492: invokestatic 347	java/lang/Integer:valueOf	(I)Ljava/lang/Integer;
    //   1495: aastore
    //   1496: dup
    //   1497: iconst_4
    //   1498: aload 44
    //   1500: aastore
    //   1501: dup
    //   1502: iconst_5
    //   1503: lload 31
    //   1505: invokestatic 334	java/lang/Long:valueOf	(J)Ljava/lang/Long;
    //   1508: aastore
    //   1509: dup
    //   1510: bipush 6
    //   1512: lload 29
    //   1514: invokestatic 334	java/lang/Long:valueOf	(J)Ljava/lang/Long;
    //   1517: aastore
    //   1518: dup
    //   1519: bipush 7
    //   1521: aload 41
    //   1523: aastore
    //   1524: invokestatic 173	java/lang/String:format	(Ljava/lang/String;[Ljava/lang/Object;)Ljava/lang/String;
    //   1527: aload 40
    //   1529: invokestatic 394	ut:a	(Ljava/lang/String;Ljava/lang/String;)Ljava/lang/String;
    //   1532: pop
    //   1533: iconst_0
    //   1534: istore 6
    //   1536: aload 40
    //   1538: astore 41
    //   1540: aload_1
    //   1541: astore 42
    //   1543: lload 29
    //   1545: lstore 17
    //   1547: aload 38
    //   1549: astore 40
    //   1551: aload 39
    //   1553: astore_1
    //   1554: aload_3
    //   1555: astore 38
    //   1557: aload 41
    //   1559: astore 39
    //   1561: aload 42
    //   1563: astore 41
    //   1565: goto -1434 -> 131
    //   1568: aload 37
    //   1570: astore 42
    //   1572: new 490	uv
    //   1575: dup
    //   1576: aload 49
    //   1578: getfield 404	bnd:g	Lbne;
    //   1581: iconst_2
    //   1582: anewarray 492	vg
    //   1585: dup
    //   1586: iconst_0
    //   1587: aload_1
    //   1588: aastore
    //   1589: dup
    //   1590: iconst_1
    //   1591: aload 45
    //   1593: aastore
    //   1594: invokespecial 495	uv:<init>	(Lbne;[Lvg;)V
    //   1597: astore 43
    //   1599: goto -688 -> 911
    //   1602: aload 37
    //   1604: astore 42
    //   1606: aload 49
    //   1608: getfield 418	bnd:b	Lbna;
    //   1611: invokevirtual 498	bna:toString	()Ljava/lang/String;
    //   1614: astore_1
    //   1615: goto -660 -> 955
    //   1618: lload 15
    //   1620: lstore 11
    //   1622: lload 29
    //   1624: lstore 13
    //   1626: goto -401 -> 1225
    //   1629: aload 37
    //   1631: invokestatic 298	org/apache/commons/io/IOUtils:closeQuietly	(Ljava/io/InputStream;)V
    //   1634: aload 40
    //   1636: astore 4
    //   1638: aload 39
    //   1640: astore_3
    //   1641: lload 9
    //   1643: lstore 19
    //   1645: lload 11
    //   1647: lstore 9
    //   1649: aload 41
    //   1651: astore 5
    //   1653: lload 19
    //   1655: lstore 11
    //   1657: lload 13
    //   1659: lstore 19
    //   1661: goto -1110 -> 551
    //   1664: astore_1
    //   1665: aload 37
    //   1667: astore 42
    //   1669: aload 42
    //   1671: invokestatic 298	org/apache/commons/io/IOUtils:closeQuietly	(Ljava/io/InputStream;)V
    //   1674: aload_1
    //   1675: athrow
    //   1676: iconst_0
    //   1677: istore 36
    //   1679: goto -1110 -> 569
    //   1682: astore 42
    //   1684: aload 38
    //   1686: astore 4
    //   1688: lload 19
    //   1690: lstore 13
    //   1692: lload 25
    //   1694: lstore 11
    //   1696: aload_1
    //   1697: astore 41
    //   1699: aload_3
    //   1700: astore 5
    //   1702: aload 37
    //   1704: astore_1
    //   1705: aload 39
    //   1707: astore 37
    //   1709: aload 42
    //   1711: astore_3
    //   1712: aload_1
    //   1713: astore 42
    //   1715: lload 11
    //   1717: lstore 17
    //   1719: lload 13
    //   1721: lstore 19
    //   1723: lload 15
    //   1725: lstore 13
    //   1727: aload 5
    //   1729: astore 39
    //   1731: aload_3
    //   1732: astore 38
    //   1734: aload 37
    //   1736: astore_1
    //   1737: aload 40
    //   1739: astore_3
    //   1740: aload 41
    //   1742: astore 5
    //   1744: lload 9
    //   1746: lstore 11
    //   1748: lload 17
    //   1750: lstore 15
    //   1752: lload 19
    //   1754: lstore 9
    //   1756: aload 42
    //   1758: astore 37
    //   1760: goto -1289 -> 471
    //   1763: astore 4
    //   1765: lload 21
    //   1767: lstore 13
    //   1769: lload 27
    //   1771: lstore 11
    //   1773: aload_1
    //   1774: astore 41
    //   1776: aload 4
    //   1778: astore_1
    //   1779: aload_1
    //   1780: astore 42
    //   1782: aload 38
    //   1784: astore 4
    //   1786: lload 11
    //   1788: lstore 17
    //   1790: lload 9
    //   1792: lstore 11
    //   1794: aload 39
    //   1796: astore_1
    //   1797: lload 13
    //   1799: lstore 9
    //   1801: aload_3
    //   1802: astore 39
    //   1804: aload 41
    //   1806: astore 5
    //   1808: lload 15
    //   1810: lstore 13
    //   1812: aload 40
    //   1814: astore_3
    //   1815: aload 42
    //   1817: astore 38
    //   1819: lload 17
    //   1821: lstore 15
    //   1823: goto -1352 -> 471
    //   1826: astore_1
    //   1827: goto -158 -> 1669
    //   1830: astore_1
    //   1831: aload 41
    //   1833: astore 42
    //   1835: goto -166 -> 1669
    //   1838: astore 4
    //   1840: aload_1
    //   1841: astore 41
    //   1843: aload 4
    //   1845: astore_1
    //   1846: lload 23
    //   1848: lstore 11
    //   1850: lload 17
    //   1852: lstore 13
    //   1854: goto -1427 -> 427
    //   1857: astore_3
    //   1858: aload_1
    //   1859: astore 4
    //   1861: aload 40
    //   1863: astore 38
    //   1865: aload_3
    //   1866: astore_1
    //   1867: aload 43
    //   1869: astore_3
    //   1870: aload 39
    //   1872: astore 40
    //   1874: aload 4
    //   1876: astore 39
    //   1878: goto -1451 -> 427
    //   1881: astore 4
    //   1883: aload_1
    //   1884: astore 39
    //   1886: aload 4
    //   1888: astore_1
    //   1889: goto -1462 -> 427
    //   1892: astore 4
    //   1894: aload_1
    //   1895: astore 41
    //   1897: aload 4
    //   1899: astore_1
    //   1900: goto -1473 -> 427
    //   1903: astore 4
    //   1905: aload_1
    //   1906: astore 41
    //   1908: aload 4
    //   1910: astore_1
    //   1911: goto -1484 -> 427
    //   1914: astore 4
    //   1916: aload 41
    //   1918: astore 37
    //   1920: aload_1
    //   1921: astore 41
    //   1923: aload 4
    //   1925: astore_1
    //   1926: goto -1499 -> 427
    //   1929: astore_3
    //   1930: aload_1
    //   1931: astore 4
    //   1933: aload 40
    //   1935: astore 38
    //   1937: aload_3
    //   1938: astore_1
    //   1939: aload 44
    //   1941: astore_3
    //   1942: aload 39
    //   1944: astore 40
    //   1946: aload 4
    //   1948: astore 39
    //   1950: goto -171 -> 1779
    //   1953: astore 5
    //   1955: aload_1
    //   1956: astore 4
    //   1958: aload 5
    //   1960: astore_1
    //   1961: aload 39
    //   1963: astore 40
    //   1965: aload 4
    //   1967: astore 39
    //   1969: goto -190 -> 1779
    //   1972: astore 4
    //   1974: aload_1
    //   1975: astore 39
    //   1977: aload 4
    //   1979: astore_1
    //   1980: goto -201 -> 1779
    //   1983: astore_1
    //   1984: goto -205 -> 1779
    //   1987: astore 4
    //   1989: aload_1
    //   1990: astore 41
    //   1992: aload 4
    //   1994: astore_1
    //   1995: goto -216 -> 1779
    //   1998: astore 4
    //   2000: aload_1
    //   2001: astore 41
    //   2003: aload 4
    //   2005: astore_1
    //   2006: goto -227 -> 1779
    //   2009: astore 4
    //   2011: aload 41
    //   2013: astore 37
    //   2015: aload_1
    //   2016: astore 41
    //   2018: aload 4
    //   2020: astore_1
    //   2021: goto -242 -> 1779
    //   2024: astore_3
    //   2025: aload 45
    //   2027: astore 5
    //   2029: aload 37
    //   2031: astore 38
    //   2033: aload 40
    //   2035: astore 4
    //   2037: aload_1
    //   2038: astore 37
    //   2040: aload 38
    //   2042: astore_1
    //   2043: aload 39
    //   2045: astore 40
    //   2047: goto -335 -> 1712
    //   2050: astore 40
    //   2052: aload 38
    //   2054: astore 4
    //   2056: aload_3
    //   2057: astore 5
    //   2059: aload 37
    //   2061: astore 38
    //   2063: aload 40
    //   2065: astore_3
    //   2066: aload_1
    //   2067: astore 37
    //   2069: aload 38
    //   2071: astore_1
    //   2072: aload 39
    //   2074: astore 40
    //   2076: goto -364 -> 1712
    //   2079: astore 39
    //   2081: aload 38
    //   2083: astore 4
    //   2085: aload_3
    //   2086: astore 5
    //   2088: aload 37
    //   2090: astore 38
    //   2092: aload 39
    //   2094: astore_3
    //   2095: aload_1
    //   2096: astore 37
    //   2098: aload 38
    //   2100: astore_1
    //   2101: goto -389 -> 1712
    //   2104: astore 42
    //   2106: aload 38
    //   2108: astore 4
    //   2110: aload_3
    //   2111: astore 5
    //   2113: aload 37
    //   2115: astore_1
    //   2116: aload 42
    //   2118: astore_3
    //   2119: aload 39
    //   2121: astore 37
    //   2123: goto -411 -> 1712
    //   2126: astore 42
    //   2128: aload 38
    //   2130: astore 4
    //   2132: aload_1
    //   2133: astore 41
    //   2135: aload_3
    //   2136: astore 5
    //   2138: aload 37
    //   2140: astore_1
    //   2141: aload 42
    //   2143: astore_3
    //   2144: aload 39
    //   2146: astore 37
    //   2148: goto -436 -> 1712
    //   2151: astore 42
    //   2153: aload 38
    //   2155: astore 4
    //   2157: aload_1
    //   2158: astore 41
    //   2160: aload_3
    //   2161: astore 5
    //   2163: aload 37
    //   2165: astore_1
    //   2166: aload 42
    //   2168: astore_3
    //   2169: aload 39
    //   2171: astore 37
    //   2173: goto -461 -> 1712
    //   2176: astore 42
    //   2178: aload 38
    //   2180: astore 4
    //   2182: aload_1
    //   2183: astore 38
    //   2185: aload_3
    //   2186: astore 5
    //   2188: aload 41
    //   2190: astore_1
    //   2191: aload 39
    //   2193: astore 37
    //   2195: aload 42
    //   2197: astore_3
    //   2198: aload 38
    //   2200: astore 41
    //   2202: goto -490 -> 1712
    //   2205: goto -1140 -> 1065
    //   2208: goto -1223 -> 985
    //   2211: iconst_1
    //   2212: istore 6
    //   2214: ldc -55
    //   2216: astore 39
    //   2218: aconst_null
    //   2219: astore 40
    //   2221: aload_3
    //   2222: astore 46
    //   2224: goto -2093 -> 131
    //   2227: astore_1
    //   2228: goto -1801 -> 427
    // Local variable table:
    //   start	length	slot	name	signature
    //   0	2231	0	this	ut
    //   0	2231	1	paramString	String
    //   0	2231	2	paramHttpMethod	HttpMethod
    //   0	2231	3	paramMap	Map<String, String>
    //   0	2231	4	parambgk	bgk
    //   0	2231	5	paramObject	Object
    //   122	2091	6	i	int
    //   83	713	7	j	int
    //   1054	3	8	k	int
    //   33	1767	9	l1	long
    //   27	1822	11	l2	long
    //   24	1829	13	l3	long
    //   30	1792	15	l4	long
    //   21	1830	17	l5	long
    //   541	1212	19	l6	long
    //   1079	687	21	l7	long
    //   1083	764	23	l8	long
    //   1067	626	25	l9	long
    //   1075	695	27	l10	long
    //   1126	497	29	l11	long
    //   13	1491	31	l12	long
    //   18	1172	33	l13	long
    //   106	630	35	bool1	boolean
    //   567	1111	36	bool2	boolean
    //   40	2154	37	localObject1	Object
    //   8	2191	38	localObject2	Object
    //   126	1947	39	localObject3	Object
    //   2079	113	39	localIllegalArgumentException1	IllegalArgumentException
    //   2216	1	39	str	String
    //   129	1917	40	localObject4	Object
    //   2050	14	40	localIllegalArgumentException2	IllegalArgumentException
    //   2074	146	40	localObject5	Object
    //   37	2164	41	localObject6	Object
    //   143	1527	42	localObject7	Object
    //   1682	28	42	localIllegalArgumentException3	IllegalArgumentException
    //   1713	121	42	localObject8	Object
    //   2104	13	42	localIllegalArgumentException4	IllegalArgumentException
    //   2126	16	42	localIllegalArgumentException5	IllegalArgumentException
    //   2151	16	42	localIllegalArgumentException6	IllegalArgumentException
    //   2176	20	42	localIllegalArgumentException7	IllegalArgumentException
    //   147	1721	43	localObject9	Object
    //   151	1789	44	localObject10	Object
    //   155	1871	45	localObject11	Object
    //   119	2104	46	localObject12	Object
    //   49	1265	47	localtz	tz
    //   328	644	48	localbnb	bnb
    //   370	1237	49	localbnd	bnd
    //   305	1054	50	localObject13	Object
    // Exception table:
    //   from	to	target	type
    //   396	403	415	java/io/IOException
    //   412	415	415	java/io/IOException
    //   744	759	415	java/io/IOException
    //   1089	1096	1664	finally
    //   1120	1128	1664	finally
    //   1152	1160	1664	finally
    //   1184	1194	1664	finally
    //   1218	1225	1664	finally
    //   1249	1256	1664	finally
    //   1280	1289	1664	finally
    //   1313	1331	1664	finally
    //   1358	1368	1664	finally
    //   1392	1403	1664	finally
    //   1427	1440	1664	finally
    //   1464	1533	1664	finally
    //   1089	1096	1682	java/lang/IllegalArgumentException
    //   1120	1128	1682	java/lang/IllegalArgumentException
    //   1152	1160	1682	java/lang/IllegalArgumentException
    //   1184	1194	1682	java/lang/IllegalArgumentException
    //   1218	1225	1682	java/lang/IllegalArgumentException
    //   1249	1256	1682	java/lang/IllegalArgumentException
    //   1280	1289	1682	java/lang/IllegalArgumentException
    //   1313	1331	1682	java/lang/IllegalArgumentException
    //   1358	1368	1682	java/lang/IllegalArgumentException
    //   1392	1403	1682	java/lang/IllegalArgumentException
    //   1427	1440	1682	java/lang/IllegalArgumentException
    //   1464	1533	1682	java/lang/IllegalArgumentException
    //   1089	1096	1763	java/lang/IllegalStateException
    //   1120	1128	1763	java/lang/IllegalStateException
    //   1152	1160	1763	java/lang/IllegalStateException
    //   1184	1194	1763	java/lang/IllegalStateException
    //   1218	1225	1763	java/lang/IllegalStateException
    //   1249	1256	1763	java/lang/IllegalStateException
    //   1280	1289	1763	java/lang/IllegalStateException
    //   1313	1331	1763	java/lang/IllegalStateException
    //   1358	1368	1763	java/lang/IllegalStateException
    //   1392	1403	1763	java/lang/IllegalStateException
    //   1427	1440	1763	java/lang/IllegalStateException
    //   1464	1533	1763	java/lang/IllegalStateException
    //   157	189	1826	finally
    //   205	213	1826	finally
    //   233	244	1826	finally
    //   260	272	1826	finally
    //   288	307	1826	finally
    //   323	330	1826	finally
    //   346	352	1826	finally
    //   365	372	1826	finally
    //   385	392	1826	finally
    //   396	403	1826	finally
    //   412	415	1826	finally
    //   475	481	1826	finally
    //   485	490	1826	finally
    //   494	502	1826	finally
    //   506	524	1826	finally
    //   528	534	1826	finally
    //   744	759	1826	finally
    //   763	776	1826	finally
    //   780	787	1826	finally
    //   804	811	1826	finally
    //   815	848	1826	finally
    //   872	883	1826	finally
    //   887	896	1826	finally
    //   900	908	1826	finally
    //   915	922	1826	finally
    //   926	940	1826	finally
    //   944	952	1826	finally
    //   959	967	1826	finally
    //   971	981	1826	finally
    //   989	996	1826	finally
    //   1000	1007	1826	finally
    //   1011	1018	1826	finally
    //   1022	1029	1826	finally
    //   1038	1045	1826	finally
    //   1572	1599	1826	finally
    //   1606	1615	1826	finally
    //   1045	1056	1830	finally
    //   1089	1096	1838	java/io/IOException
    //   1120	1128	1838	java/io/IOException
    //   1152	1160	1838	java/io/IOException
    //   1184	1194	1838	java/io/IOException
    //   1218	1225	1838	java/io/IOException
    //   1249	1256	1838	java/io/IOException
    //   1280	1289	1838	java/io/IOException
    //   1313	1331	1838	java/io/IOException
    //   1358	1368	1838	java/io/IOException
    //   1392	1403	1838	java/io/IOException
    //   1427	1440	1838	java/io/IOException
    //   1464	1533	1838	java/io/IOException
    //   157	189	1857	java/io/IOException
    //   205	213	1857	java/io/IOException
    //   233	244	1857	java/io/IOException
    //   260	272	1857	java/io/IOException
    //   288	307	1857	java/io/IOException
    //   323	330	1857	java/io/IOException
    //   346	352	1857	java/io/IOException
    //   365	372	1857	java/io/IOException
    //   385	392	1857	java/io/IOException
    //   763	776	1881	java/io/IOException
    //   959	967	1892	java/io/IOException
    //   971	981	1892	java/io/IOException
    //   989	996	1903	java/io/IOException
    //   1000	1007	1903	java/io/IOException
    //   1011	1018	1903	java/io/IOException
    //   1022	1029	1903	java/io/IOException
    //   1038	1045	1903	java/io/IOException
    //   1045	1056	1914	java/io/IOException
    //   157	189	1929	java/lang/IllegalStateException
    //   205	213	1929	java/lang/IllegalStateException
    //   233	244	1929	java/lang/IllegalStateException
    //   260	272	1929	java/lang/IllegalStateException
    //   288	307	1929	java/lang/IllegalStateException
    //   323	330	1929	java/lang/IllegalStateException
    //   346	352	1929	java/lang/IllegalStateException
    //   365	372	1929	java/lang/IllegalStateException
    //   385	392	1929	java/lang/IllegalStateException
    //   396	403	1953	java/lang/IllegalStateException
    //   412	415	1953	java/lang/IllegalStateException
    //   744	759	1953	java/lang/IllegalStateException
    //   763	776	1972	java/lang/IllegalStateException
    //   780	787	1983	java/lang/IllegalStateException
    //   804	811	1983	java/lang/IllegalStateException
    //   815	848	1983	java/lang/IllegalStateException
    //   872	883	1983	java/lang/IllegalStateException
    //   887	896	1983	java/lang/IllegalStateException
    //   900	908	1983	java/lang/IllegalStateException
    //   915	922	1983	java/lang/IllegalStateException
    //   926	940	1983	java/lang/IllegalStateException
    //   944	952	1983	java/lang/IllegalStateException
    //   1572	1599	1983	java/lang/IllegalStateException
    //   1606	1615	1983	java/lang/IllegalStateException
    //   959	967	1987	java/lang/IllegalStateException
    //   971	981	1987	java/lang/IllegalStateException
    //   989	996	1998	java/lang/IllegalStateException
    //   1000	1007	1998	java/lang/IllegalStateException
    //   1011	1018	1998	java/lang/IllegalStateException
    //   1022	1029	1998	java/lang/IllegalStateException
    //   1038	1045	1998	java/lang/IllegalStateException
    //   1045	1056	2009	java/lang/IllegalStateException
    //   157	189	2024	java/lang/IllegalArgumentException
    //   205	213	2024	java/lang/IllegalArgumentException
    //   233	244	2024	java/lang/IllegalArgumentException
    //   260	272	2024	java/lang/IllegalArgumentException
    //   288	307	2024	java/lang/IllegalArgumentException
    //   323	330	2024	java/lang/IllegalArgumentException
    //   346	352	2024	java/lang/IllegalArgumentException
    //   365	372	2024	java/lang/IllegalArgumentException
    //   385	392	2024	java/lang/IllegalArgumentException
    //   396	403	2050	java/lang/IllegalArgumentException
    //   412	415	2050	java/lang/IllegalArgumentException
    //   744	759	2050	java/lang/IllegalArgumentException
    //   763	776	2079	java/lang/IllegalArgumentException
    //   780	787	2104	java/lang/IllegalArgumentException
    //   804	811	2104	java/lang/IllegalArgumentException
    //   815	848	2104	java/lang/IllegalArgumentException
    //   872	883	2104	java/lang/IllegalArgumentException
    //   887	896	2104	java/lang/IllegalArgumentException
    //   900	908	2104	java/lang/IllegalArgumentException
    //   915	922	2104	java/lang/IllegalArgumentException
    //   926	940	2104	java/lang/IllegalArgumentException
    //   944	952	2104	java/lang/IllegalArgumentException
    //   1572	1599	2104	java/lang/IllegalArgumentException
    //   1606	1615	2104	java/lang/IllegalArgumentException
    //   959	967	2126	java/lang/IllegalArgumentException
    //   971	981	2126	java/lang/IllegalArgumentException
    //   989	996	2151	java/lang/IllegalArgumentException
    //   1000	1007	2151	java/lang/IllegalArgumentException
    //   1011	1018	2151	java/lang/IllegalArgumentException
    //   1022	1029	2151	java/lang/IllegalArgumentException
    //   1038	1045	2151	java/lang/IllegalArgumentException
    //   1045	1056	2176	java/lang/IllegalArgumentException
    //   780	787	2227	java/io/IOException
    //   804	811	2227	java/io/IOException
    //   815	848	2227	java/io/IOException
    //   872	883	2227	java/io/IOException
    //   887	896	2227	java/io/IOException
    //   900	908	2227	java/io/IOException
    //   915	922	2227	java/io/IOException
    //   926	940	2227	java/io/IOException
    //   944	952	2227	java/io/IOException
    //   1572	1599	2227	java/io/IOException
    //   1606	1615	2227	java/io/IOException
  }
}

/* Location:
 * Qualified Name:     ut
 * Java Class Version: 6 (50.0)
 * JD-Core Version:    0.7.1
 */