package kkkkkk;

import java.util.ArrayList;

public class kkxkkk
{
  private static ArrayList<xkkxkk> b043A043A043A043Aк043A;
  public static int b043A043Aкк043A043A = 47;
  public static int b043Aк043Aк043A043A = 1;
  private static int b043Aккк043A043A = 0;
  public static int bк043A043Aк043A043A = 2;
  private static boolean bк043Aкк043A043A = true;
  public static int bкк043Aк043A043A;
  private static ArrayList<xxkxxk> bкккк043A043A;
  
  static
  {
    int i = b043A043Aкк043A043A;
    switch (i * (b043Aк043Aк043A043A + i) % bКККК041AК())
    {
    default: 
      b043A043Aкк043A043A = bК041AК041AКК();
      bкк043Aк043A043A = 89;
    }
    b043Aккк043A043A = 24;
    switch (1)
    {
    case 0: 
    default: 
      for (;;)
      {
        switch (0)
        {
        }
      }
    }
  }
  
  private static void b041A041A041A041AКК()
  {
    throw new Runtime("d2j fail translate: java.lang.IndexOutOfBoundsException: fromIndex < 0: -1\n\tat java.util.BitSet.nextSetBit(BitSet.java:709)\n\tat com.googlecode.dex2jar.ir.ts.array.FillArrayTransformer.makeSureAllElementAreAssigned(FillArrayTransformer.java:505)\n\tat com.googlecode.dex2jar.ir.ts.array.FillArrayTransformer.transformReportChanged(FillArrayTransformer.java:123)\n\tat com.googlecode.dex2jar.ir.ts.StatedTransformer.transform(StatedTransformer.java:10)\n\tat com.googlecode.d2j.dex.Dex2jar$2.optimize(Dex2jar.java:149)\n\tat com.googlecode.d2j.dex.Dex2Asm.convertCode(Dex2Asm.java:414)\n\tat com.googlecode.d2j.dex.ExDex2Asm.convertCode(ExDex2Asm.java:42)\n\tat com.googlecode.d2j.dex.Dex2jar$2.convertCode(Dex2jar.java:128)\n\tat com.googlecode.d2j.dex.Dex2Asm.convertMethod(Dex2Asm.java:509)\n\tat com.googlecode.d2j.dex.Dex2Asm.convertClass(Dex2Asm.java:406)\n\tat com.googlecode.d2j.dex.Dex2Asm.convertDex(Dex2Asm.java:422)\n\tat com.googlecode.d2j.dex.Dex2jar.doTranslate(Dex2jar.java:172)\n\tat com.googlecode.d2j.dex.Dex2jar.to(Dex2jar.java:272)\n\tat com.googlecode.dex2jar.tools.Dex2jarCmd.doCommandLine(Dex2jarCmd.java:108)\n\tat com.googlecode.dex2jar.tools.BaseCmd.doMain(BaseCmd.java:288)\n\tat com.googlecode.dex2jar.tools.Dex2jarCmd.main(Dex2jarCmd.java:32)\n");
  }
  
  public static void b041A041AК041AКК(int paramInt)
  {
    if (paramInt <= 128)
    {
      i = paramInt;
      if (paramInt >= 0) {
        break label85;
      }
      paramInt = b043A043Aкк043A043A;
      i = b043Aк043Aк043A043A;
      int j = b043A043Aкк043A043A;
      int k = bк043A043Aк043A043A;
      if ((b043A043Aкк043A043A + b043Aк043Aк043A043A) * b043A043Aкк043A043A % bк043A043Aк043A043A != bкк043Aк043A043A)
      {
        b043A043Aкк043A043A = 80;
        bкк043Aк043A043A = 44;
      }
      if ((paramInt + i) * j % k != bкк043Aк043A043A)
      {
        b043A043Aкк043A043A = 11;
        bкк043Aк043A043A = 24;
      }
    }
    int i = 0;
    try
    {
      label85:
      b043Aккк043A043A = i;
      return;
    }
    catch (Exception localException)
    {
      switch (0)
      {
      case 1: 
      default: 
        for (;;)
        {
          switch (1)
          {
          }
        }
      }
      throw localException;
    }
  }
  
  public static String b041AК041A041AКК(String paramString, char paramChar1, char paramChar2, char paramChar3)
  {
    
    try
    {
      xxkxxk localxxkxxk = (xxkxxk)bкккк043A043A.get(paramChar3);
      if ((b043A043Aкк043A043A + bКК041A041AКК()) * b043A043Aкк043A043A % bк043A043Aк043A043A != bкк043Aк043A043A)
      {
        b043A043Aкк043A043A = 42;
        bкк043Aк043A043A = 3;
        paramChar3 = b043A043Aкк043A043A;
        switch (paramChar3 * (b043Aк043Aк043A043A + paramChar3) % bк043A043Aк043A043A)
        {
        default: 
          b043A043Aкк043A043A = 53;
          bкк043Aк043A043A = bК041AК041AКК();
        }
      }
      paramString = localxxkxxk.bК041A041A041A041AК(paramString, new Character(paramChar1).charValue(), new Character(paramChar2).charValue());
      switch (0)
      {
      case 1: 
      default: 
        for (;;)
        {
          switch (0)
          {
          }
        }
      }
      return paramString;
    }
    catch (Exception paramString) {}
    return new String("");
  }
  
  /* Error */
  public static String b041AКК041AКК(String paramString, char paramChar1, char paramChar2)
  {
    // Byte code:
    //   0: invokestatic 106	kkkkkk/kkxkkk:b041A041A041A041AКК	()V
    //   3: getstatic 138	kkkkkk/kkxkkk:b043A043A043A043Aк043A	Ljava/util/ArrayList;
    //   6: iload_2
    //   7: invokevirtual 114	java/util/ArrayList:get	(I)Ljava/lang/Object;
    //   10: checkcast 24	kkkkkk/xkkxkk
    //   13: astore_3
    //   14: getstatic 67	kkkkkk/kkxkkk:b043A043Aкк043A043A	I
    //   17: getstatic 69	kkkkkk/kkxkkk:b043Aк043Aк043A043A	I
    //   20: iadd
    //   21: getstatic 67	kkkkkk/kkxkkk:b043A043Aкк043A043A	I
    //   24: imul
    //   25: getstatic 102	kkkkkk/kkxkkk:bк043A043Aк043A043A	I
    //   28: irem
    //   29: getstatic 78	kkkkkk/kkxkkk:bкк043Aк043A043A	I
    //   32: if_icmpeq +58 -> 90
    //   35: getstatic 67	kkkkkk/kkxkkk:b043A043Aкк043A043A	I
    //   38: istore_2
    //   39: iload_2
    //   40: getstatic 69	kkkkkk/kkxkkk:b043Aк043Aк043A043A	I
    //   43: iload_2
    //   44: iadd
    //   45: imul
    //   46: invokestatic 73	kkkkkk/kkxkkk:bКККК041AК	()I
    //   49: irem
    //   50: tableswitch	default:+18->68, 0:+30->80
    //   68: invokestatic 76	kkkkkk/kkxkkk:bК041AК041AКК	()I
    //   71: putstatic 67	kkkkkk/kkxkkk:b043A043Aкк043A043A	I
    //   74: invokestatic 76	kkkkkk/kkxkkk:bК041AК041AКК	()I
    //   77: putstatic 78	kkkkkk/kkxkkk:bкк043Aк043A043A	I
    //   80: bipush 11
    //   82: putstatic 67	kkkkkk/kkxkkk:b043A043Aкк043A043A	I
    //   85: bipush 72
    //   87: putstatic 78	kkkkkk/kkxkkk:bкк043Aк043A043A	I
    //   90: aload_3
    //   91: aload_0
    //   92: new 119	java/lang/Character
    //   95: dup
    //   96: iload_1
    //   97: invokespecial 122	java/lang/Character:<init>	(C)V
    //   100: invokevirtual 126	java/lang/Character:charValue	()C
    //   103: invokevirtual 142	kkkkkk/xkkxkk:bК041A041AККК	(Ljava/lang/String;C)Ljava/lang/String;
    //   106: astore_0
    //   107: aload_0
    //   108: areturn
    //   109: astore_0
    //   110: aload_0
    //   111: athrow
    //   112: astore_0
    //   113: new 132	java/lang/String
    //   116: dup
    //   117: ldc -122
    //   119: invokespecial 135	java/lang/String:<init>	(Ljava/lang/String;)V
    //   122: astore_0
    //   123: aload_0
    //   124: areturn
    //   125: astore_0
    //   126: aload_0
    //   127: athrow
    // Local variable table:
    //   start	length	slot	name	signature
    //   0	128	0	paramString	String
    //   0	128	1	paramChar1	char
    //   0	128	2	paramChar2	char
    //   13	78	3	localxkkxkk	xkkxkk
    // Exception table:
    //   from	to	target	type
    //   113	123	109	java/lang/Exception
    //   3	14	112	java/lang/Exception
    //   90	107	112	java/lang/Exception
    //   0	3	125	java/lang/Exception
  }
  
  /* Error */
  public static String b041AККК041AК(String paramString, char paramChar1, char paramChar2, char paramChar3)
  {
    // Byte code:
    //   0: getstatic 67	kkkkkk/kkxkkk:b043A043Aкк043A043A	I
    //   3: istore 4
    //   5: getstatic 69	kkkkkk/kkxkkk:b043Aк043Aк043A043A	I
    //   8: istore 5
    //   10: iload 4
    //   12: iload 5
    //   14: iadd
    //   15: getstatic 67	kkkkkk/kkxkkk:b043A043Aкк043A043A	I
    //   18: imul
    //   19: getstatic 102	kkkkkk/kkxkkk:bк043A043Aк043A043A	I
    //   22: irem
    //   23: getstatic 78	kkkkkk/kkxkkk:bкк043Aк043A043A	I
    //   26: if_icmpeq +12 -> 38
    //   29: bipush 27
    //   31: putstatic 67	kkkkkk/kkxkkk:b043A043Aкк043A043A	I
    //   34: iconst_1
    //   35: putstatic 78	kkkkkk/kkxkkk:bкк043Aк043A043A	I
    //   38: aload_0
    //   39: iload_1
    //   40: iload_2
    //   41: iload_3
    //   42: invokestatic 145	kkkkkk/kkxkkk:b041AК041A041AКК	(Ljava/lang/String;CCC)Ljava/lang/String;
    //   45: astore_0
    //   46: invokestatic 76	kkkkkk/kkxkkk:bК041AК041AКК	()I
    //   49: getstatic 69	kkkkkk/kkxkkk:b043Aк043Aк043A043A	I
    //   52: iadd
    //   53: invokestatic 76	kkkkkk/kkxkkk:bК041AК041AКК	()I
    //   56: imul
    //   57: getstatic 102	kkkkkk/kkxkkk:bк043A043Aк043A043A	I
    //   60: irem
    //   61: getstatic 78	kkkkkk/kkxkkk:bкк043Aк043A043A	I
    //   64: if_icmpeq +14 -> 78
    //   67: bipush 13
    //   69: putstatic 67	kkkkkk/kkxkkk:b043A043Aкк043A043A	I
    //   72: invokestatic 76	kkkkkk/kkxkkk:bК041AК041AКК	()I
    //   75: putstatic 78	kkkkkk/kkxkkk:bкк043Aк043A043A	I
    //   78: aload_0
    //   79: invokevirtual 149	java/lang/String:intern	()Ljava/lang/String;
    //   82: astore_0
    //   83: aload_0
    //   84: areturn
    //   85: astore_0
    //   86: aload_0
    //   87: athrow
    //   88: astore_0
    //   89: aload_0
    //   90: athrow
    //   91: astore_0
    //   92: aload_0
    //   93: athrow
    // Local variable table:
    //   start	length	slot	name	signature
    //   0	94	0	paramString	String
    //   0	94	1	paramChar1	char
    //   0	94	2	paramChar2	char
    //   0	94	3	paramChar3	char
    //   3	12	4	i	int
    //   8	7	5	j	int
    // Exception table:
    //   from	to	target	type
    //   38	46	85	java/lang/Exception
    //   78	83	85	java/lang/Exception
    //   0	10	88	java/lang/Exception
    //   86	88	88	java/lang/Exception
    //   10	38	91	java/lang/Exception
  }
  
  /* Error */
  public static String bК041A041A041AКК(String paramString, char paramChar1, char paramChar2)
  {
    // Byte code:
    //   0: getstatic 67	kkkkkk/kkxkkk:b043A043Aкк043A043A	I
    //   3: getstatic 69	kkkkkk/kkxkkk:b043Aк043Aк043A043A	I
    //   6: iadd
    //   7: getstatic 67	kkkkkk/kkxkkk:b043A043Aкк043A043A	I
    //   10: imul
    //   11: getstatic 102	kkkkkk/kkxkkk:bк043A043Aк043A043A	I
    //   14: irem
    //   15: getstatic 78	kkkkkk/kkxkkk:bкк043Aк043A043A	I
    //   18: if_icmpeq +61 -> 79
    //   21: getstatic 67	kkkkkk/kkxkkk:b043A043Aкк043A043A	I
    //   24: istore_3
    //   25: iload_3
    //   26: getstatic 69	kkkkkk/kkxkkk:b043Aк043Aк043A043A	I
    //   29: iload_3
    //   30: iadd
    //   31: imul
    //   32: getstatic 102	kkkkkk/kkxkkk:bк043A043Aк043A043A	I
    //   35: irem
    //   36: tableswitch	default:+20->56, 0:+32->68
    //   56: invokestatic 76	kkkkkk/kkxkkk:bК041AК041AКК	()I
    //   59: putstatic 67	kkkkkk/kkxkkk:b043A043Aкк043A043A	I
    //   62: invokestatic 76	kkkkkk/kkxkkk:bК041AК041AКК	()I
    //   65: putstatic 78	kkkkkk/kkxkkk:bкк043Aк043A043A	I
    //   68: bipush 72
    //   70: putstatic 67	kkkkkk/kkxkkk:b043A043Aкк043A043A	I
    //   73: invokestatic 76	kkkkkk/kkxkkk:bК041AК041AКК	()I
    //   76: putstatic 78	kkkkkk/kkxkkk:bкк043Aк043A043A	I
    //   79: aload_0
    //   80: iload_1
    //   81: iload_2
    //   82: invokestatic 152	kkkkkk/kkxkkk:b041AКК041AКК	(Ljava/lang/String;CC)Ljava/lang/String;
    //   85: astore_0
    //   86: aload_0
    //   87: invokevirtual 149	java/lang/String:intern	()Ljava/lang/String;
    //   90: astore_0
    //   91: aload_0
    //   92: areturn
    //   93: astore_0
    //   94: aload_0
    //   95: athrow
    //   96: astore_0
    //   97: aload_0
    //   98: athrow
    // Local variable table:
    //   start	length	slot	name	signature
    //   0	99	0	paramString	String
    //   0	99	1	paramChar1	char
    //   0	99	2	paramChar2	char
    //   24	8	3	i	int
    // Exception table:
    //   from	to	target	type
    //   86	91	93	java/lang/Exception
    //   79	86	96	java/lang/Exception
  }
  
  public static int bК041AК041AКК()
  {
    return 35;
  }
  
  public static int bКК041A041AКК()
  {
    return 1;
  }
  
  public static int bКККК041AК()
  {
    return 2;
  }
}

/* Location:
 * Qualified Name:     kkkkkk.kkxkkk
 * Java Class Version: 6 (50.0)
 * JD-Core Version:    0.7.1
 */