package kkkkkk;

public class kxkkxk
  extends xxkxxk
{
  public static int b044E044Eюю044E044E = 40;
  public static int b044Eю044Eю044E044E = 0;
  public static int bю044E044Eю044E044E = 1;
  public static int bюю044Eю044E044E = 2;
  
  /* Error */
  public kxkkxk()
  {
    // Byte code:
    //   0: iconst_2
    //   1: istore_1
    //   2: iload_1
    //   3: iconst_0
    //   4: idiv
    //   5: istore_2
    //   6: getstatic 22	kkkkkk/kxkkxk:b044E044Eюю044E044E	I
    //   9: istore_3
    //   10: iload_2
    //   11: istore_1
    //   12: iload_3
    //   13: invokestatic 26	kkkkkk/kxkkxk:bК041A041AК041AК	()I
    //   16: iload_3
    //   17: iadd
    //   18: imul
    //   19: getstatic 28	kkkkkk/kxkkxk:bюю044Eю044E044E	I
    //   22: irem
    //   23: tableswitch	default:+17->40, 0:+-21->2
    //   40: invokestatic 31	kkkkkk/kxkkxk:b041A041A041AК041AК	()I
    //   43: putstatic 22	kkkkkk/kxkkxk:b044E044Eюю044E044E	I
    //   46: invokestatic 31	kkkkkk/kxkkxk:b041A041A041AК041AК	()I
    //   49: putstatic 28	kkkkkk/kxkkxk:bюю044Eю044E044E	I
    //   52: iload_2
    //   53: istore_1
    //   54: goto -52 -> 2
    //   57: astore 4
    //   59: aload_0
    //   60: invokespecial 33	kkkkkk/xxkxxk:<init>	()V
    //   63: return
    //   64: astore 4
    //   66: aload 4
    //   68: athrow
    //   69: astore 4
    //   71: aload 4
    //   73: athrow
    // Local variable table:
    //   start	length	slot	name	signature
    //   0	74	0	this	kxkkxk
    //   1	53	1	i	int
    //   5	48	2	j	int
    //   9	10	3	k	int
    //   57	1	4	localException1	Exception
    //   64	3	4	localException2	Exception
    //   69	3	4	localException3	Exception
    // Exception table:
    //   from	to	target	type
    //   2	6	57	java/lang/Exception
    //   59	63	64	java/lang/Exception
    //   66	69	69	java/lang/Exception
  }
  
  public static int b041A041A041AК041AК()
  {
    return 85;
  }
  
  public static int bК041A041AК041AК()
  {
    return 1;
  }
  
  public String bК041A041A041A041AК(String paramString, char paramChar1, char paramChar2)
  {
    int i = 0;
    switch (0)
    {
    case 1: 
    default: 
      for (;;)
      {
        switch (0)
        {
        }
      }
    }
    paramString = paramString.toCharArray();
    char[] arrayOfChar = new char[paramString.length];
    while (i < paramString.length)
    {
      arrayOfChar[i] = ((char)(paramString[i] + paramChar1 - paramChar2));
      int j = i + 1;
      i = j;
      if ((b044E044Eюю044E044E + bю044E044Eю044E044E) * b044E044Eюю044E044E % bюю044Eю044E044E != b044Eю044Eю044E044E)
      {
        b044E044Eюю044E044E = b041A041A041AК041AК();
        b044Eю044Eю044E044E = 76;
        i = j;
      }
    }
    return new String(arrayOfChar);
  }
}

/* Location:
 * Qualified Name:     kkkkkk.kxkkxk
 * Java Class Version: 6 (50.0)
 * JD-Core Version:    0.7.1
 */