package kkkkkk;

public class kxkxkk
  extends xkkxkk
{
  public static int b044E044E044E044Eюю = 0;
  public static int b044Eю044E044Eюю = 1;
  public static int bю044E044E044Eюю = 2;
  public static int bюю044E044Eюю = 88;
  
  public kxkxkk()
  {
    switch (0)
    {
    case 1: 
    default: 
      for (;;)
      {
        switch (0)
        {
        }
      }
    }
  }
  
  public static int b041EО041E041E041E041E()
  {
    return 30;
  }
  
  public static int bО041E041E041E041E041E()
  {
    return 1;
  }
  
  /* Error */
  public String bК041A041AККК(String paramString, char paramChar)
  {
    // Byte code:
    //   0: aload_1
    //   1: invokevirtual 44	java/lang/String:toCharArray	()[C
    //   4: astore_1
    //   5: aload_1
    //   6: arraylength
    //   7: newarray <illegal type>
    //   9: astore 6
    //   11: iconst_0
    //   12: istore_3
    //   13: iload_3
    //   14: aload_1
    //   15: arraylength
    //   16: if_icmpge +114 -> 130
    //   19: aload_1
    //   20: iload_3
    //   21: caload
    //   22: istore 4
    //   24: aload 6
    //   26: iload_3
    //   27: iload 4
    //   29: iload_2
    //   30: isub
    //   31: i2c
    //   32: castore
    //   33: iload_3
    //   34: iconst_1
    //   35: iadd
    //   36: istore 4
    //   38: getstatic 20	kkkkkk/kxkxkk:bюю044E044Eюю	I
    //   41: istore 5
    //   43: iload 4
    //   45: istore_3
    //   46: iload 5
    //   48: getstatic 22	kkkkkk/kxkxkk:b044Eю044E044Eюю	I
    //   51: iload 5
    //   53: iadd
    //   54: imul
    //   55: getstatic 28	kkkkkk/kxkxkk:bю044E044E044Eюю	I
    //   58: irem
    //   59: tableswitch	default:+17->76, 0:+-46->13
    //   76: invokestatic 31	kkkkkk/kxkxkk:b041EО041E041E041E041E	()I
    //   79: putstatic 20	kkkkkk/kxkxkk:bюю044E044Eюю	I
    //   82: invokestatic 31	kkkkkk/kxkxkk:b041EО041E041E041E041E	()I
    //   85: putstatic 22	kkkkkk/kxkxkk:b044Eю044E044Eюю	I
    //   88: iload 4
    //   90: istore_3
    //   91: getstatic 20	kkkkkk/kxkxkk:bюю044E044Eюю	I
    //   94: getstatic 22	kkkkkk/kxkxkk:b044Eю044E044Eюю	I
    //   97: iadd
    //   98: getstatic 20	kkkkkk/kxkxkk:bюю044E044Eюю	I
    //   101: imul
    //   102: getstatic 28	kkkkkk/kxkxkk:bю044E044E044Eюю	I
    //   105: irem
    //   106: getstatic 46	kkkkkk/kxkxkk:b044E044E044E044Eюю	I
    //   109: if_icmpeq -96 -> 13
    //   112: invokestatic 31	kkkkkk/kxkxkk:b041EО041E041E041E041E	()I
    //   115: putstatic 20	kkkkkk/kxkxkk:bюю044E044Eюю	I
    //   118: invokestatic 31	kkkkkk/kxkxkk:b041EО041E041E041E041E	()I
    //   121: putstatic 46	kkkkkk/kxkxkk:b044E044E044E044Eюю	I
    //   124: iload 4
    //   126: istore_3
    //   127: goto -114 -> 13
    //   130: new 40	java/lang/String
    //   133: dup
    //   134: aload 6
    //   136: invokespecial 49	java/lang/String:<init>	([C)V
    //   139: astore_1
    //   140: aload_1
    //   141: areturn
    //   142: astore_1
    //   143: aload_1
    //   144: athrow
    //   145: astore_1
    //   146: aload_1
    //   147: athrow
    // Local variable table:
    //   start	length	slot	name	signature
    //   0	148	0	this	kxkxkk
    //   0	148	1	paramString	String
    //   0	148	2	paramChar	char
    //   12	115	3	i	int
    //   22	103	4	c	char
    //   41	14	5	j	int
    //   9	126	6	arrayOfChar	char[]
    // Exception table:
    //   from	to	target	type
    //   0	11	142	java/lang/Exception
    //   13	19	142	java/lang/Exception
    //   130	140	145	java/lang/Exception
  }
}

/* Location:
 * Qualified Name:     kkkkkk.kxkxkk
 * Java Class Version: 6 (50.0)
 * JD-Core Version:    0.7.1
 */