package kkkkkk;

public class kxkxxk
{
  public static int b041D041D041D041D041DН = 0;
  private static long[] b041DН041D041D041DН;
  public static int b041DНННН041D = 2;
  public static int bН041D041D041D041DН = 20;
  private static char[][] bНН041D041D041DН;
  public static int bННННН041D = 1;
  
  static
  {
    
    if ((bН041D041D041D041DН + bННННН041D) * bН041D041D041D041DН % b041DНННН041D != b041D041D041D041D041DН)
    {
      bН041D041D041D041DН = bО041EО041EО041E();
      b041D041D041D041D041DН = bО041EО041EО041E();
      int i = bН041D041D041D041DН;
      switch (i * (bННННН041D + i) % b041EО041E041EО041E())
      {
      default: 
        bН041D041D041D041DН = bО041EО041EО041E();
        b041D041D041D041D041DН = bО041EО041EО041E();
      }
    }
    b041E041E041E041EО041E();
  }
  
  private static void b041E041E041E041EО041E()
  {
    char[] arrayOfChar = new char[30];
    b041EООО041E041E(arrayOfChar);
    bНН041D041D041DН = new char[][] { arrayOfChar };
  }
  
  public static int b041E041EО041EО041E()
  {
    return 1;
  }
  
  private static void b041E041EОО041E041E()
  {
    try
    {
      kkkkxk.bООО041E041E041E();
      int i = bН041D041D041D041DН;
      int j = bННННН041D;
      switch (1)
      {
      case 0: 
      default: 
        for (;;)
        {
          switch (0)
          {
          }
        }
      }
      switch (i * (j + i) % b041DНННН041D)
      {
      default: 
        i = bН041D041D041D041DН;
        switch (i * (bННННН041D + i) % b041DНННН041D)
        {
        default: 
          bН041D041D041D041DН = bО041EО041EО041E();
          b041D041D041D041D041DН = bО041EО041EО041E();
        }
        bН041D041D041D041DН = 24;
        b041D041D041D041D041DН = 55;
      }
      return;
    }
    catch (Exception localException)
    {
      throw localException;
    }
  }
  
  public static int b041EО041E041EО041E()
  {
    return 2;
  }
  
  private static void b041EООО041E041E(char[] paramArrayOfChar)
  {
    paramArrayOfChar[0] = 'l';
    paramArrayOfChar[1] = 'i';
    paramArrayOfChar[2] = 'b';
    paramArrayOfChar[3] = '/';
    paramArrayOfChar[4] = 'a';
    paramArrayOfChar[5] = 'r';
    paramArrayOfChar[6] = 'm';
    paramArrayOfChar[7] = 'e';
    paramArrayOfChar[8] = 'a';
    paramArrayOfChar[9] = 'b';
    paramArrayOfChar[10] = 'i';
    paramArrayOfChar[11] = '-';
    paramArrayOfChar[12] = 'v';
    paramArrayOfChar[13] = '7';
    paramArrayOfChar[14] = 'a';
    paramArrayOfChar[15] = '/';
    paramArrayOfChar[16] = 'l';
    paramArrayOfChar[17] = 'i';
    paramArrayOfChar[18] = 'b';
    paramArrayOfChar[19] = 's';
    if ((bН041D041D041D041DН + bННННН041D) * bН041D041D041D041DН % b041DНННН041D != b041D041D041D041D041DН)
    {
      bН041D041D041D041DН = bО041EО041EО041E();
      b041D041D041D041D041DН = 94;
    }
    paramArrayOfChar[20] = 'c';
    paramArrayOfChar[21] = 'p';
    paramArrayOfChar[22] = 'l';
    if ((bО041EО041EО041E() + b041E041EО041EО041E()) * bО041EО041EО041E() % b041DНННН041D != bОО041E041EО041E())
    {
      bН041D041D041D041DН = 47;
      b041D041D041D041D041DН = bО041EО041EО041E();
    }
    paramArrayOfChar[23] = 'u';
    paramArrayOfChar[24] = 'g';
    paramArrayOfChar[25] = 'i';
    paramArrayOfChar[26] = 'n';
    paramArrayOfChar[27] = '.';
    paramArrayOfChar[28] = 's';
    paramArrayOfChar[29] = 'o';
  }
  
  private static void bО041E041E041EО041E()
  {
    long[] arrayOfLong = new long[1];
    bОООО041E041E(arrayOfLong);
    b041DН041D041D041DН = arrayOfLong;
  }
  
  public static int bО041EО041EО041E()
  {
    return 47;
  }
  
  private static void bО041EОО041E041E()
  {
    if ((bН041D041D041D041DН + b041E041EО041EО041E()) * bН041D041D041D041DН % b041DНННН041D != b041D041D041D041D041DН)
    {
      bН041D041D041D041DН = bО041EО041EО041E();
      b041D041D041D041D041DН = 28;
    }
    switch (0)
    {
    case 1: 
    default: 
      for (;;)
      {
        switch (0)
        {
        }
      }
    }
  }
  
  public static int bОО041E041EО041E()
  {
    return 0;
  }
  
  /* Error */
  public static void bОО041EО041E041E(String paramString)
  {
    // Byte code:
    //   0: iconst_0
    //   1: istore_1
    //   2: new 81	java/util/zip/ZipFile
    //   5: dup
    //   6: aload_0
    //   7: invokespecial 83	java/util/zip/ZipFile:<init>	(Ljava/lang/String;)V
    //   10: astore_0
    //   11: iconst_0
    //   12: istore_2
    //   13: iload_1
    //   14: getstatic 54	kkkkkk/kxkxxk:bНН041D041D041DН	[[C
    //   17: arraylength
    //   18: if_icmpge +134 -> 152
    //   21: aload_0
    //   22: new 85	java/lang/String
    //   25: dup
    //   26: getstatic 54	kkkkkk/kxkxxk:bНН041D041D041DН	[[C
    //   29: iload_1
    //   30: aaload
    //   31: invokespecial 87	java/lang/String:<init>	([C)V
    //   34: invokevirtual 91	java/util/zip/ZipFile:getEntry	(Ljava/lang/String;)Ljava/util/zip/ZipEntry;
    //   37: astore_3
    //   38: getstatic 24	kkkkkk/kxkxxk:bН041D041D041D041DН	I
    //   41: getstatic 26	kkkkkk/kxkxxk:bННННН041D	I
    //   44: iadd
    //   45: getstatic 24	kkkkkk/kxkxxk:bН041D041D041D041DН	I
    //   48: imul
    //   49: getstatic 28	kkkkkk/kxkxxk:b041DНННН041D	I
    //   52: irem
    //   53: getstatic 30	kkkkkk/kxkxxk:b041D041D041D041D041DН	I
    //   56: if_icmpeq +15 -> 71
    //   59: invokestatic 34	kkkkkk/kxkxxk:bО041EО041EО041E	()I
    //   62: putstatic 24	kkkkkk/kxkxxk:bН041D041D041D041DН	I
    //   65: invokestatic 34	kkkkkk/kxkxxk:bО041EО041EО041E	()I
    //   68: putstatic 30	kkkkkk/kxkxxk:b041D041D041D041D041DН	I
    //   71: aload_3
    //   72: ifnull +88 -> 160
    //   75: new 93	java/util/zip/CheckedInputStream
    //   78: dup
    //   79: aload_0
    //   80: aload_3
    //   81: invokevirtual 97	java/util/zip/ZipFile:getInputStream	(Ljava/util/zip/ZipEntry;)Ljava/io/InputStream;
    //   84: new 99	java/util/zip/CRC32
    //   87: dup
    //   88: invokespecial 100	java/util/zip/CRC32:<init>	()V
    //   91: invokespecial 103	java/util/zip/CheckedInputStream:<init>	(Ljava/io/InputStream;Ljava/util/zip/Checksum;)V
    //   94: astore_3
    //   95: sipush 128
    //   98: newarray <illegal type>
    //   100: astore 4
    //   102: aload_3
    //   103: aload 4
    //   105: invokevirtual 107	java/util/zip/CheckedInputStream:read	([B)I
    //   108: ifge -6 -> 102
    //   111: aload_3
    //   112: invokevirtual 111	java/util/zip/CheckedInputStream:getChecksum	()Ljava/util/zip/Checksum;
    //   115: invokeinterface 117 1 0
    //   120: getstatic 72	kkkkkk/kxkxxk:b041DН041D041D041DН	[J
    //   123: iload_2
    //   124: laload
    //   125: lcmp
    //   126: ifeq +55 -> 181
    //   129: aload_0
    //   130: invokevirtual 120	java/util/zip/ZipFile:close	()V
    //   133: invokestatic 122	kkkkkk/kxkxxk:b041E041EОО041E041E	()V
    //   136: return
    //   137: astore_0
    //   138: aconst_null
    //   139: astore_0
    //   140: aload_0
    //   141: ifnull +7 -> 148
    //   144: aload_0
    //   145: invokevirtual 120	java/util/zip/ZipFile:close	()V
    //   148: invokestatic 122	kkkkkk/kxkxxk:b041E041EОО041E041E	()V
    //   151: return
    //   152: aload_0
    //   153: invokevirtual 120	java/util/zip/ZipFile:close	()V
    //   156: invokestatic 124	kkkkkk/kxkxxk:bО041EОО041E041E	()V
    //   159: return
    //   160: aload_0
    //   161: invokevirtual 120	java/util/zip/ZipFile:close	()V
    //   164: invokestatic 122	kkkkkk/kxkxxk:b041E041EОО041E041E	()V
    //   167: return
    //   168: astore_3
    //   169: aload_0
    //   170: ifnull +7 -> 177
    //   173: aload_0
    //   174: invokevirtual 120	java/util/zip/ZipFile:close	()V
    //   177: invokestatic 122	kkkkkk/kxkxxk:b041E041EОО041E041E	()V
    //   180: return
    //   181: iload_2
    //   182: iconst_1
    //   183: iadd
    //   184: istore_2
    //   185: iload_1
    //   186: iconst_1
    //   187: iadd
    //   188: istore_1
    //   189: goto -176 -> 13
    //   192: astore_0
    //   193: goto -16 -> 177
    //   196: astore_0
    //   197: goto -49 -> 148
    //   200: astore_3
    //   201: goto -61 -> 140
    //   204: astore_0
    //   205: aconst_null
    //   206: astore_0
    //   207: goto -38 -> 169
    // Local variable table:
    //   start	length	slot	name	signature
    //   0	210	0	paramString	String
    //   1	188	1	i	int
    //   12	173	2	j	int
    //   37	75	3	localObject	Object
    //   168	1	3	localZipException	java.util.zip.ZipException
    //   200	1	3	localIOException	java.io.IOException
    //   100	4	4	arrayOfByte	byte[]
    // Exception table:
    //   from	to	target	type
    //   2	11	137	java/io/IOException
    //   13	38	168	java/util/zip/ZipException
    //   75	102	168	java/util/zip/ZipException
    //   102	136	168	java/util/zip/ZipException
    //   152	156	168	java/util/zip/ZipException
    //   160	167	168	java/util/zip/ZipException
    //   173	177	192	java/io/IOException
    //   144	148	196	java/io/IOException
    //   13	38	200	java/io/IOException
    //   75	102	200	java/io/IOException
    //   102	136	200	java/io/IOException
    //   152	156	200	java/io/IOException
    //   160	167	200	java/io/IOException
    //   2	11	204	java/util/zip/ZipException
  }
  
  private static void bОООО041E041E(long[] paramArrayOfLong)
  {
    paramArrayOfLong[0] = 389444653L;
  }
}

/* Location:
 * Qualified Name:     kkkkkk.kxkxxk
 * Java Class Version: 6 (50.0)
 * JD-Core Version:    0.7.1
 */