package kkkkkk;

import java.io.File;
import java.lang.reflect.InvocationTargetException;
import java.lang.reflect.Method;
import java.util.ArrayList;

public final class kxxkkk
{
  public static int b043A043Aк043A043A043A = 80;
  public static int b043Aк043A043A043A043A = 2;
  public static int bк043A043A043A043A043A = 0;
  public static int bкк043A043A043A043A = 1;
  
  /* Error */
  private static void b041D041DНН041D041D(ClassLoader paramClassLoader, java.util.List<File> paramList, File paramFile)
    throws java.lang.IllegalArgumentException, IllegalAccessException, java.lang.NoSuchFieldException, InvocationTargetException, NoSuchMethodException
  {
    // Byte code:
    //   0: aload_0
    //   1: ldc 56
    //   3: sipush 184
    //   6: sipush 153
    //   9: iconst_0
    //   10: invokestatic 62	kkkkkk/kkxkkk:b041AККК041AК	(Ljava/lang/String;CCC)Ljava/lang/String;
    //   13: invokestatic 66	kkkkkk/kxxxkk:b041EООООО	(Ljava/lang/Object;Ljava/lang/String;)Ljava/lang/reflect/Field;
    //   16: astore 8
    //   18: getstatic 20	kkkkkk/kxxkkk:b043A043Aк043A043A043A	I
    //   21: istore_3
    //   22: getstatic 22	kkkkkk/kxxkkk:bкк043A043A043A043A	I
    //   25: istore 4
    //   27: getstatic 20	kkkkkk/kxxkkk:b043A043Aк043A043A043A	I
    //   30: istore 5
    //   32: getstatic 24	kkkkkk/kxxkkk:b043Aк043A043A043A043A	I
    //   35: istore 6
    //   37: getstatic 50	kkkkkk/kxxkkk:bк043A043A043A043A043A	I
    //   40: istore 7
    //   42: iload_3
    //   43: iload 4
    //   45: iadd
    //   46: iload 5
    //   48: imul
    //   49: iload 6
    //   51: irem
    //   52: iload 7
    //   54: if_icmpeq +15 -> 69
    //   57: invokestatic 28	kkkkkk/kxxkkk:b041DННН041D041D	()I
    //   60: putstatic 20	kkkkkk/kxxkkk:b043A043Aк043A043A043A	I
    //   63: invokestatic 28	kkkkkk/kxxkkk:b041DННН041D041D	()I
    //   66: putstatic 50	kkkkkk/kxxkkk:bк043A043A043A043A043A	I
    //   69: aload 8
    //   71: aload_0
    //   72: invokevirtual 72	java/lang/reflect/Field:get	(Ljava/lang/Object;)Ljava/lang/Object;
    //   75: astore_0
    //   76: ldc 74
    //   78: bipush 101
    //   80: iconst_5
    //   81: invokestatic 78	kkkkkk/kkxkkk:bК041A041A041AКК	(Ljava/lang/String;CC)Ljava/lang/String;
    //   84: astore 8
    //   86: aload_0
    //   87: new 80	java/util/ArrayList
    //   90: dup
    //   91: aload_1
    //   92: invokespecial 83	java/util/ArrayList:<init>	(Ljava/util/Collection;)V
    //   95: aload_2
    //   96: invokestatic 87	kkkkkk/kxxkkk:bНН041DН041D041D	(Ljava/lang/Object;Ljava/util/ArrayList;Ljava/io/File;)[Ljava/lang/Object;
    //   99: astore_1
    //   100: getstatic 20	kkkkkk/kxxkkk:b043A043Aк043A043A043A	I
    //   103: istore_3
    //   104: iload_3
    //   105: getstatic 22	kkkkkk/kxxkkk:bкк043A043A043A043A	I
    //   108: iload_3
    //   109: iadd
    //   110: imul
    //   111: getstatic 24	kkkkkk/kxxkkk:b043Aк043A043A043A043A	I
    //   114: irem
    //   115: tableswitch	default:+17->132, 0:+29->144
    //   132: invokestatic 28	kkkkkk/kxxkkk:b041DННН041D041D	()I
    //   135: putstatic 20	kkkkkk/kxxkkk:b043A043Aк043A043A043A	I
    //   138: invokestatic 28	kkkkkk/kxxkkk:b041DННН041D041D	()I
    //   141: putstatic 50	kkkkkk/kxxkkk:bк043A043A043A043A043A	I
    //   144: aload_0
    //   145: aload 8
    //   147: aload_1
    //   148: invokestatic 91	kkkkkk/kxxxkk:bО041EОООО	(Ljava/lang/Object;Ljava/lang/String;[Ljava/lang/Object;)V
    //   151: return
    //   152: astore_0
    //   153: aload_0
    //   154: athrow
    //   155: astore_0
    //   156: aload_0
    //   157: athrow
    // Local variable table:
    //   start	length	slot	name	signature
    //   0	158	0	paramClassLoader	ClassLoader
    //   0	158	1	paramList	java.util.List<File>
    //   0	158	2	paramFile	File
    //   21	90	3	i	int
    //   25	21	4	j	int
    //   30	19	5	k	int
    //   35	17	6	m	int
    //   40	15	7	n	int
    //   16	130	8	localObject	Object
    // Exception table:
    //   from	to	target	type
    //   57	69	152	java/lang/Exception
    //   69	100	152	java/lang/Exception
    //   144	151	152	java/lang/Exception
    //   0	42	155	java/lang/Exception
  }
  
  public static int b041DННН041D041D()
  {
    return 20;
  }
  
  public static int bН041DНН041D041D()
  {
    return 0;
  }
  
  private static Object[] bНН041DН041D041D(Object paramObject, ArrayList<File> paramArrayList, File paramFile)
    throws IllegalAccessException, InvocationTargetException, NoSuchMethodException
  {
    Object localObject = kkxkkk.bК041A041A041AКК("･ｙ｣｝＼｝ｰ］､｝･｝ｦｬｫ", 'X', '\000');
    switch (0)
    {
    case 1: 
    default: 
      for (;;)
      {
        switch (0)
        {
        }
      }
    }
    localObject = kxxxkk.b041E041EОООО(paramObject, (String)localObject, new Class[] { ArrayList.class, File.class });
    int i = b043A043Aк043A043A043A;
    switch (i * (bкк043A043A043A043A + i) % b043Aк043A043A043A043A)
    {
    default: 
      b043A043Aк043A043A043A = 99;
      bк043A043A043A043A043A = b041DННН041D041D();
    }
    if ((b043A043Aк043A043A043A + bНННН041D041D()) * b043A043Aк043A043A043A % b043Aк043A043A043A043A != bН041DНН041D041D())
    {
      b043A043Aк043A043A043A = 63;
      bк043A043A043A043A043A = 78;
    }
    switch (1)
    {
    case 0: 
    default: 
      for (;;)
      {
        switch (0)
        {
        }
      }
    }
    return (Object[])((Method)localObject).invoke(paramObject, new Object[] { paramArrayList, paramFile });
  }
  
  public static int bНННН041D041D()
  {
    return 1;
  }
}

/* Location:
 * Qualified Name:     kkkkkk.kxxkkk
 * Java Class Version: 6 (50.0)
 * JD-Core Version:    0.7.1
 */