package kkkkkk;

public abstract class xkkxkk
{
  public static int b044E044Eю044Eюю = 2;
  public static int b044Eюю044Eюю = 51;
  public static int bю044Eю044Eюю = 1;
  
  /* Error */
  public xkkxkk()
  {
    // Byte code:
    //   0: iconst_1
    //   1: tableswitch	default:+23->24, 0:+-1->0, 1:+90->91
    //   24: getstatic 20	kkkkkk/xkkxkk:b044Eюю044Eюю	I
    //   27: istore_1
    //   28: iload_1
    //   29: getstatic 22	kkkkkk/xkkxkk:bю044Eю044Eюю	I
    //   32: iload_1
    //   33: iadd
    //   34: imul
    //   35: getstatic 24	kkkkkk/xkkxkk:b044E044Eю044Eюю	I
    //   38: irem
    //   39: tableswitch	default:+17->56, 0:+27->66
    //   56: bipush 84
    //   58: putstatic 20	kkkkkk/xkkxkk:b044Eюю044Eюю	I
    //   61: bipush 63
    //   63: putstatic 22	kkkkkk/xkkxkk:bю044Eю044Eюю	I
    //   66: iconst_0
    //   67: tableswitch	default:+21->88, 0:+24->91, 1:+-67->0
    //   88: goto -64 -> 24
    //   91: getstatic 20	kkkkkk/xkkxkk:b044Eюю044Eюю	I
    //   94: istore_1
    //   95: getstatic 22	kkkkkk/xkkxkk:bю044Eю044Eюю	I
    //   98: istore_2
    //   99: getstatic 24	kkkkkk/xkkxkk:b044E044Eю044Eюю	I
    //   102: istore_3
    //   103: iload_1
    //   104: iload_2
    //   105: iload_1
    //   106: iadd
    //   107: imul
    //   108: iload_3
    //   109: irem
    //   110: tableswitch	default:+18->128, 0:+29->139
    //   128: invokestatic 28	kkkkkk/xkkxkk:b041AККККК	()I
    //   131: putstatic 20	kkkkkk/xkkxkk:b044Eюю044Eюю	I
    //   134: bipush 66
    //   136: putstatic 22	kkkkkk/xkkxkk:bю044Eю044Eюю	I
    //   139: aload_0
    //   140: invokespecial 30	java/lang/Object:<init>	()V
    //   143: return
    //   144: astore 4
    //   146: aload 4
    //   148: athrow
    //   149: astore 4
    //   151: aload 4
    //   153: athrow
    // Local variable table:
    //   start	length	slot	name	signature
    //   0	154	0	this	xkkxkk
    //   27	81	1	i	int
    //   98	9	2	j	int
    //   102	8	3	k	int
    //   144	3	4	localException1	Exception
    //   149	3	4	localException2	Exception
    // Exception table:
    //   from	to	target	type
    //   91	103	144	java/lang/Exception
    //   139	143	144	java/lang/Exception
    //   128	139	149	java/lang/Exception
  }
  
  public static int b041AККККК()
  {
    return 90;
  }
  
  public abstract String bК041A041AККК(String paramString, char paramChar);
}

/* Location:
 * Qualified Name:     kkkkkk.xkkxkk
 * Java Class Version: 6 (50.0)
 * JD-Core Version:    0.7.1
 */