package kkkkkk;

public class xxxkxk
{
  public static int b041D041DНН041DН = 0;
  public static int b041DННН041DН = 1;
  public static int bН041DНН041DН = 2;
  public static int bНННН041DН = 37;
  
  /* Error */
  public xxxkxk()
  {
    // Byte code:
    //   0: getstatic 19	kkkkkk/xxxkxk:bНННН041DН	I
    //   3: istore_1
    //   4: getstatic 21	kkkkkk/xxxkxk:b041DННН041DН	I
    //   7: istore_2
    //   8: invokestatic 25	kkkkkk/xxxkxk:bОО041EОО041E	()I
    //   11: istore_3
    //   12: iload_1
    //   13: iload_2
    //   14: iload_1
    //   15: iadd
    //   16: imul
    //   17: iload_3
    //   18: irem
    //   19: tableswitch	default:+17->36, 0:+59->78
    //   36: getstatic 19	kkkkkk/xxxkxk:bНННН041DН	I
    //   39: getstatic 21	kkkkkk/xxxkxk:b041DННН041DН	I
    //   42: iadd
    //   43: getstatic 19	kkkkkk/xxxkxk:bНННН041DН	I
    //   46: imul
    //   47: getstatic 27	kkkkkk/xxxkxk:bН041DНН041DН	I
    //   50: irem
    //   51: invokestatic 30	kkkkkk/xxxkxk:bО041E041EОО041E	()I
    //   54: if_icmpeq +14 -> 68
    //   57: invokestatic 33	kkkkkk/xxxkxk:b041EО041EОО041E	()I
    //   60: putstatic 19	kkkkkk/xxxkxk:bНННН041DН	I
    //   63: bipush 73
    //   65: putstatic 21	kkkkkk/xxxkxk:b041DННН041DН	I
    //   68: bipush 60
    //   70: putstatic 19	kkkkkk/xxxkxk:bНННН041DН	I
    //   73: bipush 6
    //   75: putstatic 21	kkkkkk/xxxkxk:b041DННН041DН	I
    //   78: iconst_0
    //   79: tableswitch	default:+21->100, 0:+48->127, 1:+-1->78
    //   100: iconst_1
    //   101: tableswitch	default:+23->124, 0:+-23->78, 1:+26->127
    //   124: goto -24 -> 100
    //   127: aload_0
    //   128: invokespecial 35	java/lang/Object:<init>	()V
    //   131: return
    //   132: astore 4
    //   134: aload 4
    //   136: athrow
    //   137: astore 4
    //   139: aload 4
    //   141: athrow
    // Local variable table:
    //   start	length	slot	name	signature
    //   0	142	0	this	xxxkxk
    //   3	14	1	i	int
    //   7	9	2	j	int
    //   11	8	3	k	int
    //   132	3	4	localException1	Exception
    //   137	3	4	localException2	Exception
    // Exception table:
    //   from	to	target	type
    //   68	73	132	java/lang/Exception
    //   127	131	132	java/lang/Exception
    //   0	12	137	java/lang/Exception
    //   73	78	137	java/lang/Exception
  }
  
  /* Error */
  public static java.io.InputStream b041E041E041EОО041E(java.io.InputStream paramInputStream, byte[] paramArrayOfByte1, byte[] paramArrayOfByte2)
    throws java.io.IOException
  {
    // Byte code:
    //   0: new 42	javax/crypto/spec/IvParameterSpec
    //   3: dup
    //   4: aload_2
    //   5: invokespecial 45	javax/crypto/spec/IvParameterSpec:<init>	([B)V
    //   8: astore_2
    //   9: new 47	javax/crypto/spec/SecretKeySpec
    //   12: dup
    //   13: aload_1
    //   14: ldc 49
    //   16: sipush 207
    //   19: iconst_5
    //   20: invokestatic 55	kkkkkk/kkxkkk:bК041A041A041AКК	(Ljava/lang/String;CC)Ljava/lang/String;
    //   23: invokespecial 58	javax/crypto/spec/SecretKeySpec:<init>	([BLjava/lang/String;)V
    //   26: astore_1
    //   27: ldc 60
    //   29: bipush 77
    //   31: sipush 144
    //   34: iconst_1
    //   35: invokestatic 64	kkkkkk/kkxkkk:b041AККК041AК	(Ljava/lang/String;CCC)Ljava/lang/String;
    //   38: astore 6
    //   40: invokestatic 33	kkkkkk/xxxkxk:b041EО041EОО041E	()I
    //   43: istore_3
    //   44: iload_3
    //   45: getstatic 21	kkkkkk/xxxkxk:b041DННН041DН	I
    //   48: iload_3
    //   49: iadd
    //   50: imul
    //   51: invokestatic 25	kkkkkk/xxxkxk:bОО041EОО041E	()I
    //   54: irem
    //   55: tableswitch	default:+17->72, 0:+27->82
    //   72: bipush 44
    //   74: putstatic 19	kkkkkk/xxxkxk:bНННН041DН	I
    //   77: bipush 88
    //   79: putstatic 66	kkkkkk/xxxkxk:b041D041DНН041DН	I
    //   82: aload 6
    //   84: ldc 68
    //   86: bipush 24
    //   88: bipush 17
    //   90: iconst_2
    //   91: invokestatic 64	kkkkkk/kkxkkk:b041AККК041AК	(Ljava/lang/String;CCC)Ljava/lang/String;
    //   94: invokestatic 74	javax/crypto/Cipher:getInstance	(Ljava/lang/String;Ljava/lang/String;)Ljavax/crypto/Cipher;
    //   97: astore 6
    //   99: aload 6
    //   101: iconst_2
    //   102: aload_1
    //   103: aload_2
    //   104: invokevirtual 78	javax/crypto/Cipher:init	(ILjava/security/Key;Ljava/security/spec/AlgorithmParameterSpec;)V
    //   107: new 80	kkkkkk/xkxkxk
    //   110: dup
    //   111: aload_0
    //   112: aload 6
    //   114: invokespecial 83	kkkkkk/xkxkxk:<init>	(Ljava/io/InputStream;Ljavax/crypto/Cipher;)V
    //   117: astore_0
    //   118: getstatic 19	kkkkkk/xxxkxk:bНННН041DН	I
    //   121: istore_3
    //   122: getstatic 21	kkkkkk/xxxkxk:b041DННН041DН	I
    //   125: istore 4
    //   127: getstatic 19	kkkkkk/xxxkxk:bНННН041DН	I
    //   130: istore 5
    //   132: iload_3
    //   133: iload 4
    //   135: iadd
    //   136: iload 5
    //   138: imul
    //   139: getstatic 27	kkkkkk/xxxkxk:bН041DНН041DН	I
    //   142: irem
    //   143: getstatic 66	kkkkkk/xxxkxk:b041D041DНН041DН	I
    //   146: if_icmpeq +14 -> 160
    //   149: bipush 16
    //   151: putstatic 19	kkkkkk/xxxkxk:bНННН041DН	I
    //   154: invokestatic 33	kkkkkk/xxxkxk:b041EО041EОО041E	()I
    //   157: putstatic 66	kkkkkk/xxxkxk:b041D041DНН041DН	I
    //   160: aload_0
    //   161: areturn
    //   162: astore_0
    //   163: new 40	java/io/IOException
    //   166: dup
    //   167: aload_0
    //   168: invokevirtual 87	java/lang/Exception:getMessage	()Ljava/lang/String;
    //   171: invokespecial 90	java/io/IOException:<init>	(Ljava/lang/String;)V
    //   174: athrow
    //   175: astore_0
    //   176: aload_0
    //   177: athrow
    //   178: astore_0
    //   179: aload_0
    //   180: athrow
    // Local variable table:
    //   start	length	slot	name	signature
    //   0	181	0	paramInputStream	java.io.InputStream
    //   0	181	1	paramArrayOfByte1	byte[]
    //   0	181	2	paramArrayOfByte2	byte[]
    //   43	93	3	i	int
    //   125	11	4	j	int
    //   130	9	5	k	int
    //   38	75	6	localObject	Object
    // Exception table:
    //   from	to	target	type
    //   0	40	162	java/lang/Exception
    //   82	118	162	java/lang/Exception
    //   118	132	175	java/lang/Exception
    //   163	175	175	java/lang/Exception
    //   132	160	178	java/lang/Exception
  }
  
  public static int b041EО041EОО041E()
  {
    return 71;
  }
  
  public static int bО041E041EОО041E()
  {
    return 0;
  }
  
  public static int bОО041EОО041E()
  {
    return 2;
  }
}

/* Location:
 * Qualified Name:     kkkkkk.xxxkxk
 * Java Class Version: 6 (50.0)
 * JD-Core Version:    0.7.1
 */