package kkkkkk;

public final class xxxkkk
{
  public static int b044E044Eюююю = 65;
  public static int b044Eююююю = 1;
  public static int bю044Eюююю = 2;
  public static int bюю044Eююю;
  
  public static int b041D041D041DН041D041D()
  {
    return 10;
  }
  
  /* Error */
  private static Object[] b041DНН041D041D041D(Object paramObject, java.util.ArrayList<java.io.File> paramArrayList, java.io.File paramFile, java.util.ArrayList<java.io.IOException> paramArrayList1)
    throws java.lang.IllegalAccessException, java.lang.reflect.InvocationTargetException, java.lang.NoSuchMethodException
  {
    // Byte code:
    //   0: invokestatic 23	kkkkkk/xxxkkk:b041D041D041DН041D041D	()I
    //   3: getstatic 25	kkkkkk/xxxkkk:b044Eююююю	I
    //   6: iadd
    //   7: invokestatic 23	kkkkkk/xxxkkk:b041D041D041DН041D041D	()I
    //   10: imul
    //   11: getstatic 27	kkkkkk/xxxkkk:bю044Eюююю	I
    //   14: irem
    //   15: getstatic 50	kkkkkk/xxxkkk:bюю044Eююю	I
    //   18: if_icmpeq +14 -> 32
    //   21: invokestatic 23	kkkkkk/xxxkkk:b041D041D041DН041D041D	()I
    //   24: putstatic 52	kkkkkk/xxxkkk:b044E044Eюююю	I
    //   27: bipush 81
    //   29: putstatic 50	kkkkkk/xxxkkk:bюю044Eююю	I
    //   32: ldc 54
    //   34: bipush 110
    //   36: bipush 6
    //   38: invokestatic 60	kkkkkk/kkxkkk:bК041A041A041AКК	(Ljava/lang/String;CC)Ljava/lang/String;
    //   41: astore 4
    //   43: getstatic 52	kkkkkk/xxxkkk:b044E044Eюююю	I
    //   46: getstatic 25	kkkkkk/xxxkkk:b044Eююююю	I
    //   49: iadd
    //   50: getstatic 52	kkkkkk/xxxkkk:b044E044Eюююю	I
    //   53: imul
    //   54: invokestatic 63	kkkkkk/xxxkkk:bН041D041DН041D041D	()I
    //   57: irem
    //   58: getstatic 50	kkkkkk/xxxkkk:bюю044Eююю	I
    //   61: if_icmpeq +66 -> 127
    //   64: iconst_0
    //   65: tableswitch	default:+23->88, 0:+50->115, 1:+-1->64
    //   88: iconst_0
    //   89: tableswitch	default:+23->112, 0:+26->115, 1:+-25->64
    //   112: goto -24 -> 88
    //   115: invokestatic 23	kkkkkk/xxxkkk:b041D041D041DН041D041D	()I
    //   118: putstatic 52	kkkkkk/xxxkkk:b044E044Eюююю	I
    //   121: invokestatic 23	kkkkkk/xxxkkk:b041D041D041DН041D041D	()I
    //   124: putstatic 50	kkkkkk/xxxkkk:bюю044Eююю	I
    //   127: aload_0
    //   128: aload 4
    //   130: iconst_3
    //   131: anewarray 65	java/lang/Class
    //   134: dup
    //   135: iconst_0
    //   136: ldc 67
    //   138: aastore
    //   139: dup
    //   140: iconst_1
    //   141: ldc 69
    //   143: aastore
    //   144: dup
    //   145: iconst_2
    //   146: ldc 67
    //   148: aastore
    //   149: invokestatic 73	kkkkkk/kxxxkk:b041E041EОООО	(Ljava/lang/Object;Ljava/lang/String;[Ljava/lang/Class;)Ljava/lang/reflect/Method;
    //   152: astore 4
    //   154: aload 4
    //   156: aload_0
    //   157: iconst_3
    //   158: anewarray 4	java/lang/Object
    //   161: dup
    //   162: iconst_0
    //   163: aload_1
    //   164: aastore
    //   165: dup
    //   166: iconst_1
    //   167: aload_2
    //   168: aastore
    //   169: dup
    //   170: iconst_2
    //   171: aload_3
    //   172: aastore
    //   173: invokevirtual 79	java/lang/reflect/Method:invoke	(Ljava/lang/Object;[Ljava/lang/Object;)Ljava/lang/Object;
    //   176: checkcast 81	[Ljava/lang/Object;
    //   179: checkcast 81	[Ljava/lang/Object;
    //   182: astore_0
    //   183: aload_0
    //   184: areturn
    //   185: astore_0
    //   186: aload_0
    //   187: athrow
    //   188: astore_0
    //   189: aload_0
    //   190: athrow
    // Local variable table:
    //   start	length	slot	name	signature
    //   0	191	0	paramObject	Object
    //   0	191	1	paramArrayList	java.util.ArrayList<java.io.File>
    //   0	191	2	paramFile	java.io.File
    //   0	191	3	paramArrayList1	java.util.ArrayList<java.io.IOException>
    //   41	114	4	localObject	Object
    // Exception table:
    //   from	to	target	type
    //   32	43	185	java/lang/Exception
    //   127	154	185	java/lang/Exception
    //   154	183	188	java/lang/Exception
  }
  
  public static int bН041D041DН041D041D()
  {
    return 2;
  }
  
  /* Error */
  private static void bННН041D041D041D(ClassLoader paramClassLoader, java.util.List<java.io.File> paramList, java.io.File paramFile)
    throws java.lang.IllegalArgumentException, java.lang.IllegalAccessException, java.lang.NoSuchFieldException, java.lang.reflect.InvocationTargetException, java.lang.NoSuchMethodException
  {
    // Byte code:
    //   0: aload_0
    //   1: ldc 85
    //   3: bipush 81
    //   5: iconst_0
    //   6: invokestatic 60	kkkkkk/kkxkkk:bК041A041A041AКК	(Ljava/lang/String;CC)Ljava/lang/String;
    //   9: invokestatic 89	kkkkkk/kxxxkk:b041EООООО	(Ljava/lang/Object;Ljava/lang/String;)Ljava/lang/reflect/Field;
    //   12: aload_0
    //   13: invokevirtual 95	java/lang/reflect/Field:get	(Ljava/lang/Object;)Ljava/lang/Object;
    //   16: astore 6
    //   18: new 67	java/util/ArrayList
    //   21: dup
    //   22: invokespecial 96	java/util/ArrayList:<init>	()V
    //   25: astore 5
    //   27: ldc 98
    //   29: sipush 243
    //   32: iconst_3
    //   33: invokestatic 60	kkkkkk/kkxkkk:bК041A041A041AКК	(Ljava/lang/String;CC)Ljava/lang/String;
    //   36: astore 7
    //   38: aload 6
    //   40: aload 7
    //   42: aload 6
    //   44: new 67	java/util/ArrayList
    //   47: dup
    //   48: aload_1
    //   49: invokespecial 101	java/util/ArrayList:<init>	(Ljava/util/Collection;)V
    //   52: aload_2
    //   53: aload 5
    //   55: invokestatic 103	kkkkkk/xxxkkk:b041DНН041D041D041D	(Ljava/lang/Object;Ljava/util/ArrayList;Ljava/io/File;Ljava/util/ArrayList;)[Ljava/lang/Object;
    //   58: invokestatic 107	kkkkkk/kxxxkk:bО041EОООО	(Ljava/lang/Object;Ljava/lang/String;[Ljava/lang/Object;)V
    //   61: aload 5
    //   63: invokevirtual 110	java/util/ArrayList:size	()I
    //   66: ifle +234 -> 300
    //   69: aload 5
    //   71: invokevirtual 114	java/util/ArrayList:iterator	()Ljava/util/Iterator;
    //   74: astore_1
    //   75: aload_1
    //   76: invokeinterface 120 1 0
    //   81: ifeq +164 -> 245
    //   84: aload_1
    //   85: invokeinterface 124 1 0
    //   90: checkcast 126	java/io/IOException
    //   93: astore_2
    //   94: ldc -128
    //   96: bipush 114
    //   98: iconst_1
    //   99: invokestatic 60	kkkkkk/kkxkkk:bК041A041A041AКК	(Ljava/lang/String;CC)Ljava/lang/String;
    //   102: astore 6
    //   104: ldc -126
    //   106: bipush 81
    //   108: iconst_3
    //   109: invokestatic 60	kkkkkk/kkxkkk:bК041A041A041AКК	(Ljava/lang/String;CC)Ljava/lang/String;
    //   112: astore 7
    //   114: getstatic 52	kkkkkk/xxxkkk:b044E044Eюююю	I
    //   117: istore_3
    //   118: iconst_1
    //   119: tableswitch	default:+21->140, 0:+-1->118, 1:+48->167
    //   140: iconst_1
    //   141: tableswitch	default:+23->164, 0:+-23->118, 1:+26->167
    //   164: goto -24 -> 140
    //   167: iload_3
    //   168: getstatic 25	kkkkkk/xxxkkk:b044Eююююю	I
    //   171: iadd
    //   172: getstatic 52	kkkkkk/xxxkkk:b044E044Eюююю	I
    //   175: imul
    //   176: getstatic 27	kkkkkk/xxxkkk:bю044Eюююю	I
    //   179: irem
    //   180: getstatic 50	kkkkkk/xxxkkk:bюю044Eююю	I
    //   183: if_icmpeq +47 -> 230
    //   186: invokestatic 23	kkkkkk/xxxkkk:b041D041D041DН041D041D	()I
    //   189: putstatic 52	kkkkkk/xxxkkk:b044E044Eюююю	I
    //   192: invokestatic 23	kkkkkk/xxxkkk:b041D041D041DН041D041D	()I
    //   195: putstatic 50	kkkkkk/xxxkkk:bюю044Eююю	I
    //   198: getstatic 52	kkkkkk/xxxkkk:b044E044Eюююю	I
    //   201: getstatic 25	kkkkkk/xxxkkk:b044Eююююю	I
    //   204: iadd
    //   205: getstatic 52	kkkkkk/xxxkkk:b044E044Eюююю	I
    //   208: imul
    //   209: getstatic 27	kkkkkk/xxxkkk:bю044Eюююю	I
    //   212: irem
    //   213: getstatic 50	kkkkkk/xxxkkk:bюю044Eююю	I
    //   216: if_icmpeq +14 -> 230
    //   219: bipush 50
    //   221: putstatic 52	kkkkkk/xxxkkk:b044E044Eюююю	I
    //   224: invokestatic 23	kkkkkk/xxxkkk:b041D041D041DН041D041D	()I
    //   227: putstatic 50	kkkkkk/xxxkkk:bюю044Eююю	I
    //   230: aload 6
    //   232: aload 7
    //   234: aload_2
    //   235: invokestatic 136	android/util/Log:w	(Ljava/lang/String;Ljava/lang/String;Ljava/lang/Throwable;)I
    //   238: pop
    //   239: goto -164 -> 75
    //   242: astore_0
    //   243: aload_0
    //   244: athrow
    //   245: aload_0
    //   246: ldc -118
    //   248: sipush 186
    //   251: iconst_1
    //   252: invokestatic 60	kkkkkk/kkxkkk:bК041A041A041AКК	(Ljava/lang/String;CC)Ljava/lang/String;
    //   255: invokestatic 89	kkkkkk/kxxxkk:b041EООООО	(Ljava/lang/Object;Ljava/lang/String;)Ljava/lang/reflect/Field;
    //   258: astore_2
    //   259: aload_2
    //   260: aload_0
    //   261: invokevirtual 95	java/lang/reflect/Field:get	(Ljava/lang/Object;)Ljava/lang/Object;
    //   264: checkcast 140	[Ljava/io/IOException;
    //   267: checkcast 140	[Ljava/io/IOException;
    //   270: astore 6
    //   272: aload 6
    //   274: ifnonnull +27 -> 301
    //   277: aload 5
    //   279: aload 5
    //   281: invokevirtual 110	java/util/ArrayList:size	()I
    //   284: anewarray 126	java/io/IOException
    //   287: invokevirtual 144	java/util/ArrayList:toArray	([Ljava/lang/Object;)[Ljava/lang/Object;
    //   290: checkcast 140	[Ljava/io/IOException;
    //   293: astore_1
    //   294: aload_2
    //   295: aload_0
    //   296: aload_1
    //   297: invokevirtual 148	java/lang/reflect/Field:set	(Ljava/lang/Object;Ljava/lang/Object;)V
    //   300: return
    //   301: aload 5
    //   303: invokevirtual 110	java/util/ArrayList:size	()I
    //   306: istore_3
    //   307: aload 6
    //   309: arraylength
    //   310: istore 4
    //   312: iload_3
    //   313: iload 4
    //   315: iadd
    //   316: anewarray 126	java/io/IOException
    //   319: astore_1
    //   320: aload 5
    //   322: aload_1
    //   323: invokevirtual 144	java/util/ArrayList:toArray	([Ljava/lang/Object;)[Ljava/lang/Object;
    //   326: pop
    //   327: aload 5
    //   329: invokevirtual 110	java/util/ArrayList:size	()I
    //   332: istore_3
    //   333: aload 6
    //   335: iconst_0
    //   336: aload_1
    //   337: iload_3
    //   338: aload 6
    //   340: arraylength
    //   341: invokestatic 154	java/lang/System:arraycopy	(Ljava/lang/Object;ILjava/lang/Object;II)V
    //   344: goto -50 -> 294
    //   347: astore_0
    //   348: aload_0
    //   349: athrow
    // Local variable table:
    //   start	length	slot	name	signature
    //   0	350	0	paramClassLoader	ClassLoader
    //   0	350	1	paramList	java.util.List<java.io.File>
    //   0	350	2	paramFile	java.io.File
    //   117	221	3	i	int
    //   310	6	4	j	int
    //   25	303	5	localArrayList	java.util.ArrayList
    //   16	323	6	localObject	Object
    //   36	197	7	str	String
    // Exception table:
    //   from	to	target	type
    //   0	27	242	java/lang/Exception
    //   38	75	242	java/lang/Exception
    //   75	114	242	java/lang/Exception
    //   230	239	242	java/lang/Exception
    //   245	272	242	java/lang/Exception
    //   301	312	242	java/lang/Exception
    //   327	333	242	java/lang/Exception
    //   27	38	347	java/lang/Exception
    //   277	294	347	java/lang/Exception
    //   294	300	347	java/lang/Exception
    //   312	327	347	java/lang/Exception
    //   333	344	347	java/lang/Exception
  }
}

/* Location:
 * Qualified Name:     kkkkkk.xxxkkk
 * Java Class Version: 6 (50.0)
 * JD-Core Version:    0.7.1
 */