package kkkkkk;

public class xxxxkk
  extends xkkxkk
{
  public static int b044E044E044Eюю044E = 0;
  public static int b044Eюю044Eю044E = 2;
  public static int bю044E044Eюю044E = 77;
  public static int bююю044Eю044E = 1;
  
  public static int b041E041EО041E041E041E()
  {
    return 62;
  }
  
  public static int bО041EО041E041E041E()
  {
    return 1;
  }
  
  public static int bОО041E041E041E041E()
  {
    return 2;
  }
  
  /* Error */
  public String bК041A041AККК(String paramString, char paramChar)
  {
    // Byte code:
    //   0: aload_1
    //   1: invokevirtual 38	java/lang/String:toCharArray	()[C
    //   4: astore_1
    //   5: aload_1
    //   6: arraylength
    //   7: newarray <illegal type>
    //   9: astore 6
    //   11: iconst_0
    //   12: istore_3
    //   13: aload_1
    //   14: arraylength
    //   15: istore 4
    //   17: iload_3
    //   18: iload 4
    //   20: if_icmpge +167 -> 187
    //   23: iconst_1
    //   24: tableswitch	default:+24->48, 0:+-1->23, 1:+51->75
    //   48: iconst_1
    //   49: tableswitch	default:+23->72, 0:+-26->23, 1:+26->75
    //   72: goto -24 -> 48
    //   75: aload 6
    //   77: iload_3
    //   78: aload_1
    //   79: iload_3
    //   80: caload
    //   81: iload_2
    //   82: iadd
    //   83: i2c
    //   84: castore
    //   85: iload_3
    //   86: iconst_1
    //   87: iadd
    //   88: istore 4
    //   90: getstatic 40	kkkkkk/xxxxkk:bю044E044Eюю044E	I
    //   93: istore 5
    //   95: iload 4
    //   97: istore_3
    //   98: iload 5
    //   100: invokestatic 42	kkkkkk/xxxxkk:bО041EО041E041E041E	()I
    //   103: iload 5
    //   105: iadd
    //   106: imul
    //   107: invokestatic 44	kkkkkk/xxxxkk:bОО041E041E041E041E	()I
    //   110: irem
    //   111: tableswitch	default:+17->128, 0:+-98->13
    //   128: invokestatic 46	kkkkkk/xxxxkk:b041E041EО041E041E041E	()I
    //   131: istore_3
    //   132: iload_3
    //   133: getstatic 48	kkkkkk/xxxxkk:bююю044Eю044E	I
    //   136: iload_3
    //   137: iadd
    //   138: imul
    //   139: getstatic 50	kkkkkk/xxxxkk:b044Eюю044Eю044E	I
    //   142: irem
    //   143: tableswitch	default:+17->160, 0:+28->171
    //   160: invokestatic 46	kkkkkk/xxxxkk:b041E041EО041E041E041E	()I
    //   163: putstatic 40	kkkkkk/xxxxkk:bю044E044Eюю044E	I
    //   166: bipush 74
    //   168: putstatic 52	kkkkkk/xxxxkk:b044E044E044Eюю044E	I
    //   171: bipush 83
    //   173: putstatic 40	kkkkkk/xxxxkk:bю044E044Eюю044E	I
    //   176: bipush 80
    //   178: putstatic 52	kkkkkk/xxxxkk:b044E044E044Eюю044E	I
    //   181: iload 4
    //   183: istore_3
    //   184: goto -171 -> 13
    //   187: new 34	java/lang/String
    //   190: dup
    //   191: aload 6
    //   193: invokespecial 55	java/lang/String:<init>	([C)V
    //   196: astore_1
    //   197: aload_1
    //   198: areturn
    //   199: astore_1
    //   200: aload_1
    //   201: athrow
    //   202: astore_1
    //   203: aload_1
    //   204: athrow
    // Local variable table:
    //   start	length	slot	name	signature
    //   0	205	0	this	xxxxkk
    //   0	205	1	paramString	String
    //   0	205	2	paramChar	char
    //   12	172	3	i	int
    //   15	167	4	j	int
    //   93	14	5	k	int
    //   9	183	6	arrayOfChar	char[]
    // Exception table:
    //   from	to	target	type
    //   0	11	199	java/lang/Exception
    //   13	17	199	java/lang/Exception
    //   187	197	202	java/lang/Exception
  }
}

/* Location:
 * Qualified Name:     kkkkkk.xxxxkk
 * Java Class Version: 6 (50.0)
 * JD-Core Version:    0.7.1
 */