package com.google.android.gms.internal;

import android.os.Binder;
import android.os.IBinder;
import android.os.IInterface;
import android.os.Parcel;
import com.google.android.gms.dynamic.zzd;
import com.google.android.gms.dynamic.zzd.zza;

public abstract interface zzbi
  extends IInterface
{
  public abstract void destroy();
  
  public abstract String getMediationAdapterClassName();
  
  public abstract boolean isReady();
  
  public abstract void pause();
  
  public abstract void resume();
  
  public abstract void showInterstitial();
  
  public abstract void stopLoading();
  
  public abstract void zza(zzba paramzzba);
  
  public abstract void zza(zzbg paramzzbg);
  
  public abstract void zza(zzbh paramzzbh);
  
  public abstract void zza(zzbk paramzzbk);
  
  public abstract void zza(zzbl paramzzbl);
  
  public abstract void zza(zzcj paramzzcj);
  
  public abstract void zza(zzfo paramzzfo);
  
  public abstract void zza(zzfs paramzzfs, String paramString);
  
  public abstract boolean zza(zzax paramzzax);
  
  public abstract zzd zzac();
  
  public abstract zzba zzad();
  
  public abstract void zzan();
  
  public static abstract class zza
    extends Binder
    implements zzbi
  {
    public zza()
    {
      attachInterface(this, "com.google.android.gms.ads.internal.client.IAdManager");
    }
    
    public static zzbi zzg(IBinder paramIBinder)
    {
      if (paramIBinder == null) {
        return null;
      }
      IInterface localIInterface = paramIBinder.queryLocalInterface("com.google.android.gms.ads.internal.client.IAdManager");
      if ((localIInterface != null) && ((localIInterface instanceof zzbi))) {
        return (zzbi)localIInterface;
      }
      return new zza(paramIBinder);
    }
    
    public IBinder asBinder()
    {
      return this;
    }
    
    public boolean onTransact(int paramInt1, Parcel paramParcel1, Parcel paramParcel2, int paramInt2)
    {
      zzd localzzd = null;
      Object localObject2 = null;
      Object localObject1 = null;
      int i = 0;
      boolean bool;
      switch (paramInt1)
      {
      default: 
        return super.onTransact(paramInt1, paramParcel1, paramParcel2, paramInt2);
      case 1598968902: 
        paramParcel2.writeString("com.google.android.gms.ads.internal.client.IAdManager");
        return true;
      case 1: 
        paramParcel1.enforceInterface("com.google.android.gms.ads.internal.client.IAdManager");
        localzzd = zzac();
        paramParcel2.writeNoException();
        paramParcel1 = (Parcel)localObject1;
        if (localzzd != null) {
          paramParcel1 = localzzd.asBinder();
        }
        paramParcel2.writeStrongBinder(paramParcel1);
        return true;
      case 2: 
        paramParcel1.enforceInterface("com.google.android.gms.ads.internal.client.IAdManager");
        destroy();
        paramParcel2.writeNoException();
        return true;
      case 3: 
        paramParcel1.enforceInterface("com.google.android.gms.ads.internal.client.IAdManager");
        bool = isReady();
        paramParcel2.writeNoException();
        if (bool) {}
        for (paramInt1 = 1;; paramInt1 = 0)
        {
          paramParcel2.writeInt(paramInt1);
          return true;
        }
      case 4: 
        paramParcel1.enforceInterface("com.google.android.gms.ads.internal.client.IAdManager");
        localObject1 = localzzd;
        if (paramParcel1.readInt() != 0) {
          localObject1 = zzax.CREATOR.zzb(paramParcel1);
        }
        bool = zza((zzax)localObject1);
        paramParcel2.writeNoException();
        paramInt1 = i;
        if (bool) {
          paramInt1 = 1;
        }
        paramParcel2.writeInt(paramInt1);
        return true;
      case 5: 
        paramParcel1.enforceInterface("com.google.android.gms.ads.internal.client.IAdManager");
        pause();
        paramParcel2.writeNoException();
        return true;
      case 6: 
        paramParcel1.enforceInterface("com.google.android.gms.ads.internal.client.IAdManager");
        resume();
        paramParcel2.writeNoException();
        return true;
      case 7: 
        paramParcel1.enforceInterface("com.google.android.gms.ads.internal.client.IAdManager");
        zza(zzbh.zza.zzf(paramParcel1.readStrongBinder()));
        paramParcel2.writeNoException();
        return true;
      case 8: 
        paramParcel1.enforceInterface("com.google.android.gms.ads.internal.client.IAdManager");
        zza(zzbk.zza.zzi(paramParcel1.readStrongBinder()));
        paramParcel2.writeNoException();
        return true;
      case 9: 
        paramParcel1.enforceInterface("com.google.android.gms.ads.internal.client.IAdManager");
        showInterstitial();
        paramParcel2.writeNoException();
        return true;
      case 10: 
        paramParcel1.enforceInterface("com.google.android.gms.ads.internal.client.IAdManager");
        stopLoading();
        paramParcel2.writeNoException();
        return true;
      case 11: 
        paramParcel1.enforceInterface("com.google.android.gms.ads.internal.client.IAdManager");
        zzan();
        paramParcel2.writeNoException();
        return true;
      case 12: 
        paramParcel1.enforceInterface("com.google.android.gms.ads.internal.client.IAdManager");
        paramParcel1 = zzad();
        paramParcel2.writeNoException();
        if (paramParcel1 != null)
        {
          paramParcel2.writeInt(1);
          paramParcel1.writeToParcel(paramParcel2, 1);
          return true;
        }
        paramParcel2.writeInt(0);
        return true;
      case 13: 
        paramParcel1.enforceInterface("com.google.android.gms.ads.internal.client.IAdManager");
        localObject1 = localObject2;
        if (paramParcel1.readInt() != 0) {
          localObject1 = zzba.CREATOR.zzc(paramParcel1);
        }
        zza((zzba)localObject1);
        paramParcel2.writeNoException();
        return true;
      case 14: 
        paramParcel1.enforceInterface("com.google.android.gms.ads.internal.client.IAdManager");
        zza(zzfo.zza.zzz(paramParcel1.readStrongBinder()));
        paramParcel2.writeNoException();
        return true;
      case 15: 
        paramParcel1.enforceInterface("com.google.android.gms.ads.internal.client.IAdManager");
        zza(zzfs.zza.zzD(paramParcel1.readStrongBinder()), paramParcel1.readString());
        paramParcel2.writeNoException();
        return true;
      case 18: 
        paramParcel1.enforceInterface("com.google.android.gms.ads.internal.client.IAdManager");
        paramParcel1 = getMediationAdapterClassName();
        paramParcel2.writeNoException();
        paramParcel2.writeString(paramParcel1);
        return true;
      case 19: 
        paramParcel1.enforceInterface("com.google.android.gms.ads.internal.client.IAdManager");
        zza(zzcj.zza.zzn(paramParcel1.readStrongBinder()));
        paramParcel2.writeNoException();
        return true;
      case 20: 
        paramParcel1.enforceInterface("com.google.android.gms.ads.internal.client.IAdManager");
        zza(zzbg.zza.zze(paramParcel1.readStrongBinder()));
        paramParcel2.writeNoException();
        return true;
      }
      paramParcel1.enforceInterface("com.google.android.gms.ads.internal.client.IAdManager");
      zza(zzbl.zza.zzj(paramParcel1.readStrongBinder()));
      paramParcel2.writeNoException();
      return true;
    }
    
    static class zza
      implements zzbi
    {
      private IBinder zzle;
      
      zza(IBinder paramIBinder)
      {
        zzle = paramIBinder;
      }
      
      public IBinder asBinder()
      {
        return zzle;
      }
      
      public void destroy()
      {
        Parcel localParcel1 = Parcel.obtain();
        Parcel localParcel2 = Parcel.obtain();
        try
        {
          localParcel1.writeInterfaceToken("com.google.android.gms.ads.internal.client.IAdManager");
          zzle.transact(2, localParcel1, localParcel2, 0);
          localParcel2.readException();
          return;
        }
        finally
        {
          localParcel2.recycle();
          localParcel1.recycle();
        }
      }
      
      public String getMediationAdapterClassName()
      {
        Parcel localParcel1 = Parcel.obtain();
        Parcel localParcel2 = Parcel.obtain();
        try
        {
          localParcel1.writeInterfaceToken("com.google.android.gms.ads.internal.client.IAdManager");
          zzle.transact(18, localParcel1, localParcel2, 0);
          localParcel2.readException();
          String str = localParcel2.readString();
          return str;
        }
        finally
        {
          localParcel2.recycle();
          localParcel1.recycle();
        }
      }
      
      public boolean isReady()
      {
        boolean bool = false;
        Parcel localParcel1 = Parcel.obtain();
        Parcel localParcel2 = Parcel.obtain();
        try
        {
          localParcel1.writeInterfaceToken("com.google.android.gms.ads.internal.client.IAdManager");
          zzle.transact(3, localParcel1, localParcel2, 0);
          localParcel2.readException();
          int i = localParcel2.readInt();
          if (i != 0) {
            bool = true;
          }
          return bool;
        }
        finally
        {
          localParcel2.recycle();
          localParcel1.recycle();
        }
      }
      
      public void pause()
      {
        Parcel localParcel1 = Parcel.obtain();
        Parcel localParcel2 = Parcel.obtain();
        try
        {
          localParcel1.writeInterfaceToken("com.google.android.gms.ads.internal.client.IAdManager");
          zzle.transact(5, localParcel1, localParcel2, 0);
          localParcel2.readException();
          return;
        }
        finally
        {
          localParcel2.recycle();
          localParcel1.recycle();
        }
      }
      
      public void resume()
      {
        Parcel localParcel1 = Parcel.obtain();
        Parcel localParcel2 = Parcel.obtain();
        try
        {
          localParcel1.writeInterfaceToken("com.google.android.gms.ads.internal.client.IAdManager");
          zzle.transact(6, localParcel1, localParcel2, 0);
          localParcel2.readException();
          return;
        }
        finally
        {
          localParcel2.recycle();
          localParcel1.recycle();
        }
      }
      
      public void showInterstitial()
      {
        Parcel localParcel1 = Parcel.obtain();
        Parcel localParcel2 = Parcel.obtain();
        try
        {
          localParcel1.writeInterfaceToken("com.google.android.gms.ads.internal.client.IAdManager");
          zzle.transact(9, localParcel1, localParcel2, 0);
          localParcel2.readException();
          return;
        }
        finally
        {
          localParcel2.recycle();
          localParcel1.recycle();
        }
      }
      
      public void stopLoading()
      {
        Parcel localParcel1 = Parcel.obtain();
        Parcel localParcel2 = Parcel.obtain();
        try
        {
          localParcel1.writeInterfaceToken("com.google.android.gms.ads.internal.client.IAdManager");
          zzle.transact(10, localParcel1, localParcel2, 0);
          localParcel2.readException();
          return;
        }
        finally
        {
          localParcel2.recycle();
          localParcel1.recycle();
        }
      }
      
      /* Error */
      public void zza(zzba paramzzba)
      {
        // Byte code:
        //   0: invokestatic 28	android/os/Parcel:obtain	()Landroid/os/Parcel;
        //   3: astore_2
        //   4: invokestatic 28	android/os/Parcel:obtain	()Landroid/os/Parcel;
        //   7: astore_3
        //   8: aload_2
        //   9: ldc 30
        //   11: invokevirtual 34	android/os/Parcel:writeInterfaceToken	(Ljava/lang/String;)V
        //   14: aload_1
        //   15: ifnull +42 -> 57
        //   18: aload_2
        //   19: iconst_1
        //   20: invokevirtual 66	android/os/Parcel:writeInt	(I)V
        //   23: aload_1
        //   24: aload_2
        //   25: iconst_0
        //   26: invokevirtual 72	com/google/android/gms/internal/zzba:writeToParcel	(Landroid/os/Parcel;I)V
        //   29: aload_0
        //   30: getfield 18	com/google/android/gms/internal/zzbi$zza$zza:zzle	Landroid/os/IBinder;
        //   33: bipush 13
        //   35: aload_2
        //   36: aload_3
        //   37: iconst_0
        //   38: invokeinterface 40 5 0
        //   43: pop
        //   44: aload_3
        //   45: invokevirtual 43	android/os/Parcel:readException	()V
        //   48: aload_3
        //   49: invokevirtual 46	android/os/Parcel:recycle	()V
        //   52: aload_2
        //   53: invokevirtual 46	android/os/Parcel:recycle	()V
        //   56: return
        //   57: aload_2
        //   58: iconst_0
        //   59: invokevirtual 66	android/os/Parcel:writeInt	(I)V
        //   62: goto -33 -> 29
        //   65: astore_1
        //   66: aload_3
        //   67: invokevirtual 46	android/os/Parcel:recycle	()V
        //   70: aload_2
        //   71: invokevirtual 46	android/os/Parcel:recycle	()V
        //   74: aload_1
        //   75: athrow
        // Local variable table:
        //   start	length	slot	name	signature
        //   0	76	0	this	zza
        //   0	76	1	paramzzba	zzba
        //   3	68	2	localParcel1	Parcel
        //   7	60	3	localParcel2	Parcel
        // Exception table:
        //   from	to	target	type
        //   8	14	65	finally
        //   18	29	65	finally
        //   29	48	65	finally
        //   57	62	65	finally
      }
      
      /* Error */
      public void zza(zzbg paramzzbg)
      {
        // Byte code:
        //   0: invokestatic 28	android/os/Parcel:obtain	()Landroid/os/Parcel;
        //   3: astore_2
        //   4: invokestatic 28	android/os/Parcel:obtain	()Landroid/os/Parcel;
        //   7: astore_3
        //   8: aload_2
        //   9: ldc 30
        //   11: invokevirtual 34	android/os/Parcel:writeInterfaceToken	(Ljava/lang/String;)V
        //   14: aload_1
        //   15: ifnull +43 -> 58
        //   18: aload_1
        //   19: invokeinterface 77 1 0
        //   24: astore_1
        //   25: aload_2
        //   26: aload_1
        //   27: invokevirtual 80	android/os/Parcel:writeStrongBinder	(Landroid/os/IBinder;)V
        //   30: aload_0
        //   31: getfield 18	com/google/android/gms/internal/zzbi$zza$zza:zzle	Landroid/os/IBinder;
        //   34: bipush 20
        //   36: aload_2
        //   37: aload_3
        //   38: iconst_0
        //   39: invokeinterface 40 5 0
        //   44: pop
        //   45: aload_3
        //   46: invokevirtual 43	android/os/Parcel:readException	()V
        //   49: aload_3
        //   50: invokevirtual 46	android/os/Parcel:recycle	()V
        //   53: aload_2
        //   54: invokevirtual 46	android/os/Parcel:recycle	()V
        //   57: return
        //   58: aconst_null
        //   59: astore_1
        //   60: goto -35 -> 25
        //   63: astore_1
        //   64: aload_3
        //   65: invokevirtual 46	android/os/Parcel:recycle	()V
        //   68: aload_2
        //   69: invokevirtual 46	android/os/Parcel:recycle	()V
        //   72: aload_1
        //   73: athrow
        // Local variable table:
        //   start	length	slot	name	signature
        //   0	74	0	this	zza
        //   0	74	1	paramzzbg	zzbg
        //   3	66	2	localParcel1	Parcel
        //   7	58	3	localParcel2	Parcel
        // Exception table:
        //   from	to	target	type
        //   8	14	63	finally
        //   18	25	63	finally
        //   25	49	63	finally
      }
      
      /* Error */
      public void zza(zzbh paramzzbh)
      {
        // Byte code:
        //   0: invokestatic 28	android/os/Parcel:obtain	()Landroid/os/Parcel;
        //   3: astore_2
        //   4: invokestatic 28	android/os/Parcel:obtain	()Landroid/os/Parcel;
        //   7: astore_3
        //   8: aload_2
        //   9: ldc 30
        //   11: invokevirtual 34	android/os/Parcel:writeInterfaceToken	(Ljava/lang/String;)V
        //   14: aload_1
        //   15: ifnull +43 -> 58
        //   18: aload_1
        //   19: invokeinterface 84 1 0
        //   24: astore_1
        //   25: aload_2
        //   26: aload_1
        //   27: invokevirtual 80	android/os/Parcel:writeStrongBinder	(Landroid/os/IBinder;)V
        //   30: aload_0
        //   31: getfield 18	com/google/android/gms/internal/zzbi$zza$zza:zzle	Landroid/os/IBinder;
        //   34: bipush 7
        //   36: aload_2
        //   37: aload_3
        //   38: iconst_0
        //   39: invokeinterface 40 5 0
        //   44: pop
        //   45: aload_3
        //   46: invokevirtual 43	android/os/Parcel:readException	()V
        //   49: aload_3
        //   50: invokevirtual 46	android/os/Parcel:recycle	()V
        //   53: aload_2
        //   54: invokevirtual 46	android/os/Parcel:recycle	()V
        //   57: return
        //   58: aconst_null
        //   59: astore_1
        //   60: goto -35 -> 25
        //   63: astore_1
        //   64: aload_3
        //   65: invokevirtual 46	android/os/Parcel:recycle	()V
        //   68: aload_2
        //   69: invokevirtual 46	android/os/Parcel:recycle	()V
        //   72: aload_1
        //   73: athrow
        // Local variable table:
        //   start	length	slot	name	signature
        //   0	74	0	this	zza
        //   0	74	1	paramzzbh	zzbh
        //   3	66	2	localParcel1	Parcel
        //   7	58	3	localParcel2	Parcel
        // Exception table:
        //   from	to	target	type
        //   8	14	63	finally
        //   18	25	63	finally
        //   25	49	63	finally
      }
      
      /* Error */
      public void zza(zzbk paramzzbk)
      {
        // Byte code:
        //   0: invokestatic 28	android/os/Parcel:obtain	()Landroid/os/Parcel;
        //   3: astore_2
        //   4: invokestatic 28	android/os/Parcel:obtain	()Landroid/os/Parcel;
        //   7: astore_3
        //   8: aload_2
        //   9: ldc 30
        //   11: invokevirtual 34	android/os/Parcel:writeInterfaceToken	(Ljava/lang/String;)V
        //   14: aload_1
        //   15: ifnull +43 -> 58
        //   18: aload_1
        //   19: invokeinterface 88 1 0
        //   24: astore_1
        //   25: aload_2
        //   26: aload_1
        //   27: invokevirtual 80	android/os/Parcel:writeStrongBinder	(Landroid/os/IBinder;)V
        //   30: aload_0
        //   31: getfield 18	com/google/android/gms/internal/zzbi$zza$zza:zzle	Landroid/os/IBinder;
        //   34: bipush 8
        //   36: aload_2
        //   37: aload_3
        //   38: iconst_0
        //   39: invokeinterface 40 5 0
        //   44: pop
        //   45: aload_3
        //   46: invokevirtual 43	android/os/Parcel:readException	()V
        //   49: aload_3
        //   50: invokevirtual 46	android/os/Parcel:recycle	()V
        //   53: aload_2
        //   54: invokevirtual 46	android/os/Parcel:recycle	()V
        //   57: return
        //   58: aconst_null
        //   59: astore_1
        //   60: goto -35 -> 25
        //   63: astore_1
        //   64: aload_3
        //   65: invokevirtual 46	android/os/Parcel:recycle	()V
        //   68: aload_2
        //   69: invokevirtual 46	android/os/Parcel:recycle	()V
        //   72: aload_1
        //   73: athrow
        // Local variable table:
        //   start	length	slot	name	signature
        //   0	74	0	this	zza
        //   0	74	1	paramzzbk	zzbk
        //   3	66	2	localParcel1	Parcel
        //   7	58	3	localParcel2	Parcel
        // Exception table:
        //   from	to	target	type
        //   8	14	63	finally
        //   18	25	63	finally
        //   25	49	63	finally
      }
      
      /* Error */
      public void zza(zzbl paramzzbl)
      {
        // Byte code:
        //   0: invokestatic 28	android/os/Parcel:obtain	()Landroid/os/Parcel;
        //   3: astore_2
        //   4: invokestatic 28	android/os/Parcel:obtain	()Landroid/os/Parcel;
        //   7: astore_3
        //   8: aload_2
        //   9: ldc 30
        //   11: invokevirtual 34	android/os/Parcel:writeInterfaceToken	(Ljava/lang/String;)V
        //   14: aload_1
        //   15: ifnull +43 -> 58
        //   18: aload_1
        //   19: invokeinterface 92 1 0
        //   24: astore_1
        //   25: aload_2
        //   26: aload_1
        //   27: invokevirtual 80	android/os/Parcel:writeStrongBinder	(Landroid/os/IBinder;)V
        //   30: aload_0
        //   31: getfield 18	com/google/android/gms/internal/zzbi$zza$zza:zzle	Landroid/os/IBinder;
        //   34: bipush 21
        //   36: aload_2
        //   37: aload_3
        //   38: iconst_0
        //   39: invokeinterface 40 5 0
        //   44: pop
        //   45: aload_3
        //   46: invokevirtual 43	android/os/Parcel:readException	()V
        //   49: aload_3
        //   50: invokevirtual 46	android/os/Parcel:recycle	()V
        //   53: aload_2
        //   54: invokevirtual 46	android/os/Parcel:recycle	()V
        //   57: return
        //   58: aconst_null
        //   59: astore_1
        //   60: goto -35 -> 25
        //   63: astore_1
        //   64: aload_3
        //   65: invokevirtual 46	android/os/Parcel:recycle	()V
        //   68: aload_2
        //   69: invokevirtual 46	android/os/Parcel:recycle	()V
        //   72: aload_1
        //   73: athrow
        // Local variable table:
        //   start	length	slot	name	signature
        //   0	74	0	this	zza
        //   0	74	1	paramzzbl	zzbl
        //   3	66	2	localParcel1	Parcel
        //   7	58	3	localParcel2	Parcel
        // Exception table:
        //   from	to	target	type
        //   8	14	63	finally
        //   18	25	63	finally
        //   25	49	63	finally
      }
      
      /* Error */
      public void zza(zzcj paramzzcj)
      {
        // Byte code:
        //   0: invokestatic 28	android/os/Parcel:obtain	()Landroid/os/Parcel;
        //   3: astore_2
        //   4: invokestatic 28	android/os/Parcel:obtain	()Landroid/os/Parcel;
        //   7: astore_3
        //   8: aload_2
        //   9: ldc 30
        //   11: invokevirtual 34	android/os/Parcel:writeInterfaceToken	(Ljava/lang/String;)V
        //   14: aload_1
        //   15: ifnull +43 -> 58
        //   18: aload_1
        //   19: invokeinterface 96 1 0
        //   24: astore_1
        //   25: aload_2
        //   26: aload_1
        //   27: invokevirtual 80	android/os/Parcel:writeStrongBinder	(Landroid/os/IBinder;)V
        //   30: aload_0
        //   31: getfield 18	com/google/android/gms/internal/zzbi$zza$zza:zzle	Landroid/os/IBinder;
        //   34: bipush 19
        //   36: aload_2
        //   37: aload_3
        //   38: iconst_0
        //   39: invokeinterface 40 5 0
        //   44: pop
        //   45: aload_3
        //   46: invokevirtual 43	android/os/Parcel:readException	()V
        //   49: aload_3
        //   50: invokevirtual 46	android/os/Parcel:recycle	()V
        //   53: aload_2
        //   54: invokevirtual 46	android/os/Parcel:recycle	()V
        //   57: return
        //   58: aconst_null
        //   59: astore_1
        //   60: goto -35 -> 25
        //   63: astore_1
        //   64: aload_3
        //   65: invokevirtual 46	android/os/Parcel:recycle	()V
        //   68: aload_2
        //   69: invokevirtual 46	android/os/Parcel:recycle	()V
        //   72: aload_1
        //   73: athrow
        // Local variable table:
        //   start	length	slot	name	signature
        //   0	74	0	this	zza
        //   0	74	1	paramzzcj	zzcj
        //   3	66	2	localParcel1	Parcel
        //   7	58	3	localParcel2	Parcel
        // Exception table:
        //   from	to	target	type
        //   8	14	63	finally
        //   18	25	63	finally
        //   25	49	63	finally
      }
      
      /* Error */
      public void zza(zzfo paramzzfo)
      {
        // Byte code:
        //   0: invokestatic 28	android/os/Parcel:obtain	()Landroid/os/Parcel;
        //   3: astore_2
        //   4: invokestatic 28	android/os/Parcel:obtain	()Landroid/os/Parcel;
        //   7: astore_3
        //   8: aload_2
        //   9: ldc 30
        //   11: invokevirtual 34	android/os/Parcel:writeInterfaceToken	(Ljava/lang/String;)V
        //   14: aload_1
        //   15: ifnull +43 -> 58
        //   18: aload_1
        //   19: invokeinterface 100 1 0
        //   24: astore_1
        //   25: aload_2
        //   26: aload_1
        //   27: invokevirtual 80	android/os/Parcel:writeStrongBinder	(Landroid/os/IBinder;)V
        //   30: aload_0
        //   31: getfield 18	com/google/android/gms/internal/zzbi$zza$zza:zzle	Landroid/os/IBinder;
        //   34: bipush 14
        //   36: aload_2
        //   37: aload_3
        //   38: iconst_0
        //   39: invokeinterface 40 5 0
        //   44: pop
        //   45: aload_3
        //   46: invokevirtual 43	android/os/Parcel:readException	()V
        //   49: aload_3
        //   50: invokevirtual 46	android/os/Parcel:recycle	()V
        //   53: aload_2
        //   54: invokevirtual 46	android/os/Parcel:recycle	()V
        //   57: return
        //   58: aconst_null
        //   59: astore_1
        //   60: goto -35 -> 25
        //   63: astore_1
        //   64: aload_3
        //   65: invokevirtual 46	android/os/Parcel:recycle	()V
        //   68: aload_2
        //   69: invokevirtual 46	android/os/Parcel:recycle	()V
        //   72: aload_1
        //   73: athrow
        // Local variable table:
        //   start	length	slot	name	signature
        //   0	74	0	this	zza
        //   0	74	1	paramzzfo	zzfo
        //   3	66	2	localParcel1	Parcel
        //   7	58	3	localParcel2	Parcel
        // Exception table:
        //   from	to	target	type
        //   8	14	63	finally
        //   18	25	63	finally
        //   25	49	63	finally
      }
      
      /* Error */
      public void zza(zzfs paramzzfs, String paramString)
      {
        // Byte code:
        //   0: invokestatic 28	android/os/Parcel:obtain	()Landroid/os/Parcel;
        //   3: astore_3
        //   4: invokestatic 28	android/os/Parcel:obtain	()Landroid/os/Parcel;
        //   7: astore 4
        //   9: aload_3
        //   10: ldc 30
        //   12: invokevirtual 34	android/os/Parcel:writeInterfaceToken	(Ljava/lang/String;)V
        //   15: aload_1
        //   16: ifnull +51 -> 67
        //   19: aload_1
        //   20: invokeinterface 104 1 0
        //   25: astore_1
        //   26: aload_3
        //   27: aload_1
        //   28: invokevirtual 80	android/os/Parcel:writeStrongBinder	(Landroid/os/IBinder;)V
        //   31: aload_3
        //   32: aload_2
        //   33: invokevirtual 107	android/os/Parcel:writeString	(Ljava/lang/String;)V
        //   36: aload_0
        //   37: getfield 18	com/google/android/gms/internal/zzbi$zza$zza:zzle	Landroid/os/IBinder;
        //   40: bipush 15
        //   42: aload_3
        //   43: aload 4
        //   45: iconst_0
        //   46: invokeinterface 40 5 0
        //   51: pop
        //   52: aload 4
        //   54: invokevirtual 43	android/os/Parcel:readException	()V
        //   57: aload 4
        //   59: invokevirtual 46	android/os/Parcel:recycle	()V
        //   62: aload_3
        //   63: invokevirtual 46	android/os/Parcel:recycle	()V
        //   66: return
        //   67: aconst_null
        //   68: astore_1
        //   69: goto -43 -> 26
        //   72: astore_1
        //   73: aload 4
        //   75: invokevirtual 46	android/os/Parcel:recycle	()V
        //   78: aload_3
        //   79: invokevirtual 46	android/os/Parcel:recycle	()V
        //   82: aload_1
        //   83: athrow
        // Local variable table:
        //   start	length	slot	name	signature
        //   0	84	0	this	zza
        //   0	84	1	paramzzfs	zzfs
        //   0	84	2	paramString	String
        //   3	76	3	localParcel1	Parcel
        //   7	67	4	localParcel2	Parcel
        // Exception table:
        //   from	to	target	type
        //   9	15	72	finally
        //   19	26	72	finally
        //   26	57	72	finally
      }
      
      public boolean zza(zzax paramzzax)
      {
        boolean bool = true;
        Parcel localParcel1 = Parcel.obtain();
        Parcel localParcel2 = Parcel.obtain();
        for (;;)
        {
          try
          {
            localParcel1.writeInterfaceToken("com.google.android.gms.ads.internal.client.IAdManager");
            if (paramzzax != null)
            {
              localParcel1.writeInt(1);
              paramzzax.writeToParcel(localParcel1, 0);
              zzle.transact(4, localParcel1, localParcel2, 0);
              localParcel2.readException();
              int i = localParcel2.readInt();
              if (i != 0) {
                return bool;
              }
            }
            else
            {
              localParcel1.writeInt(0);
              continue;
            }
            bool = false;
          }
          finally
          {
            localParcel2.recycle();
            localParcel1.recycle();
          }
        }
      }
      
      public zzd zzac()
      {
        Parcel localParcel1 = Parcel.obtain();
        Parcel localParcel2 = Parcel.obtain();
        try
        {
          localParcel1.writeInterfaceToken("com.google.android.gms.ads.internal.client.IAdManager");
          zzle.transact(1, localParcel1, localParcel2, 0);
          localParcel2.readException();
          zzd localzzd = zzd.zza.zzau(localParcel2.readStrongBinder());
          return localzzd;
        }
        finally
        {
          localParcel2.recycle();
          localParcel1.recycle();
        }
      }
      
      /* Error */
      public zzba zzad()
      {
        // Byte code:
        //   0: invokestatic 28	android/os/Parcel:obtain	()Landroid/os/Parcel;
        //   3: astore_2
        //   4: invokestatic 28	android/os/Parcel:obtain	()Landroid/os/Parcel;
        //   7: astore_3
        //   8: aload_2
        //   9: ldc 30
        //   11: invokevirtual 34	android/os/Parcel:writeInterfaceToken	(Ljava/lang/String;)V
        //   14: aload_0
        //   15: getfield 18	com/google/android/gms/internal/zzbi$zza$zza:zzle	Landroid/os/IBinder;
        //   18: bipush 12
        //   20: aload_2
        //   21: aload_3
        //   22: iconst_0
        //   23: invokeinterface 40 5 0
        //   28: pop
        //   29: aload_3
        //   30: invokevirtual 43	android/os/Parcel:readException	()V
        //   33: aload_3
        //   34: invokevirtual 57	android/os/Parcel:readInt	()I
        //   37: ifeq +21 -> 58
        //   40: getstatic 128	com/google/android/gms/internal/zzba:CREATOR	Lcom/google/android/gms/internal/zzbb;
        //   43: aload_3
        //   44: invokevirtual 134	com/google/android/gms/internal/zzbb:zzc	(Landroid/os/Parcel;)Lcom/google/android/gms/internal/zzba;
        //   47: astore_1
        //   48: aload_3
        //   49: invokevirtual 46	android/os/Parcel:recycle	()V
        //   52: aload_2
        //   53: invokevirtual 46	android/os/Parcel:recycle	()V
        //   56: aload_1
        //   57: areturn
        //   58: aconst_null
        //   59: astore_1
        //   60: goto -12 -> 48
        //   63: astore_1
        //   64: aload_3
        //   65: invokevirtual 46	android/os/Parcel:recycle	()V
        //   68: aload_2
        //   69: invokevirtual 46	android/os/Parcel:recycle	()V
        //   72: aload_1
        //   73: athrow
        // Local variable table:
        //   start	length	slot	name	signature
        //   0	74	0	this	zza
        //   47	13	1	localzzba	zzba
        //   63	10	1	localObject	Object
        //   3	66	2	localParcel1	Parcel
        //   7	58	3	localParcel2	Parcel
        // Exception table:
        //   from	to	target	type
        //   8	48	63	finally
      }
      
      public void zzan()
      {
        Parcel localParcel1 = Parcel.obtain();
        Parcel localParcel2 = Parcel.obtain();
        try
        {
          localParcel1.writeInterfaceToken("com.google.android.gms.ads.internal.client.IAdManager");
          zzle.transact(11, localParcel1, localParcel2, 0);
          localParcel2.readException();
          return;
        }
        finally
        {
          localParcel2.recycle();
          localParcel1.recycle();
        }
      }
    }
  }
}

/* Location:
 * Qualified Name:     com.google.android.gms.internal.zzbi
 * Java Class Version: 6 (50.0)
 * JD-Core Version:    0.7.1
 */