package com.google.android.gms.internal;

import android.os.IBinder;

class zzpv$zza$zza
  implements zzpv
{
  private IBinder zzle;
  
  zzpv$zza$zza(IBinder paramIBinder)
  {
    zzle = paramIBinder;
  }
  
  public IBinder asBinder()
  {
    return zzle;
  }
  
  /* Error */
  public void zzX(com.google.android.gms.common.data.DataHolder paramDataHolder)
  {
    // Byte code:
    //   0: invokestatic 29	android/os/Parcel:obtain	()Landroid/os/Parcel;
    //   3: astore_2
    //   4: aload_2
    //   5: ldc 31
    //   7: invokevirtual 35	android/os/Parcel:writeInterfaceToken	(Ljava/lang/String;)V
    //   10: aload_1
    //   11: ifnull +33 -> 44
    //   14: aload_2
    //   15: iconst_1
    //   16: invokevirtual 39	android/os/Parcel:writeInt	(I)V
    //   19: aload_1
    //   20: aload_2
    //   21: iconst_0
    //   22: invokevirtual 45	com/google/android/gms/common/data/DataHolder:writeToParcel	(Landroid/os/Parcel;I)V
    //   25: aload_0
    //   26: getfield 18	com/google/android/gms/internal/zzpv$zza$zza:zzle	Landroid/os/IBinder;
    //   29: iconst_1
    //   30: aload_2
    //   31: aconst_null
    //   32: iconst_1
    //   33: invokeinterface 51 5 0
    //   38: pop
    //   39: aload_2
    //   40: invokevirtual 54	android/os/Parcel:recycle	()V
    //   43: return
    //   44: aload_2
    //   45: iconst_0
    //   46: invokevirtual 39	android/os/Parcel:writeInt	(I)V
    //   49: goto -24 -> 25
    //   52: astore_1
    //   53: aload_2
    //   54: invokevirtual 54	android/os/Parcel:recycle	()V
    //   57: aload_1
    //   58: athrow
    // Local variable table:
    //   start	length	slot	name	signature
    //   0	59	0	this	zza
    //   0	59	1	paramDataHolder	com.google.android.gms.common.data.DataHolder
    //   3	51	2	localParcel	android.os.Parcel
    // Exception table:
    //   from	to	target	type
    //   4	10	52	finally
    //   14	25	52	finally
    //   25	39	52	finally
    //   44	49	52	finally
  }
  
  /* Error */
  public void zzY(com.google.android.gms.common.data.DataHolder paramDataHolder)
  {
    // Byte code:
    //   0: invokestatic 29	android/os/Parcel:obtain	()Landroid/os/Parcel;
    //   3: astore_2
    //   4: aload_2
    //   5: ldc 31
    //   7: invokevirtual 35	android/os/Parcel:writeInterfaceToken	(Ljava/lang/String;)V
    //   10: aload_1
    //   11: ifnull +33 -> 44
    //   14: aload_2
    //   15: iconst_1
    //   16: invokevirtual 39	android/os/Parcel:writeInt	(I)V
    //   19: aload_1
    //   20: aload_2
    //   21: iconst_0
    //   22: invokevirtual 45	com/google/android/gms/common/data/DataHolder:writeToParcel	(Landroid/os/Parcel;I)V
    //   25: aload_0
    //   26: getfield 18	com/google/android/gms/internal/zzpv$zza$zza:zzle	Landroid/os/IBinder;
    //   29: iconst_2
    //   30: aload_2
    //   31: aconst_null
    //   32: iconst_1
    //   33: invokeinterface 51 5 0
    //   38: pop
    //   39: aload_2
    //   40: invokevirtual 54	android/os/Parcel:recycle	()V
    //   43: return
    //   44: aload_2
    //   45: iconst_0
    //   46: invokevirtual 39	android/os/Parcel:writeInt	(I)V
    //   49: goto -24 -> 25
    //   52: astore_1
    //   53: aload_2
    //   54: invokevirtual 54	android/os/Parcel:recycle	()V
    //   57: aload_1
    //   58: athrow
    // Local variable table:
    //   start	length	slot	name	signature
    //   0	59	0	this	zza
    //   0	59	1	paramDataHolder	com.google.android.gms.common.data.DataHolder
    //   3	51	2	localParcel	android.os.Parcel
    // Exception table:
    //   from	to	target	type
    //   4	10	52	finally
    //   14	25	52	finally
    //   25	39	52	finally
    //   44	49	52	finally
  }
  
  /* Error */
  public void zzZ(com.google.android.gms.common.data.DataHolder paramDataHolder)
  {
    // Byte code:
    //   0: invokestatic 29	android/os/Parcel:obtain	()Landroid/os/Parcel;
    //   3: astore_2
    //   4: aload_2
    //   5: ldc 31
    //   7: invokevirtual 35	android/os/Parcel:writeInterfaceToken	(Ljava/lang/String;)V
    //   10: aload_1
    //   11: ifnull +33 -> 44
    //   14: aload_2
    //   15: iconst_1
    //   16: invokevirtual 39	android/os/Parcel:writeInt	(I)V
    //   19: aload_1
    //   20: aload_2
    //   21: iconst_0
    //   22: invokevirtual 45	com/google/android/gms/common/data/DataHolder:writeToParcel	(Landroid/os/Parcel;I)V
    //   25: aload_0
    //   26: getfield 18	com/google/android/gms/internal/zzpv$zza$zza:zzle	Landroid/os/IBinder;
    //   29: iconst_3
    //   30: aload_2
    //   31: aconst_null
    //   32: iconst_1
    //   33: invokeinterface 51 5 0
    //   38: pop
    //   39: aload_2
    //   40: invokevirtual 54	android/os/Parcel:recycle	()V
    //   43: return
    //   44: aload_2
    //   45: iconst_0
    //   46: invokevirtual 39	android/os/Parcel:writeInt	(I)V
    //   49: goto -24 -> 25
    //   52: astore_1
    //   53: aload_2
    //   54: invokevirtual 54	android/os/Parcel:recycle	()V
    //   57: aload_1
    //   58: athrow
    // Local variable table:
    //   start	length	slot	name	signature
    //   0	59	0	this	zza
    //   0	59	1	paramDataHolder	com.google.android.gms.common.data.DataHolder
    //   3	51	2	localParcel	android.os.Parcel
    // Exception table:
    //   from	to	target	type
    //   4	10	52	finally
    //   14	25	52	finally
    //   25	39	52	finally
    //   44	49	52	finally
  }
  
  /* Error */
  public void zzaa(com.google.android.gms.common.data.DataHolder paramDataHolder)
  {
    // Byte code:
    //   0: invokestatic 29	android/os/Parcel:obtain	()Landroid/os/Parcel;
    //   3: astore_2
    //   4: aload_2
    //   5: ldc 31
    //   7: invokevirtual 35	android/os/Parcel:writeInterfaceToken	(Ljava/lang/String;)V
    //   10: aload_1
    //   11: ifnull +33 -> 44
    //   14: aload_2
    //   15: iconst_1
    //   16: invokevirtual 39	android/os/Parcel:writeInt	(I)V
    //   19: aload_1
    //   20: aload_2
    //   21: iconst_0
    //   22: invokevirtual 45	com/google/android/gms/common/data/DataHolder:writeToParcel	(Landroid/os/Parcel;I)V
    //   25: aload_0
    //   26: getfield 18	com/google/android/gms/internal/zzpv$zza$zza:zzle	Landroid/os/IBinder;
    //   29: iconst_5
    //   30: aload_2
    //   31: aconst_null
    //   32: iconst_1
    //   33: invokeinterface 51 5 0
    //   38: pop
    //   39: aload_2
    //   40: invokevirtual 54	android/os/Parcel:recycle	()V
    //   43: return
    //   44: aload_2
    //   45: iconst_0
    //   46: invokevirtual 39	android/os/Parcel:writeInt	(I)V
    //   49: goto -24 -> 25
    //   52: astore_1
    //   53: aload_2
    //   54: invokevirtual 54	android/os/Parcel:recycle	()V
    //   57: aload_1
    //   58: athrow
    // Local variable table:
    //   start	length	slot	name	signature
    //   0	59	0	this	zza
    //   0	59	1	paramDataHolder	com.google.android.gms.common.data.DataHolder
    //   3	51	2	localParcel	android.os.Parcel
    // Exception table:
    //   from	to	target	type
    //   4	10	52	finally
    //   14	25	52	finally
    //   25	39	52	finally
    //   44	49	52	finally
  }
  
  /* Error */
  public void zzay(com.google.android.gms.common.api.Status paramStatus)
  {
    // Byte code:
    //   0: invokestatic 29	android/os/Parcel:obtain	()Landroid/os/Parcel;
    //   3: astore_2
    //   4: aload_2
    //   5: ldc 31
    //   7: invokevirtual 35	android/os/Parcel:writeInterfaceToken	(Ljava/lang/String;)V
    //   10: aload_1
    //   11: ifnull +33 -> 44
    //   14: aload_2
    //   15: iconst_1
    //   16: invokevirtual 39	android/os/Parcel:writeInt	(I)V
    //   19: aload_1
    //   20: aload_2
    //   21: iconst_0
    //   22: invokevirtual 62	com/google/android/gms/common/api/Status:writeToParcel	(Landroid/os/Parcel;I)V
    //   25: aload_0
    //   26: getfield 18	com/google/android/gms/internal/zzpv$zza$zza:zzle	Landroid/os/IBinder;
    //   29: iconst_4
    //   30: aload_2
    //   31: aconst_null
    //   32: iconst_1
    //   33: invokeinterface 51 5 0
    //   38: pop
    //   39: aload_2
    //   40: invokevirtual 54	android/os/Parcel:recycle	()V
    //   43: return
    //   44: aload_2
    //   45: iconst_0
    //   46: invokevirtual 39	android/os/Parcel:writeInt	(I)V
    //   49: goto -24 -> 25
    //   52: astore_1
    //   53: aload_2
    //   54: invokevirtual 54	android/os/Parcel:recycle	()V
    //   57: aload_1
    //   58: athrow
    // Local variable table:
    //   start	length	slot	name	signature
    //   0	59	0	this	zza
    //   0	59	1	paramStatus	com.google.android.gms.common.api.Status
    //   3	51	2	localParcel	android.os.Parcel
    // Exception table:
    //   from	to	target	type
    //   4	10	52	finally
    //   14	25	52	finally
    //   25	39	52	finally
    //   44	49	52	finally
  }
}

/* Location:
 * Qualified Name:     com.google.android.gms.internal.zzpv.zza.zza
 * Java Class Version: 6 (50.0)
 * JD-Core Version:    0.7.1
 */